Workbook

Sheet resumo_cx
A2: Saldo Inicial | B2: 0
A3: Vendas | B3: =SUM('01'!C5,'02'!C5,'03'!C5,'04'!C5,'05'!C5,'06'!C5,'07'!C5,'08'!C5,'09'!C5,'10'!C5,'11'!C5,'12'!C5,'13'!C5,'14'!C5,'15'!C5,'16'!C5,'17'!C5,'18'!C5,'19'!C5,'20'!C5,'21'!C5,'22'!C5,'23'!C5,'24'!C5,#REF!,'25'!C5,'27'!C5,'28'!C5,'29'!C5,'30'!C5,'31'!C5) -> #REF!
A4: Entrada | B4: =SUM('01'!C6,'02'!C6,'03'!C6,'04'!C6,'05'!C6,'06'!C6,'07'!C6,'08'!C6,'09'!C6,'10'!C6,'11'!C6,'12'!C6,'13'!C6,'14'!C6,'15'!C6,'16'!C6,'17'!C6,'18'!C6,'19'!C6,'20'!C6,'21'!C6,'22'!C6,'23'!C6,'24'!C6,#REF!,'25'!C6,'27'!C6,'28'!C6,'29'!C6,'30'!C6,'31'!C6) -> #REF!
A5: Despesas | B5: =SUM('01'!C7,'02'!C7,'03'!C7,'04'!C7,'05'!C7,'06'!C7,'07'!C7,'08'!C7,'09'!C7,'10'!C7,'11'!C7,'12'!C7,'13'!C7,'14'!C7,'15'!C7,'16'!C7,'17'!C7,'18'!C7,'19'!C7,'20'!C7,'21'!C7,'22'!C7,'23'!C7,'24'!C7,#REF!,'25'!C7,'27'!C7,'28'!C7,'29'!C7,'30'!C7,'31'!C7) -> #REF!
A6: Entr_Desp | B6: =SUM(B4:B5) -> #REF!
A8: Tipos de Pagtos
A9: DN | B9: =SUM('01'!C11,'02'!C11,'03'!C11,'04'!C11,'05'!C11,'06'!C11,'07'!C11,'08'!C11,'09'!C11,'10'!C11,'11'!C11,'12'!C11,'13'!C11,'14'!C11,'15'!C11,'16'!C11,'17'!C11,'18'!C11,'19'!C11,'20'!C11,'21'!C11,'22'!C11,'23'!C11,'24'!C11,#REF!,'25'!C11,'27'!C11,'28'!C11,'29'!C11,'30'!C11,'31'!C11) -> #REF!
A10: CTD | B10: =SUM('01'!C12,'02'!C12,'03'!C12,'04'!C12,'05'!C12,'06'!C12,'07'!C12,'08'!C12,'09'!C12,'10'!C12,'11'!C12,'12'!C12,'13'!C12,'14'!C12,'15'!C12,'16'!C12,'17'!C12,'18'!C12,'19'!C12,'20'!C12,'21'!C12,'22'!C12,'23'!C12,'24'!C12,#REF!,'25'!C12,'27'!C12,'28'!C12,'29'!C12,'30'!C12,'31'!C12) -> #REF!
A11: CTC | B11: =SUM('01'!C13,'02'!C13,'03'!C13,'04'!C13,'05'!C13,'06'!C13,'07'!C13,'08'!C13,'09'!C13,'10'!C13,'11'!C13,'12'!C13,'13'!C13,'14'!C13,'15'!C13,'16'!C13,'17'!C13,'18'!C13,'19'!C13,'20'!C13,'21'!C13,'22'!C13,'23'!C13,'24'!C13,#REF!,'25'!C13,'27'!C13,'28'!C13,'29'!C13,'30'!C13,'31'!C13) -> #REF!
A12: PCTC | B12: =SUM('01'!C14,'02'!C14,'03'!C14,'04'!C14,'05'!C14,'06'!C14,'07'!C14,'08'!C14,'09'!C14,'10'!C14,'11'!C14,'12'!C14,'13'!C14,'14'!C14,'15'!C14,'16'!C14,'17'!C14,'18'!C14,'19'!C14,'20'!C14,'21'!C14,'22'!C14,'23'!C14,'24'!C14,#REF!,'25'!C14,'27'!C14,'28'!C14,'29'!C14,'30'!C14,'31'!C14) -> #REF!
A13: PIX | B13: =SUM('01'!C15,'02'!C15,'03'!C15,'04'!C15,'05'!C15,'06'!C15,'07'!C15,'08'!C15,'09'!C15,'10'!C15,'11'!C15,'12'!C15,'13'!C15,'14'!C15,'15'!C15,'16'!C15,'17'!C15,'18'!C15,'19'!C15,'20'!C15,'21'!C15,'22'!C15,'23'!C15,'24'!C15,#REF!,'25'!C15,'27'!C15,'28'!C15,'29'!C15,'30'!C15,'31'!C15) -> #REF!
A14: Total | B14: =SUM(B9:B13) -> #REF!
A16: Entrega de Carne
A17: =COUNT(#REF!) -> 0 | B17: =SUM('01'!C19,'02'!C19,'03'!C19,'04'!C19,'05'!C19,'06'!C19,'07'!C19,'08'!C19,'09'!C19,'10'!C19,'11'!C19,'12'!C19,'13'!C19,'14'!C19,'15'!C19,'16'!C19,'17'!C19,'18'!C19,'19'!C19,'20'!C19,'21'!C19,'22'!C19,'23'!C19,'24'!C19,#REF!,'25'!C19,'27'!C19,'28'!C19,'29'!C19,'30'!C19,'31'!C19) -> #REF!
A18: Total | B18: =SUM(B17:B17) -> #REF!

Sheet 01
B1: 45444
B2: Fechamento Diário do Caixa - Escritório
B4: Saldo Inicial | C4: 0 | E4: Vendas | K4: Despesas
B5: Vendas | C5: =SUMIF(I6:I31,">0",H6:H31) -> 2800 | E5: Nº Venda | F5: Cliente | G5: Forma de Pgto | H5: Valor Venda | I5: Entrada | K5: Descrição | L5: Tipo de Pagto | M5: Valor
B6: Entrada | C6: =SUM(I6:I41) -> 900 | E6: 9306 | F6: raphael da silva | G6: CTC | H6: 500 | I6: 500 | R6: =IF(vend1[[#This Row],[Nº Venda]]>1,1,0) -> 1
B7: Despesas | C7: =SUM(M6:M11) -> 0 | E7: 9307 | F7: edneusa aparecida | G7: CTD | H7: 1000 | I7: 100 | R7: =IF(vend1[[#This Row],[Nº Venda]]>1,1,0) -> 1
B8: Total entrada | C8: =SUM(C6:C7) -> 900 | E8: 9308 | F8: jaqueline dos santos | G8: PIX | H8: 1300 | I8: 300 | R8: =IF(vend1[[#This Row],[Nº Venda]]>1,1,0) -> 1
R9: =IF(vend1[[#This Row],[Nº Venda]]>1,1,0) -> 0
B10: Tipos de Pagtos | R10: =IF(vend1[[#This Row],[Nº Venda]]>1,1,0) -> 0
B11: DN | C11: =(SUMIF($G$2:$G$31,B11,$I$2:$I$31))+(SUMIF($G$35:$G$41,B11,$H$35:$H$41)) -> 0 | O11: =IF(C16=0,0,1) -> 1 | R11: =IF(vend1[[#This Row],[Nº Venda]]>1,1,0) -> 0
B12: CTD | C12: =(SUMIF($G$2:$G$31,B12,$I$2:$I$31))+(SUMIF($G$35:$G$41,B12,$H$35:$H$41)) -> 100 | R12: =IF(vend1[[#This Row],[Nº Venda]]>1,1,0) -> 0
B13: CTC | C13: =(SUMIF($G$2:$G$31,B13,$I$2:$I$31))+(SUMIF($G$35:$G$41,B13,$H$35:$H$41)) -> 500 | K13: OS Entregue no Dia | R13: =IF(vend1[[#This Row],[Nº Venda]]>1,1,0) -> 0
B14: PCTC | C14: =(SUMIF($G$2:$G$31,B14,$I$2:$I$31))+(SUMIF($G$35:$G$41,B14,$H$35:$H$41)) -> 0 | K14: OS | L14: Vendedor | M14: CARNE | R14: =IF(vend1[[#This Row],[Nº Venda]]>1,1,0) -> 0
B15: PIX | C15: =(SUMIF($G$2:$G$31,B15,$I$2:$I$31))+(SUMIF($G$35:$G$41,B15,$H$35:$H$41)) -> 300 | K15: 9252 | L15: taty | M15: Não | R15: =IF(vend1[[#This Row],[Nº Venda]]>1,1,0) -> 0
B16: Total | C16: =SUM(C11:C15) -> 900 | K16: 9234 | L16: jocy | M16: Não | R16: =IF(vend1[[#This Row],[Nº Venda]]>1,1,0) -> 0
K17: 9226 | L17: taty | M17: Não | R17: =IF(vend1[[#This Row],[Nº Venda]]>1,1,0) -> 0
B18: Entrega de Carne | K18: 9193 | L18: taty | M18: Sim | R18: =IF(vend1[[#This Row],[Nº Venda]]>1,1,0) -> 0
B19: =COUNT(entr_carn31195[OS]) -> 0 | C19: =SUM(entr_carn31195[Valor Total]) -> 0 | R19: =IF(vend1[[#This Row],[Nº Venda]]>1,1,0) -> 0
B20: Total | C20: =SUM(C19:C19) -> 0 | R20: =IF(vend1[[#This Row],[Nº Venda]]>1,1,0) -> 0
B22: Venda | C22: =C5 -> 2800
E24: Restante Entrada
E25: Nº Venda | F25: Cliente | G25: Forma de Pgto | H25: Valor Venda | I25: Entrada
E33: Recebimento de Carnê | K33: Entrega de Carne
E34: OS | F34: Cliente | G34: Forma de Pgto | H34: Valor Parcela | I34: Nº Parcela | K34: OS | L34: Parcelas | M34: Valor Total
Q40: Total de OS | R40: =SUM(R6:R21) -> 3

Sheet 02
B1: ='01'!B1+1 -> 45445
B2: Fechamento Diário do Caixa
B4: Saldo Inicial | C4: 0 | E4: Vendas | K4: Despesas
B5: Vendas | C5: =SUMIF(I6:I31,">0",H6:H31) -> 0 | E5: Nº Venda | F5: Cliente | G5: Forma de Pgto | H5: Valor Venda | I5: Entrada | K5: Descrição | L5: Tipo de Pagto | M5: Valor
B6: Entrada | C6: =SUM(I6:I41) -> 0 | R6: =IF(vend2[[#This Row],[Nº Venda]]>1,1,0) -> 0
B7: Despesas | C7: =SUM(M6:M11) -> 0 | R7: =IF(vend2[[#This Row],[Nº Venda]]>1,1,0) -> 0
B8: Total entrada | C8: =SUM(C6:C7) -> 0 | R8: =IF(vend2[[#This Row],[Nº Venda]]>1,1,0) -> 0
R9: =IF(vend2[[#This Row],[Nº Venda]]>1,1,0) -> 0
B10: Tipos de Pagtos | R10: =IF(vend2[[#This Row],[Nº Venda]]>1,1,0) -> 0
B11: DN | C11: =(SUMIF($G$2:$G$31,B11,$I$2:$I$31))+(SUMIF($G$35:$G$41,B11,$H$35:$H$41)) -> 0 | O11: =IF(C16=0,0,1) -> 0 | R11: =IF(vend2[[#This Row],[Nº Venda]]>1,1,0) -> 0
B12: CTD | C12: =(SUMIF($G$2:$G$31,B12,$I$2:$I$31))+(SUMIF($G$35:$G$41,B12,$H$35:$H$41)) -> 0 | R12: =IF(vend2[[#This Row],[Nº Venda]]>1,1,0) -> 0
B13: CTC | C13: =(SUMIF($G$2:$G$31,B13,$I$2:$I$31))+(SUMIF($G$35:$G$41,B13,$H$35:$H$41)) -> 0 | K13: OS Entregue no Dia | R13: =IF(vend2[[#This Row],[Nº Venda]]>1,1,0) -> 0
B14: PCTC | C14: =(SUMIF($G$2:$G$31,B14,$I$2:$I$31))+(SUMIF($G$35:$G$41,B14,$H$35:$H$41)) -> 0 | K14: OS | L14: Vendedor | M14: CARNE | R14: =IF(vend2[[#This Row],[Nº Venda]]>1,1,0) -> 0
B15: PIX | C15: =(SUMIF($G$2:$G$31,B15,$I$2:$I$31))+(SUMIF($G$35:$G$41,B15,$H$35:$H$41)) -> 0 | R15: =IF(vend2[[#This Row],[Nº Venda]]>1,1,0) -> 0
B16: Total | C16: =SUM(C11:C15) -> 0 | R16: =IF(vend2[[#This Row],[Nº Venda]]>1,1,0) -> 0
R17: =IF(vend2[[#This Row],[Nº Venda]]>1,1,0) -> 0
B18: Entrega de Carne | R18: =IF(vend2[[#This Row],[Nº Venda]]>1,1,0) -> 0
B19: =COUNT(entr_carn2[OS]) -> 0 | C19: =SUM(entr_carn2[Valor Total]) -> 0 | R19: =IF(vend2[[#This Row],[Nº Venda]]>1,1,0) -> 0
B20: Total | C20: =SUM(C19:C19) -> 0 | R20: =IF(vend2[[#This Row],[Nº Venda]]>1,1,0) -> 0
B22: Venda | C22: =C5 -> 0
E24: Restante Entrada
E25: Nº Venda | F25: Cliente | G25: Forma de Pgto | H25: Valor Venda | I25: Entrada
E33: Recebimento de Carnê | K33: Entrega de Carne
E34: OS | F34: Cliente | G34: Forma de Pgto | H34: Valor Parcela | I34: Nº Parcela | K34: OS | L34: Parcelas | M34: Valor Total | U34: V
Q40: Total de OS | R40: =SUM(R6:R21) -> 0

Sheet 03
B1: ='02'!B1+1 -> 45446
B2: Fechamento Diário do Caixa
B4: Saldo Inicial | C4: 0 | E4: Vendas | K4: Despesas
B5: Vendas | C5: =SUMIF(I6:I31,">0",H6:H31) -> 4400 | E5: Nº Venda | F5: Cliente | G5: Forma de Pgto | H5: Valor Venda | I5: Entrada | K5: Descrição | L5: Tipo de Pagto | M5: Valor
B6: Entrada | C6: =SUM(I6:I41) -> 2550 | E6: 9309 | F6: joao bosco | G6: DN | H6: 1100 | I6: 550 | K6: v.t debora | L6: dn | M6: 10.6 | R6: =IF(vend3[[#This Row],[Nº Venda]]>1,1,0) -> 1
B7: Despesas | C7: =SUM(M6:M11) -> 10.6 | E7: 9310 | F7: paulo da paixão | G7: CTC | H7: 200 | I7: 200 | R7: =IF(vend3[[#This Row],[Nº Venda]]>1,1,0) -> 1
B8: Total entrada | C8: =SUM(C6:C7) -> 2560.6 | E8: 9311 | F8: paulo da paixão | G8: CTC | H8: 600 | I8: 600 | R8: =IF(vend3[[#This Row],[Nº Venda]]>1,1,0) -> 1
E9: 9312 | F9: viviane de fatima | G9: CTC | H9: 180 | I9: 180 | R9: =IF(vend3[[#This Row],[Nº Venda]]>1,1,0) -> 1
B10: Tipos de Pagtos | E10: 9313 | F10: giberto gomes | G10: DN | H10: 2200 | I10: 900 | R10: =IF(vend3[[#This Row],[Nº Venda]]>1,1,0) -> 1
B11: DN | C11: =(SUMIF($G$2:$G$31,B11,$I$2:$I$31))+(SUMIF($G$35:$G$41,B11,$H$35:$H$41)) -> 1450 | E11: 9314 | F11: atalibar ximenes | G11: SS | H11: 35 | O11: =IF(C16=0,0,1) -> 1 | R11: =IF(vend3[[#This Row],[Nº Venda]]>1,1,0) -> 1
B12: CTD | C12: =(SUMIF($G$2:$G$31,B12,$I$2:$I$31))+(SUMIF($G$35:$G$41,B12,$H$35:$H$41)) -> 520 | E12: 9323 | F12: marinete denis dos santos | G12: CTD | H12: 120 | I12: 120 | R12: =IF(vend3[[#This Row],[Nº Venda]]>1,1,0) -> 1
B13: CTC | C13: =(SUMIF($G$2:$G$31,B13,$I$2:$I$31))+(SUMIF($G$35:$G$41,B13,$H$35:$H$41)) -> 980 | K13: OS Entregue no Dia | R13: =IF(vend3[[#This Row],[Nº Venda]]>1,1,0) -> 0
B14: PCTC | C14: =(SUMIF($G$2:$G$31,B14,$I$2:$I$31))+(SUMIF($G$35:$G$41,B14,$H$35:$H$41)) -> 0 | K14: OS | L14: Vendedor | M14: CARNE | R14: =IF(vend3[[#This Row],[Nº Venda]]>1,1,0) -> 0
B15: PIX | C15: =(SUMIF($G$2:$G$31,B15,$I$2:$I$31))+(SUMIF($G$35:$G$41,B15,$H$35:$H$41)) -> 125 | K15: 9353 | L15: guilherme silva | M15: Não | R15: =IF(vend3[[#This Row],[Nº Venda]]>1,1,0) -> 0
B16: Total | C16: =SUM(C11:C15) -> 3075 | R16: =IF(vend3[[#This Row],[Nº Venda]]>1,1,0) -> 0
R17: =IF(vend3[[#This Row],[Nº Venda]]>1,1,0) -> 0
B18: Entrega de Carne | R18: =IF(vend3[[#This Row],[Nº Venda]]>1,1,0) -> 0
B19: =COUNT(entr_carn3[OS]) -> 0 | C19: =SUM(entr_carn3[Valor Total]) -> 0 | R19: =IF(vend3[[#This Row],[Nº Venda]]>1,1,0) -> 0
B20: Total | C20: =SUM(C19:C19) -> 0 | R20: =IF(vend3[[#This Row],[Nº Venda]]>1,1,0) -> 0
B22: Venda | C22: =C5 -> 4400
E24: Restante Entrada
E25: Nº Venda | F25: Cliente | G25: Forma de Pgto | H25: Valor Venda | I25: Entrada
E33: Recebimento de Carnê | K33: Entrega de Carne
E34: OS | F34: Cliente | G34: Forma de Pgto | H34: Valor Parcela | I34: Nº Parcela | K34: OS | L34: Parcelas | M34: Valor Total
E35: 9064 | F35: antonio armando | G35: CTD | H35: 400 | I35: PARC. 1/1
E36: 9068 | F36: fernando joao | G36: PIX | H36: 125 | I36: PARC. 1/7
Q40: Total de OS | R40: =SUM(R6:R21) -> 7

Sheet 04
B1: ='03'!B1+1 -> 45447
B2: Fechamento Diário do Caixa
B4: Saldo Inicial | C4: 0 | E4: Vendas | K4: Despesas
B5: Vendas | C5: =SUMIF(I6:I31,">0",H6:H31) -> 35 | E5: Nº Venda | F5: Cliente | G5: Forma de Pgto | H5: Valor Venda | I5: Entrada | K5: Descrição | L5: Tipo de Pagto | M5: Valor
B6: Entrada | C6: =SUM(I6:I41) -> 35 | E6: 9318 | F6: marilu candido | G6: GARANTIA | R6: =IF(vend4[[#This Row],[Nº Venda]]>1,1,0) -> 1
B7: Despesas | C7: =SUM(M6:M11) -> 0 | E7: 9319 | F7: maria de souza | G7: GARANTIA | R7: =IF(vend4[[#This Row],[Nº Venda]]>1,1,0) -> 1
B8: Total entrada | C8: =SUM(C6:C7) -> 35 | E8: 9320 | F8: jocicreide macedo | G8: GARANTIA | R8: =IF(vend4[[#This Row],[Nº Venda]]>1,1,0) -> 1
R9: =IF(vend4[[#This Row],[Nº Venda]]>1,1,0) -> 0
B10: Tipos de Pagtos | R10: =IF(vend4[[#This Row],[Nº Venda]]>1,1,0) -> 0
B11: DN | C11: =(SUMIF($G$2:$G$31,B11,$I$2:$I$31))+(SUMIF($G$35:$G$45,B11,$H$35:$H$45)) -> 370.17 | O11: =IF(C16=0,0,1) -> 1 | R11: =IF(vend4[[#This Row],[Nº Venda]]>1,1,0) -> 0
B12: CTD | C12: =(SUMIF($G$2:$G$31,B12,$I$2:$I$31))+(SUMIF($G$35:$G$45,B12,$H$35:$H$45)) -> 169.58 | R12: =IF(vend4[[#This Row],[Nº Venda]]>1,1,0) -> 0
B13: CTC | C13: =(SUMIF($G$2:$G$31,B13,$I$2:$I$31))+(SUMIF($G$35:$G$45,B13,$H$35:$H$45)) -> 35 | K13: OS Entregue no Dia | R13: =IF(vend4[[#This Row],[Nº Venda]]>1,1,0) -> 0
B14: PCTC | C14: =(SUMIF($G$2:$G$31,B14,$I$2:$I$31))+(SUMIF($G$35:$G$45,B14,$H$35:$H$45)) -> 0 | K14: OS | L14: Vendedor | M14: CARNE | R14: =IF(vend4[[#This Row],[Nº Venda]]>1,1,0) -> 0
B15: PIX | C15: =(SUMIF($G$2:$G$31,B15,$I$2:$I$31))+(SUMIF($G$35:$G$45,B15,$H$35:$H$45)) -> 0 | K15: 9312 | L15: ariani | M15: Não | R15: =IF(vend4[[#This Row],[Nº Venda]]>1,1,0) -> 0
B16: Total | C16: =SUM(C11:C15) -> 574.75 | K16: 8943 | L16: taty | M16: Sim | R16: =IF(vend4[[#This Row],[Nº Venda]]>1,1,0) -> 0
K17: 9314 | L17: ariani | M17: Não | R17: =IF(vend4[[#This Row],[Nº Venda]]>1,1,0) -> 0
B18: Entrega de Carne | K18: 9249 | L18: taty | M18: Não | R18: =IF(vend4[[#This Row],[Nº Venda]]>1,1,0) -> 0
B19: =COUNT(entr_carn4[OS]) -> 1 | C19: =SUM(entr_carn4[Valor Total]) -> 1800 | K19: 9248 | L19: taty | M19: Não | R19: =IF(vend4[[#This Row],[Nº Venda]]>1,1,0) -> 0
B20: Total | C20: =SUM(C19:C19) -> 1800 | K20: 9247 | L20: taty | R20: =IF(vend4[[#This Row],[Nº Venda]]>1,1,0) -> 0
B22: Venda | C22: =C5 -> 35
E24: Restante Entrada
E25: Nº Venda | F25: Cliente | G25: Forma de Pgto | H25: Valor Venda | I25: Entrada
E26: 9314 | F26: atalibar ximenes | G26: CTC | H26: 35 | I26: 35
E33: Recebimento de Carnê | K33: Entrega de Carne
E34: OS | F34: Cliente | G34: Forma de Pgto | H34: Valor Parcela | I34: Nº Parcela | K34: OS | L34: Parcelas | M34: Valor Total
E35: 8266 | F35: vanderleia viana | G35: CTD | H35: 108.33 | I35: PARC. 5/6 | K35: 8943 | L35: 9 | M35: 1800
E36: 8266 | F36: vanderleia viana | G36: CTD | H36: 108,,33 | I36: PARC. 6/6
E37: 9118 | F37: lilian cristina | G37: DN | H37: 118.75 | I37: PARC. 1/8
E38: 9116 | F38: jose de araujo | G38: DN | H38: 100 | I38: PARC. 1/8
E39: 9116 | F39: jose de araujo | G39: CTD | H39: 61.25 | I39: PARC. 1/8
E40: 8328 | F40: marinalva beserra | G40: DN | H40: 50 | I40: PARC. 5/8 | Q40: Total de OS | R40: =SUM(R6:R21) -> 3
E41: 8999 | F41: marinalva beserra | G41: DN | H41: 60 | I41: PARC. 2/7
E42: 8624 | F42: marinalva beserra | G42: DN | H42: 41.42 | I42: PARC. 4/7

Sheet 05
B1: ='04'!B1+1 -> 45448
B2: Fechamento Diário do Caixa
B4: Saldo Inicial | C4: 0 | E4: Vendas | K4: Despesas
B5: Vendas | C5: =SUMIF(I6:I31,">0",H6:H31) -> 30 | E5: Nº Venda | F5: Cliente | G5: Forma de Pgto | H5: Valor Venda | I5: Entrada | K5: Descrição | L5: Tipo de Pagto | M5: Valor
B6: Entrada | C6: =SUM(I6:I41) -> 30 | E6: 9321 | F6: jose roberto | G6: CTD | H6: 30 | I6: 30 | R6: =IF(vend5[[#This Row],[Nº Venda]]>1,1,0) -> 1
B7: Despesas | C7: =SUM(M6:M11) -> 0 | R7: =IF(vend5[[#This Row],[Nº Venda]]>1,1,0) -> 0
B8: Total entrada | C8: =SUM(C6:C7) -> 30 | R8: =IF(vend5[[#This Row],[Nº Venda]]>1,1,0) -> 0
R9: =IF(vend5[[#This Row],[Nº Venda]]>1,1,0) -> 0
B10: Tipos de Pagtos | R10: =IF(vend5[[#This Row],[Nº Venda]]>1,1,0) -> 0
B11: DN | C11: =(SUMIF($G$2:$G$31,B11,$I$2:$I$31))+(SUMIF($G$35:$G$41,B11,$H$35:$H$41)) -> 192.8 | O11: =IF(C16=0,0,1) -> 1 | R11: =IF(vend5[[#This Row],[Nº Venda]]>1,1,0) -> 0
B12: CTD | C12: =(SUMIF($G$2:$G$31,B12,$I$2:$I$31))+(SUMIF($G$35:$G$41,B12,$H$35:$H$41)) -> 136.25 | R12: =IF(vend5[[#This Row],[Nº Venda]]>1,1,0) -> 0
B13: CTC | C13: =(SUMIF($G$2:$G$31,B13,$I$2:$I$31))+(SUMIF($G$35:$G$41,B13,$H$35:$H$41)) -> 0 | K13: OS Entregue no Dia | R13: =IF(vend5[[#This Row],[Nº Venda]]>1,1,0) -> 0
B14: PCTC | C14: =(SUMIF($G$2:$G$31,B14,$I$2:$I$31))+(SUMIF($G$35:$G$41,B14,$H$35:$H$41)) -> 0 | K14: OS | L14: Vendedor | M14: CARNE | Q14: =IF(vend5[[#This Row],[Nº Venda]]>1,1,0) -> 0
B15: PIX | C15: =(SUMIF($G$2:$G$31,B15,$I$2:$I$31))+(SUMIF($G$35:$G$41,B15,$H$35:$H$41)) -> 92.85 | K15: 9280 | L15: ariani | M15: Não | Q15: =IF(vend5[[#This Row],[Nº Venda]]>1,1,0) -> 0
B16: Total | C16: =SUM(C11:C15) -> 421.9 | K16: 9129 | L16: garantia | M16: Não | Q16: =IF(vend5[[#This Row],[Nº Venda]]>1,1,0) -> 0
K17: 8966 | L17: garantia | M17: Não | Q17: =IF(vend5[[#This Row],[Nº Venda]]>1,1,0) -> 0
B18: Entrega de Carne | K18: 9273 | L18: ariani | M18: Não | Q18: =IF(vend5[[#This Row],[Nº Venda]]>1,1,0) -> 0
B19: =COUNT(entr_carn5[OS]) -> 0 | C19: =SUM(entr_carn5[Valor Total]) -> 0 | Q19: =IF(vend5[[#This Row],[Nº Venda]]>1,1,0) -> 0
B20: Total | C20: =SUM(C19:C19) -> 0 | Q20: =IF(vend5[[#This Row],[Nº Venda]]>1,1,0) -> 0
B22: Venda | C22: =C5 -> 30
E24: Restante Entrada
E25: Nº Venda | F25: Cliente | G25: Forma de Pgto | H25: Valor Venda | I25: Entrada
E33: Recebimento de Carnê | K33: Entrega de Carne
E34: OS | F34: Cliente | G34: Forma de Pgto | H34: Valor Parcela | I34: Nº Parcela | K34: OS | L34: Parcelas | M34: Valor Total
E35: 8563 | F35: fernanda aparecida | G35: DN | H35: 142.8 | I35: PARC. 5/5
E36: 8907 | F36: jose carlos furnielles | G36: DN | H36: 50 | I36: PARC. 2/4
E37: 9285 | F37: hellen vitoria | G37: PIX | H37: 92.85 | I37: PARC. 4/7
E38: 8619 | F38: carlos aparecido | G38: CTD | H38: 106.25 | I38: PARC. 3/8
Q40: Total de OS | R40: =SUM(R6:R21) -> 1

Sheet 06
B1: ='05'!B1+1 -> 45449
B2: Fechamento Diário do Caixa
B4: Saldo Inicial | C4: 0 | E4: Vendas | K4: Despesas
B5: Vendas | C5: =SUMIF(I6:I31,">0",H6:H31) -> 200 | E5: Nº Venda | F5: Cliente | G5: Forma de Pgto | H5: Valor Venda | I5: Entrada | K5: Descrição | L5: Tipo de Pagto | M5: Valor
B6: Entrada | C6: =SUM(I6:I41) -> 118.5 | E6: 9322 | F6: katia maria | G6: GARANTIA | R6: =IF(vend[[#This Row],[Nº Venda]]>1,1,0) -> 1
B7: Despesas | C7: =SUM(M6:M11) -> 0 | E7: 9384 | F7: marilu candida | G7: DN | H7: 200 | I7: 18.5 | R7: =IF(vend[[#This Row],[Nº Venda]]>1,1,0) -> 1
B8: Total entrada | C8: =SUM(C6:C7) -> 118.5 | R8: =IF(vend[[#This Row],[Nº Venda]]>1,1,0) -> 0
R9: =IF(vend[[#This Row],[Nº Venda]]>1,1,0) -> 0
B10: Tipos de Pagtos | R10: =IF(vend[[#This Row],[Nº Venda]]>1,1,0) -> 0
B11: DN | C11: =(SUMIF($G$2:$G$31,B11,$I$2:$I$31))+(SUMIF($G$35:$G$41,B11,$H$35:$H$41)) -> 209.5 | O11: =IF(C16=0,0,1) -> 1 | R11: =IF(vend[[#This Row],[Nº Venda]]>1,1,0) -> 0
B12: CTD | C12: =(SUMIF($G$2:$G$31,B12,$I$2:$I$31))+(SUMIF($G$35:$G$41,B12,$H$35:$H$41)) -> 0 | R12: =IF(vend[[#This Row],[Nº Venda]]>1,1,0) -> 0
B13: CTC | C13: =(SUMIF($G$2:$G$31,B13,$I$2:$I$31))+(SUMIF($G$35:$G$41,B13,$H$35:$H$41)) -> 0 | K13: OS Entregue no Dia | R13: =IF(vend[[#This Row],[Nº Venda]]>1,1,0) -> 0
B14: PCTC | C14: =(SUMIF($G$2:$G$31,B14,$I$2:$I$31))+(SUMIF($G$35:$G$41,B14,$H$35:$H$41)) -> 0 | K14: OS | L14: Vendedor | M14: CARNE | R14: =IF(vend[[#This Row],[Nº Venda]]>1,1,0) -> 0
B15: PIX | C15: =(SUMIF($G$2:$G$31,B15,$I$2:$I$31))+(SUMIF($G$35:$G$41,B15,$H$35:$H$41)) -> 427.85 | K15: 9012 | L15: taty | M15: Sim | R15: =IF(vend[[#This Row],[Nº Venda]]>1,1,0) -> 0
B16: Total | C16: =SUM(C11:C15) -> 637.35 | K16: 8814 | L16: taty | M16: Sim | R16: =IF(vend[[#This Row],[Nº Venda]]>1,1,0) -> 0
R17: =IF(vend[[#This Row],[Nº Venda]]>1,1,0) -> 0
B18: Entrega de Carne | R18: =IF(vend[[#This Row],[Nº Venda]]>1,1,0) -> 0
B19: =COUNT(entr_carn6[OS]) -> 2 | C19: =SUM(entr_carn6[Valor Total]) -> 2234 | R19: =IF(vend[[#This Row],[Nº Venda]]>1,1,0) -> 0
B20: Total | C20: =SUM(C19:C19) -> 2234 | R20: =IF(vend[[#This Row],[Nº Venda]]>1,1,0) -> 0
B22: Venda | C22: =C5 -> 200
E24: Restante Entrada
E25: Nº Venda | F25: Cliente | G25: Forma de Pgto | H25: Valor Venda | I25: Entrada
E26: 8814 | F26: mirian de souza | G26: DN | I26: 100
E33: Recebimento de Carnê | K33: Entrega de Carne
E34: OS | F34: Cliente | G34: Forma de Pgto | H34: Valor Parcela | I34: Nº Parcela | K34: OS | L34: Parcelas | M34: Valor Total
E35: 7675 | F35: camila andrade | G35: PIX | H35: 325 | I35: PARC. 7/8 | K35: 9012 | L35: 8 | M35: 1800
E36: 8850 | F36: delcira vieira | G36: DN | H36: 91 | I36: PARC. 2/2 | K36: 8814 | L36: 4 | M36: 434
E37: 8847 | F37: jose santos | G37: PIX | H37: 102.85 | I37: PARC. 2/7
Q40: Total de OS | R40: =SUM(R6:R21) -> 2

Sheet 07
B1: ='06'!B1+1 -> 45450
B2: Fechamento Diário do Caixa
B4: Saldo Inicial | C4: 0 | E4: Vendas | K4: Despesas | U4: 0
B5: Vendas | C5: =SUMIF(I6:I31,">0",H6:H31) -> 2985 | E5: Nº Venda | F5: Cliente | G5: Forma de Pgto | H5: Valor Venda | I5: Entrada | K5: Descrição | L5: Tipo de Pagto | M5: Valor
B6: Entrada | C6: =SUM(I6:I41) -> 3095 | E6: 9324 | F6: massae yonamine | G6: CTD | H6: 780 | I6: 100 | R6: =IF(vend7[[#This Row],[Nº Venda]]>1,1,0) -> 1
B7: Despesas | C7: =SUM(M6:M11) -> 0 | E7: 9326 | F7: maria jose | G7: CTD | H7: 2015 | I7: 2015 | R7: =IF(vend7[[#This Row],[Nº Venda]]>1,1,0) -> 1
B8: Total entrada | C8: =SUM(C6:C7) -> 3095 | E8: 9327 | F8: maria jose | G8: CTD | H8: 190 | I8: 190 | R8: =IF(vend7[[#This Row],[Nº Venda]]>1,1,0) -> 1
E9: 9328 | F9: rosemeire | G9: GARANTIA | R9: =IF(vend7[[#This Row],[Nº Venda]]>1,1,0) -> 1
B10: Tipos de Pagtos | R10: =IF(vend7[[#This Row],[Nº Venda]]>1,1,0) -> 0
B11: DN | C11: =(SUMIF($G$2:$G$31,B11,$I$2:$I$31))+(SUMIF($G$35:$G$41,B11,$H$35:$H$41)) -> 620 | O11: =IF(C16=0,0,1) -> 1 | R11: =IF(vend7[[#This Row],[Nº Venda]]>1,1,0) -> 0
B12: CTD | C12: =(SUMIF($G$2:$G$31,B12,$I$2:$I$31))+(SUMIF($G$35:$G$41,B12,$H$35:$H$41)) -> 2675 | R12: =IF(vend7[[#This Row],[Nº Venda]]>1,1,0) -> 0
B13: CTC | C13: =(SUMIF($G$2:$G$31,B13,$I$2:$I$31))+(SUMIF($G$35:$G$41,B13,$H$35:$H$41)) -> 0 | K13: OS Entregue no Dia | R13: =IF(vend7[[#This Row],[Nº Venda]]>1,1,0) -> 0
B14: PCTC | C14: =(SUMIF($G$2:$G$31,B14,$I$2:$I$31))+(SUMIF($G$35:$G$41,B14,$H$35:$H$41)) -> 0 | K14: OS | L14: Vendedor | M14: CARNE | R14: =IF(vend7[[#This Row],[Nº Venda]]>1,1,0) -> 0
B15: PIX | C15: =(SUMIF($G$2:$G$31,B15,$I$2:$I$31))+(SUMIF($G$35:$G$41,B15,$H$35:$H$41)) -> 255.71 | K15: 9327 | L15: ariani | M15: Não | R15: =IF(vend7[[#This Row],[Nº Venda]]>1,1,0) -> 0
B16: Total | C16: =SUM(C11:C15) -> 3550.71 | K16: 9204 | L16: taty | M16: Não | R16: =IF(vend7[[#This Row],[Nº Venda]]>1,1,0) -> 0
K17: 9257 | L17: jocy | M17: Não | R17: =IF(vend7[[#This Row],[Nº Venda]]>1,1,0) -> 0
B18: Entrega de Carne | K18: 9260 | L18: jocxy | M18: Não | R18: =IF(vend7[[#This Row],[Nº Venda]]>1,1,0) -> 0
B19: =COUNT(entr_carn7[OS]) -> 1 | C19: =SUM(entr_carn7[Valor Total]) -> 530 | K19: 9263 | L19: jocy | M19: Não | R19: =IF(vend7[[#This Row],[Nº Venda]]>1,1,0) -> 0
B20: Total | C20: =SUM(C19:C19) -> 530 | K20: 9092 | L20: jocy | M20: Sim | R20: =IF(vend7[[#This Row],[Nº Venda]]>1,1,0) -> 0
K21: 9212 | L21: ariani | M21: Não
B22: Venda | C22: =C5 -> 2985
E24: Restante Entrada
E25: Nº Venda | F25: Cliente | G25: Forma de Pgto | H25: Valor Venda | I25: Entrada
E26: 8531 | F26: maria das dores | G26: DN | H26: 0 | I26: 100
E27: 9204 | F27: valdivo pereira | G27: CTD | H27: 0 | I27: 370
E28: 9092 | F28: maria neuza | G28: DN | H28: 0 | I28: 100
E29: 8992 | F29: nivalda rabelo | G29: DN | H29: 0 | I29: 120
E30: 8992 | F30: nivalda rabelo | G30: PIX | H30: 0 | I30: 100
E33: Recebimento de Carnê | K33: Entrega de Carne
E34: OS | F34: Cliente | G34: Forma de Pgto | H34: Valor Parcela | I34: Nº Parcela | K34: OS | L34: Parcelas | M34: Valor Total
E35: 9104 | F35: fabiana de souza | G35: PIX | H35: 57.14 | I35: PARC. 1/7 | K35: 9092 | L35: 5 | M35: 530
E36: 8551 | F36: aparecida maria | G36: PIX | H36: 98.57 | I36: PARC. 4/7
E37: 9222 | F37: quezia de almeida | G37: DN | H37: 150 | I37: PARC. 1/3
E38: 9222 | F38: quezia de almeida | G38: DN | H38: 150 | I38: PARC. 1/3
Q40: Total de OS | R40: =SUM(R6:R21) -> 4

Sheet 08
B1: ='07'!B1+1 -> 45451
B2: Fechamento Diário do Caixa
B4: Saldo Inicial | C4: 0 | E4: Vendas | K4: Despesas
B5: Vendas | C5: =SUMIF(I6:I31,">0",H6:H31) -> 719.9 | E5: Nº Venda | F5: Cliente | G5: Forma de Pgto | H5: Valor Venda | I5: Entrada | K5: Descrição | L5: Tipo de Pagto | M5: Valor
B6: Entrada | C6: =SUM(I6:I41) -> 2620.4 | E6: 9325 | F6: albertina da costa | G6: CTD | H6: 39.9 | I6: 39.9 | R6: =IF(vend8[[#This Row],[Nº Venda]]>1,1,0) -> 1
B7: Despesas | C7: =SUM(M6:M11) -> 0 | E7: 9328 | F7: kaio gabriel | G7: PIX | H7: 280 | I7: 250 | R7: =IF(vend8[[#This Row],[Nº Venda]]>1,1,0) -> 1
B8: Total entrada | C8: =SUM(C6:C7) -> 2620.4 | E8: 9330 | F8: marinalva bezerra | G8: DN | H8: 400 | I8: 50 | R8: =IF(vend8[[#This Row],[Nº Venda]]>1,1,0) -> 1
R9: =IF(vend8[[#This Row],[Nº Venda]]>1,1,0) -> 0
B10: Tipos de Pagtos | R10: =IF(vend8[[#This Row],[Nº Venda]]>1,1,0) -> 0
B11: DN | C11: =(SUMIF($G$2:$G$31,B11,$I$2:$I$31))+(SUMIF($G$35:$G$42,B11,$H$35:$H$42)) -> 105 | O11: =IF(C16=0,0,1) -> 1 | R11: =IF(vend8[[#This Row],[Nº Venda]]>1,1,0) -> 0
B12: CTD | C12: =(SUMIF($G$2:$G$31,B12,$I$2:$I$31))+(SUMIF($G$35:$G$42,B12,$H$35:$H$42)) -> 1065.62 | R12: =IF(vend8[[#This Row],[Nº Venda]]>1,1,0) -> 0
B13: CTC | C13: =(SUMIF($G$2:$G$31,B13,$I$2:$I$31))+(SUMIF($G$35:$G$42,B13,$H$35:$H$42)) -> 1399 | K13: OS Entregue no Dia | R13: =IF(vend8[[#This Row],[Nº Venda]]>1,1,0) -> 0
B14: PCTC | C14: =(SUMIF($G$2:$G$31,B14,$I$2:$I$31))+(SUMIF($G$35:$G$42,B14,$H$35:$H$42)) -> 0 | K14: OS | L14: Vendedor | M14: CARNE | R14: =IF(vend8[[#This Row],[Nº Venda]]>1,1,0) -> 0
B15: PIX | C15: =(SUMIF($G$2:$G$31,B15,$I$2:$I$31))+(SUMIF($G$35:$G$42,B15,$H$35:$H$42)) -> 688.83 | K15: 9030 | L15: garantia | M15: Não | R15: =IF(vend8[[#This Row],[Nº Venda]]>1,1,0) -> 0
B16: Total | C16: =SUM(C11:C15) -> 3258.45 | K16: 9201 | L16: ariani | M16: Não | R16: =IF(vend8[[#This Row],[Nº Venda]]>1,1,0) -> 0
K17: 9225 | L17: jocy | M17: Não | R17: =IF(vend8[[#This Row],[Nº Venda]]>1,1,0) -> 0
B18: Entrega de Carne | K18: 8822 | L18: taty | M18: Não | R18: =IF(vend8[[#This Row],[Nº Venda]]>1,1,0) -> 0
B19: =COUNT(entr_carn8[OS]) -> 0 | C19: =SUM(entr_carn8[Valor Total]) -> 0 | K19: 9190 | L19: taty | M19: Não | R19: =IF(vend8[[#This Row],[Nº Venda]]>1,1,0) -> 0
B20: Total | C20: =SUM(C19:C19) -> 0 | K20: 9256 | L20: jocy | M20: Não | R20: =IF(vend8[[#This Row],[Nº Venda]]>1,1,0) -> 0
B22: Venda | C22: =C5 -> 719.9
E24: Restante Entrada
E25: Nº Venda | F25: Cliente | G25: Forma de Pgto | H25: Valor Venda | I25: Entrada
E26: 9201 | F26: benedito oliveira | G26: CTC | H26: 0 | I26: 900
E27: 9225 | F27: rejane martiniano | G27: CTD | H27: 0 | I27: 700
E28: 8822 | F28: anna karolina | G28: CTC | H28: 0 | I28: 499
E29: 9323 | F29: marilu candido | G29: PIX | H29: 0 | I29: 181.5
E33: Recebimento de Carnê | K33: Entrega de Carne
E34: OS | F34: Cliente | G34: Forma de Pgto | H34: Valor Parcela | I34: Nº Parcela | K34: OS | L34: Parcelas | M34: Valor Total
E35: 9072 | F35: marilu candida | G35: PIX | H35: 168.33 | I35: PARC. 1/6
E36: 8472 | F36: arlete vieira | G36: CTD | H36: 125.72 | I36: PARC. 5/7
E37: 8370 | F37: wilson rodrigues | G37: CTD | H37: 120 | I37: PARC. 5/5
E38: 8790 | F38: maria aparecida | G38: DN | H38: 55 | I38: PARC. 3/7
E39: 8364 | F39: jesus ricardo | G39: CTD | H39: 80 | I39: PARC. 6/6
E40: 9166 | F40: izildinha aparecida | G40: PIX | H40: 89 | I40: PARC. 1/8 | Q40: Total de OS | R40: =SUM(R6:R21) -> 3

Sheet 09
B1: ='08'!B1+1 -> 45452
B2: Fechamento Diário do Caixa
B4: Saldo Inicial | C4: 0 | E4: Vendas | K4: Despesas
B5: Vendas | C5: =SUMIF(I6:I31,">0",H6:H31) -> 0 | E5: Nº Venda | F5: Cliente | G5: Forma de Pgto | H5: Valor Venda | I5: Entrada | K5: Descrição | L5: Tipo de Pagto | M5: Valor
B6: Entrada | C6: =SUM(I6:I41) -> 0 | R6: =IF(vend9[[#This Row],[Nº Venda]]>1,1,0) -> 0
B7: Despesas | C7: =SUM(M6:M11) -> 0 | R7: =IF(vend9[[#This Row],[Nº Venda]]>1,1,0) -> 0
B8: Total entrada | C8: =SUM(C6:C7) -> 0 | R8: =IF(vend9[[#This Row],[Nº Venda]]>1,1,0) -> 0
R9: =IF(vend9[[#This Row],[Nº Venda]]>1,1,0) -> 0
B10: Tipos de Pagtos | R10: =IF(vend9[[#This Row],[Nº Venda]]>1,1,0) -> 0
B11: DN | C11: =(SUMIF($G$2:$G$31,B11,$I$2:$I$31))+(SUMIF($G$35:$G$41,B11,$H$35:$H$41)) -> 0 | O11: =IF(C16=0,0,1) -> 0 | R11: =IF(vend9[[#This Row],[Nº Venda]]>1,1,0) -> 0
B12: CTD | C12: =(SUMIF($G$2:$G$31,B12,$I$2:$I$31))+(SUMIF($G$35:$G$41,B12,$H$35:$H$41)) -> 0 | R12: =IF(vend9[[#This Row],[Nº Venda]]>1,1,0) -> 0 | V12: 0
B13: CTC | C13: =(SUMIF($G$2:$G$31,B13,$I$2:$I$31))+(SUMIF($G$35:$G$41,B13,$H$35:$H$41)) -> 0 | K13: OS Entregue no Dia | R13: =IF(vend9[[#This Row],[Nº Venda]]>1,1,0) -> 0
B14: PCTC | C14: =(SUMIF($G$2:$G$31,B14,$I$2:$I$31))+(SUMIF($G$35:$G$41,B14,$H$35:$H$41)) -> 0 | K14: OS | L14: Vendedor | M14: CARNE | R14: =IF(vend9[[#This Row],[Nº Venda]]>1,1,0) -> 0
B15: PIX | C15: =(SUMIF($G$2:$G$31,B15,$I$2:$I$31))+(SUMIF($G$35:$G$41,B15,$H$35:$H$41)) -> 0 | R15: =IF(vend9[[#This Row],[Nº Venda]]>1,1,0) -> 0
B16: Total | C16: =SUM(C11:C15) -> 0 | R16: =IF(vend9[[#This Row],[Nº Venda]]>1,1,0) -> 0
R17: =IF(vend9[[#This Row],[Nº Venda]]>1,1,0) -> 0
B18: Entrega de Carne | R18: =IF(vend9[[#This Row],[Nº Venda]]>1,1,0) -> 0
B19: =COUNT(entr_carn9[OS]) -> 0 | C19: =SUM(entr_carn9[Valor Total]) -> 0 | R19: =IF(vend9[[#This Row],[Nº Venda]]>1,1,0) -> 0
B20: Total | C20: =SUM(C19:C19) -> 0 | R20: =IF(vend9[[#This Row],[Nº Venda]]>1,1,0) -> 0
B22: Venda | C22: =C5 -> 0
E24: Restante Entrada
E25: Nº Venda | F25: Cliente | G25: Forma de Pgto | H25: Valor Venda | I25: Entrada
E33: Recebimento de Carnê | K33: Entrega de Carne
E34: OS | F34: Cliente | G34: Forma de Pgto | H34: Valor Parcela | I34: Nº Parcela | K34: OS | L34: Parcelas | M34: Valor Total
Q40: Total de OS | R40: =SUM(R6:R21) -> 0

Sheet 10
B1: ='09'!B1+1 -> 45453
B2: Fechamento Diário do Caixa
B4: Saldo Inicial | C4: 0 | E4: Vendas | K4: Despesas
B5: Vendas | C5: =SUMIF(I6:I32,">0",H6:H32) -> 1218.97 | E5: Nº Venda | F5: Cliente | G5: Forma de Pgto | H5: Valor Venda | I5: Entrada | K5: Descrição | L5: Tipo de Pagto | M5: Valor
B6: Entrada | C6: =SUM(I6:I42) -> 1028.99 | E6: 9331 | F6: eufrasia de souza | G6: DN | H6: 40 | I6: 40 | R6: =IF(vend10[[#This Row],[Nº Venda]]>1,1,0) -> 1
B7: Despesas | C7: =SUM(M6:M11) -> 0 | E7: 9332 | F7: miriam watanabe | G7: CTD | H7: 110 | I7: 110 | R7: =IF(vend10[[#This Row],[Nº Venda]]>1,1,0) -> 1
B8: Total entrada | C8: =SUM(C6:C7) -> 1028.99 | E8: 9333 | F8: eunice lopes | G8: CTC | H8: 120 | I8: 120 | R8: =IF(vend10[[#This Row],[Nº Venda]]>1,1,0) -> 1
E9: 9334 | F9: sandra regina valdagno | G9: CTD | H9: 300 | I9: 150 | R9: =IF(vend10[[#This Row],[Nº Venda]]>1,1,0) -> 1
B10: Tipos de Pagtos | E10: 9335 | F10: douglas prieto | G10: CTC | H10: 499 | I10: 499 | R10: =IF(vend10[[#This Row],[Nº Venda]]>1,1,0) -> 1
B11: DN | C11: =(SUMIF($G$2:$G$32,B11,$I$2:$I$32))+(SUMIF($G$36:$G$42,B11,$H$36:$H$42)) -> 181.25 | E11: 9336 | F11: joão lucas da silva junior | G11: DN | H11: 99.98 | I11: 10 | O11: =IF(C16=0,0,1) -> 1 | R11: =IF(vend10[[#This Row],[Nº Venda]]>1,1,0) -> 1
B12: CTD | C12: =(SUMIF($G$2:$G$32,B12,$I$2:$I$32))+(SUMIF($G$36:$G$42,B12,$H$36:$H$42)) -> 260 | E12: 9337 | F12: alessandra g de oliveira | G12: PIX | H12: 49.99 | I12: 49.99 | R12: =IF(vend10[[#This Row],[Nº Venda]]>1,1,0) -> 1
B13: CTC | C13: =(SUMIF($G$2:$G$32,B13,$I$2:$I$32))+(SUMIF($G$36:$G$42,B13,$H$36:$H$42)) -> 619 | K13: OS Entregue no Dia | R13: =IF(vend10[[#This Row],[Nº Venda]]>1,1,0) -> 0
B14: PCTC | C14: =(SUMIF($G$2:$G$32,B14,$I$2:$I$32))+(SUMIF($G$36:$G$42,B14,$H$36:$H$42)) -> 0 | K14: OS | L14: Vendedor | M14: CARNE | R14: =IF(vend10[[#This Row],[Nº Venda]]>1,1,0) -> 0
B15: PIX | C15: =(SUMIF($G$2:$G$32,B15,$I$2:$I$32))+(SUMIF($G$36:$G$42,B15,$H$36:$H$42)) -> 49.99 | K15: 9287 | L15: ariani | M15: Não | R15: =IF(vend10[[#This Row],[Nº Venda]]>1,1,0) -> 0
B16: Total | C16: =SUM(C11:C15) -> 1110.24 | K16: 9337 | L16: taty | M16: não | R16: =IF(vend10[[#This Row],[Nº Venda]]>1,1,0) -> 0
K17: 9253 | L17: felipe | M17: Não | R17: =IF(vend10[[#This Row],[Nº Venda]]>1,1,0) -> 0
B18: Entrega de Carne | K18: 9302 | L18: jocy | M18: Não | R18: =IF(vend10[[#This Row],[Nº Venda]]>1,1,0) -> 0
B19: =COUNT(entr_carn10[OS]) -> 1 | C19: =SUM(entr_carn10[Valor Total]) -> 600 | K19: 9286 | L19: ariani | M19: Não | R19: =IF(vend10[[#This Row],[Nº Venda]]>1,1,0) -> 0
B20: Total | C20: =SUM(C19:C19) -> 600 | K20: 8987 | L20: taty | M20: Não | R20: =IF(vend10[[#This Row],[Nº Venda]]>1,1,0) -> 0
K21: 9258 | L21: jocy | M21: Sim
B22: Venda | C22: =C5 -> 1218.97 | K22: 9265 | L22: jocy | M22: Não
E24: Restante Entrada
E25: Nº Venda | F25: Cliente | G25: Forma de Pgto | H25: Valor Venda | I25: Entrada
E26: 9282 | F26: isaias xavier | G26: DN | I26: 50
K33: Entrega de Carne
E34: Recebimento de Carnê | K34: OS | L34: Parcelas | M34: Valor Total
E35: OS | F35: Cliente | G35: Forma de Pgto | H35: Valor Parcela | I35: Nº Parcela | K35: 9258 | L35: 6 | M35: 600
E36: 8078 | F36: joana maria | G36: DN | H36: 81.25 | I36: PARC. 8/8
Q40: Total de OS | R40: =SUM(R6:R21) -> 7

Sheet 11
B1: ='10'!B1+1 -> 45454
B2: Fechamento Diário do Caixa
B4: Saldo Inicial | C4: 0 | E4: Vendas | K4: Despesas
B5: Vendas | C5: =SUMIF(I6:I31,">0",H6:H31) -> 899 | E5: Nº Venda | F5: Cliente | G5: Forma de Pgto | H5: Valor Venda | I5: Entrada | K5: Descrição | L5: Tipo de Pagto | M5: Valor
B6: Entrada | C6: =SUM(I6:I41) -> 2409 | E6: 9338 | F6: atemilsom | G6: CTC | H6: 149 | I6: 149 | R6: =IF(vend11[[#This Row],[Nº Venda]]>1,1,0) -> 1
B7: Despesas | C7: =SUM(M6:M11) -> 0 | E7: 9339 | F7: gabrielle beserra | G7: CTC | H7: 750 | I7: 750 | R7: =IF(vend11[[#This Row],[Nº Venda]]>1,1,0) -> 1
B8: Total entrada | C8: =SUM(C6:C7) -> 2409 | R8: =IF(vend11[[#This Row],[Nº Venda]]>1,1,0) -> 0
R9: =IF(vend11[[#This Row],[Nº Venda]]>1,1,0) -> 0
B10: Tipos de Pagtos | R10: =IF(vend11[[#This Row],[Nº Venda]]>1,1,0) -> 0
B11: DN | C11: =(SUMIF($G$2:$G$31,B11,$I$2:$I$31))+(SUMIF($G$35:$G$41,B11,$H$35:$H$41)) -> 0 | O11: =IF(C16=0,0,1) -> 1 | R11: =IF(vend11[[#This Row],[Nº Venda]]>1,1,0) -> 0
B12: CTD | C12: =(SUMIF($G$2:$G$31,B12,$I$2:$I$31))+(SUMIF($G$35:$G$41,B12,$H$35:$H$41)) -> 115 | R12: =IF(vend11[[#This Row],[Nº Venda]]>1,1,0) -> 0
B13: CTC | C13: =(SUMIF($G$2:$G$31,B13,$I$2:$I$31))+(SUMIF($G$35:$G$41,B13,$H$35:$H$41)) -> 2409 | K13: OS Entregue no Dia | R13: =IF(vend11[[#This Row],[Nº Venda]]>1,1,0) -> 0
B14: PCTC | C14: =(SUMIF($G$2:$G$31,B14,$I$2:$I$31))+(SUMIF($G$35:$G$41,B14,$H$35:$H$41)) -> 0 | K14: OS | L14: Vendedor | M14: CARNE | R14: =IF(vend11[[#This Row],[Nº Venda]]>1,1,0) -> 0
B15: PIX | C15: =(SUMIF($G$2:$G$31,B15,$I$2:$I$31))+(SUMIF($G$35:$G$41,B15,$H$35:$H$41)) -> 184 | K15: 9333 | L15: ariane | M15: Não | R15: =IF(vend11[[#This Row],[Nº Venda]]>1,1,0) -> 0
B16: Total | C16: =SUM(C11:C15) -> 2708 | K16: 9306 | L16: ariane | M16: Não | R16: =IF(vend11[[#This Row],[Nº Venda]]>1,1,0) -> 0
K17: 9310 | L17: ariane | M17: Não | R17: =IF(vend11[[#This Row],[Nº Venda]]>1,1,0) -> 0
B18: Entrega de Carne | K18: 9336 | L18: taty | M18: Não | R18: =IF(vend11[[#This Row],[Nº Venda]]>1,1,0) -> 0
B19: =COUNT(entr_carn11[OS]) -> 0 | C19: =SUM(entr_carn11[Valor Total]) -> 0 | K19: 9337 | L19: taty | M19: Não | R19: =IF(vend11[[#This Row],[Nº Venda]]>1,1,0) -> 0
B20: Total | C20: =SUM(C19:C19) -> 0 | R20: =IF(vend11[[#This Row],[Nº Venda]]>1,1,0) -> 0
B22: Venda | C22: =C5 -> 899
E24: Restante Entrada
E25: Nº Venda | F25: Cliente | G25: Forma de Pgto | H25: Valor Venda | I25: Entrada
E26: 9299 | F26: claudenor de jesus | G26: CTC | I26: 1510
E33: Recebimento de Carnê | K33: Entrega de Carne
E34: OS | F34: Cliente | G34: Forma de Pgto | H34: Valor Parcela | I34: Nº Parcela | K34: OS | L34: Parcelas | M34: Valor Total
E35: 8504 | F35: izabel dos santos | G35: CTD | H35: 115 | I35: PARC. 5/6
E36: 8156 | F36: andressa souza | G36: PIX | H36: 74 | I36: PARC. 8/8
E37: 9102 | F37: ellen cristina | G37: PIX | H37: 60 | I37: PARC. 1/5
E38: 8153 | F38: valdineia molina | G38: PIX | H38: 50 | I38: PARC. 6/8
Q40: Total de OS | R40: =SUM(R6:R21) -> 2

Sheet 12
B1: ='11'!B1+1 -> 45455
B2: Fechamento Diário do Caixa
B4: Saldo Inicial | C4: 0 | E4: Vendas | K4: Despesas
B5: Vendas | C5: =SUMIF(I6:I31,">0",H6:H31) -> 3078.99 | E5: Nº Venda | F5: Cliente | G5: Forma de Pgto | H5: Valor Venda | I5: Entrada | K5: Descrição | L5: Tipo de Pagto | M5: Valor
B6: Entrada | C6: =SUM(I6:I41) -> 3278.99 | E6: 9340 | F6: alvaro rodrigues | G6: CTC | H6: 980 | I6: 980 | R6: =IF(vend12[[#This Row],[Nº Venda]]>1,1,0) -> 1
B7: Despesas | C7: =SUM(M6:M11) -> 0 | E7: 9341 | F7: leonardo dos santos | G7: CTD | H7: 99.99 | I7: 99.99 | R7: =IF(vend12[[#This Row],[Nº Venda]]>1,1,0) -> 1
B8: Total entrada | C8: =SUM(C6:C7) -> 3278.99 | E8: 9342 | F8: fabiana alves | G8: DN | H8: 600 | I8: 200 | R8: =IF(vend12[[#This Row],[Nº Venda]]>1,1,0) -> 1
E9: 9343 | F9: teresinha de fatima | G9: PIX | H9: 125 | I9: 125 | R9: =IF(vend12[[#This Row],[Nº Venda]]>1,1,0) -> 1
B10: Tipos de Pagtos | E10: 9344 | F10: gabriela mayara | G10: CTC | H10: 399 | I10: 399 | R10: =IF(vend12[[#This Row],[Nº Venda]]>1,1,0) -> 1
B11: DN | C11: =(SUMIF($G$2:$G$31,B11,$I$2:$I$31))+(SUMIF($G$35:$G$41,B11,$H$35:$H$41)) -> 880 | E11: 9345 | F11: teresinha de fatima | G11: PIX | H11: 125 | I11: 125 | O11: =IF(C16=0,0,1) -> 1 | R11: =IF(vend12[[#This Row],[Nº Venda]]>1,1,0) -> 1
B12: CTD | C12: =(SUMIF($G$2:$G$31,B12,$I$2:$I$31))+(SUMIF($G$35:$G$41,B12,$H$35:$H$41)) -> 849.99 | E12: 9346 | F12: joao soares | G12: CTD | H12: 750 | I12: 750 | R12: =IF(vend12[[#This Row],[Nº Venda]]>1,1,0) -> 1
B13: CTC | C13: =(SUMIF($G$2:$G$31,B13,$I$2:$I$31))+(SUMIF($G$35:$G$41,B13,$H$35:$H$41)) -> 1379 | K13: OS Entregue no Dia | R13: =IF(vend12[[#This Row],[Nº Venda]]>1,1,0) -> 0
B14: PCTC | C14: =(SUMIF($G$2:$G$31,B14,$I$2:$I$31))+(SUMIF($G$35:$G$41,B14,$H$35:$H$41)) -> 0 | K14: OS | L14: Vendedor | M14: CARNE | R14: =IF(vend12[[#This Row],[Nº Venda]]>1,1,0) -> 0
B15: PIX | C15: =(SUMIF($G$2:$G$31,B15,$I$2:$I$31))+(SUMIF($G$35:$G$41,B15,$H$35:$H$41)) -> 250 | K15: 9343 | L15: jocy | M15: Não | R15: =IF(vend12[[#This Row],[Nº Venda]]>1,1,0) -> 0
B16: Total | C16: =SUM(C11:C15) -> 3358.99 | K16: 9246 | L16: jocy | M16: Não | R16: =IF(vend12[[#This Row],[Nº Venda]]>1,1,0) -> 0
K17: 9261 | L17: taty | M17: Não | R17: =IF(vend12[[#This Row],[Nº Venda]]>1,1,0) -> 0
B18: Entrega de Carne | K18: 9244 | L18: taty | M18: Não | R18: =IF(vend12[[#This Row],[Nº Venda]]>1,1,0) -> 0
B19: =COUNT(entr_carn12[OS]) -> 0 | C19: =SUM(entr_carn12[Valor Total]) -> 0 | K19: 9345 | L19: jocy | M19: Não | R19: =IF(vend12[[#This Row],[Nº Venda]]>1,1,0) -> 0
B20: Total | C20: =SUM(C19:C19) -> 0 | K20: 9254 | L20: felipe | M20: Não | R20: =IF(vend12[[#This Row],[Nº Venda]]>1,1,0) -> 0
K21: 9311 | L21: ariani | M21: Não
B22: Venda | C22: =C5 -> 3078.99
E24: Restante Entrada
E25: Nº Venda | F25: Cliente | G25: Forma de Pgto | H25: Valor Venda | I25: Entrada
E26: 9244 | F26: larissa yuka | G26: DN | H26: 0 | I26: 600
E33: Recebimento de Carnê | K33: Entrega de Carne
E34: OS | F34: Cliente | G34: Forma de Pgto | H34: Valor Parcela | I34: Nº Parcela | K34: OS | L34: Parcelas | M34: Valor Total
E35: 8617 | F35: maria aparecida | G35: DN | H35: 80 | I35: PARC. 4/4
Q40: Total de OS | R40: =SUM(R6:R21) -> 7

Sheet 13
B1: ='12'!B1+1 -> 45456
B2: Fechamento Diário do Caixa
B4: Saldo Inicial | C4: 0 | E4: Vendas | K4: Despesas
B5: Vendas | C5: =SUMIF(I6:I31,">0",H6:H31) -> 2010 | E5: Nº Venda | F5: Cliente | G5: Forma de Pgto | H5: Valor Venda | I5: Entrada | K5: Descrição | L5: Tipo de Pagto | M5: Valor
B6: Entrada | C6: =SUM(I6:I41) -> 1560 | E6: 9347 | F6: PEDRO BRASIL | G6: CTC | H6: 480 | I6: 480 | R6: =IF(vend13[[#This Row],[Nº Venda]]>1,1,0) -> 1
B7: Despesas | C7: =SUM(M6:M11) -> 0 | E7: 9348 | F7: BENEDITO DA SILVA | G7: CTD | H7: 650 | I7: 150 | R7: =IF(vend13[[#This Row],[Nº Venda]]>1,1,0) -> 1
B8: Total entrada | C8: =SUM(C6:C7) -> 1560 | E8: 9349 | F8: FABIANA ALVES | G8: CTD | H8: 250 | I8: 200 | R8: =IF(vend13[[#This Row],[Nº Venda]]>1,1,0) -> 1
E9: 9349 | F9: FABIANA ALVES | G9: DN | I9: 50 | R9: =IF(vend13[[#This Row],[Nº Venda]]>1,1,0) -> 1
B10: Tipos de Pagtos | E10: 9350 | F10: CRISTIANE DE CASSIA | G10: PIX | H10: 40 | I10: 40 | R10: =IF(vend13[[#This Row],[Nº Venda]]>1,1,0) -> 1
B11: DN | C11: =(SUMIF($G$2:$G$31,B11,$I$2:$I$31))+(SUMIF($G$35:$G$41,B11,$H$35:$H$41)) -> 166.5 | E11: 9351 | F11: RENAN BALBINO | G11: CTC | H11: 590 | I11: 590 | O11: =IF(C16=0,0,1) -> 1 | R11: =IF(vend13[[#This Row],[Nº Venda]]>1,1,0) -> 1
B12: CTD | C12: =(SUMIF($G$2:$G$31,B12,$I$2:$I$31))+(SUMIF($G$35:$G$41,B12,$H$35:$H$41)) -> 450 | R12: =IF(vend13[[#This Row],[Nº Venda]]>1,1,0) -> 0
B13: CTC | C13: =(SUMIF($G$2:$G$31,B13,$I$2:$I$31))+(SUMIF($G$35:$G$41,B13,$H$35:$H$41)) -> 1070 | K13: OS Entregue no Dia | R13: =IF(vend13[[#This Row],[Nº Venda]]>1,1,0) -> 0
B14: PCTC | C14: =(SUMIF($G$2:$G$31,B14,$I$2:$I$31))+(SUMIF($G$35:$G$41,B14,$H$35:$H$41)) -> 0 | K14: OS | L14: Vendedor | M14: CARNE | R14: =IF(vend13[[#This Row],[Nº Venda]]>1,1,0) -> 0
B15: PIX | C15: =(SUMIF($G$2:$G$31,B15,$I$2:$I$31))+(SUMIF($G$35:$G$41,B15,$H$35:$H$41)) -> 40 | K15: 9229 | L15: ARIANI | M15: Não | R15: =IF(vend13[[#This Row],[Nº Venda]]>1,1,0) -> 0
B16: Total | C16: =SUM(C11:C15) -> 1726.5 | K16: 9330 | L16: ARIANI | M16: Sim | R16: =IF(vend13[[#This Row],[Nº Venda]]>1,1,0) -> 0
R17: =IF(vend13[[#This Row],[Nº Venda]]>1,1,0) -> 0
B18: Entrega de Carne | R18: =IF(vend13[[#This Row],[Nº Venda]]>1,1,0) -> 0
B19: =COUNT(entr_carn13[OS]) -> 1 | C19: =SUM(entr_carn13[Valor Total]) -> 300 | R19: =IF(vend13[[#This Row],[Nº Venda]]>1,1,0) -> 0
B20: Total | C20: =SUM(C19:C19) -> 300 | R20: =IF(vend13[[#This Row],[Nº Venda]]>1,1,0) -> 0
B22: Venda | C22: =C5 -> 2010
E24: Restante Entrada
E25: Nº Venda | F25: Cliente | G25: Forma de Pgto | H25: Valor Venda | I25: Entrada
E26: 9330 | F26: MARINALVA BEZERRA | G26: DN | I26: 50
E33: Recebimento de Carnê | K33: Entrega de Carne
E34: OS | F34: Cliente | G34: Forma de Pgto | H34: Valor Parcela | I34: Nº Parcela | K34: OS | L34: Parcelas | M34: Valor Total
E35: 8486 | F35: SUELY PEREIRA | G35: CTD | H35: 100 | I35: PARC. 4/4 | K35: 9330 | L35: 6 | M35: 300
E36: 9156 | F36: SIMOME IGNACIIO | G36: DN | H36: 66.5 | I36: PARC. 1/6
Q40: Total de OS | R40: =SUM(R6:R21) -> 6

Sheet 14
B1: ='13'!B1+1 -> 45457
B2: Fechamento Diário do Caixa
B4: Saldo Inicial | C4: 0 | E4: Vendas | K4: Despesas
B5: Vendas | C5: =SUMIF(I6:I31,">0",H6:H31) -> 6779.99 | E5: Nº Venda | F5: Cliente | G5: Forma de Pgto | H5: Valor Venda | I5: Entrada | K5: Descrição | L5: Tipo de Pagto | M5: Valor
B6: Entrada | C6: =SUM(I6:I41) -> 7057.49 | E6: 9352 | F6: miguel quedas | G6: CTC | H6: 550 | I6: 550 | K6: extensão | L6: dn | M6: 39.95 | R6: =IF(vend14[[#This Row],[Nº Venda]]>1,1,0) -> 1
B7: Despesas | C7: =SUM(M6:M11) -> 39.95 | E7: 9353 | F7: delzuina de souza | G7: CTC | H7: 2200 | I7: 2200 | R7: =IF(vend14[[#This Row],[Nº Venda]]>1,1,0) -> 1
B8: Total entrada | C8: =SUM(C6:C7) -> 7097.44 | E8: 9354 | F8: antonio rodrigues | G8: CTD | H8: 800 | I8: 400 | R8: =IF(vend14[[#This Row],[Nº Venda]]>1,1,0) -> 1
E9: 9355 | F9: benedito gava | G9: DN | H9: 200 | I9: 200 | R9: =IF(vend14[[#This Row],[Nº Venda]]>1,1,0) -> 1
B10: Tipos de Pagtos | E10: 9356 | F10: elenice alves | G10: DN | H10: 200 | I10: 50 | R10: =IF(vend14[[#This Row],[Nº Venda]]>1,1,0) -> 1
B11: DN | C11: =(SUMIF($G$2:$G$31,B11,$I$2:$I$31))+(SUMIF($G$35:$G$41,B11,$H$35:$H$41)) -> 3162.5 | E11: 9357 | F11: ueodi de souza | G11: DN | H11: 2690 | I11: 1000 | O11: =IF(C16=0,0,1) -> 1 | R11: =IF(vend14[[#This Row],[Nº Venda]]>1,1,0) -> 1
B12: CTD | C12: =(SUMIF($G$2:$G$31,B12,$I$2:$I$31))+(SUMIF($G$35:$G$41,B12,$H$35:$H$41)) -> 440 | E12: 9358 | F12: delzuina de souza | G12: PIX | H12: 139.99 | I12: 99.99 | R12: =IF(vend14[[#This Row],[Nº Venda]]>1,1,0) -> 1
B13: CTC | C13: =(SUMIF($G$2:$G$31,B13,$I$2:$I$31))+(SUMIF($G$35:$G$41,B13,$H$35:$H$41)) -> 3230 | E13: 9358 | F13: delzuina de souza | G13: CTD | I13: 40 | K13: OS Entregue no Dia | R13: =IF(vend14[[#This Row],[Nº Venda]]>1,1,0) -> 1
B14: PCTC | C14: =(SUMIF($G$2:$G$31,B14,$I$2:$I$31))+(SUMIF($G$35:$G$41,B14,$H$35:$H$41)) -> 0 | K14: OS | L14: Vendedor | M14: CARNE | R14: =IF(vend14[[#This Row],[Nº Venda]]>1,1,0) -> 0
B15: PIX | C15: =(SUMIF($G$2:$G$31,B15,$I$2:$I$31))+(SUMIF($G$35:$G$41,B15,$H$35:$H$41)) -> 224.99 | K15: 9309 | L15: ariani | M15: Não | R15: =IF(vend14[[#This Row],[Nº Venda]]>1,1,0) -> 0
B16: Total | C16: =SUM(C11:C15) -> 7057.49 | K16: 9290 | L16: ariani | M16: Não | R16: =IF(vend14[[#This Row],[Nº Venda]]>1,1,0) -> 0
K17: 9313 | L17: jocy | M17: Não | R17: =IF(vend14[[#This Row],[Nº Venda]]>1,1,0) -> 0
B18: Entrega de Carne | K18: 9237 | L18: taty | M18: Não | R18: =IF(vend14[[#This Row],[Nº Venda]]>1,1,0) -> 0
B19: =COUNT(entr_carn14[OS]) -> 1 | C19: =SUM(entr_carn14[Valor Total]) -> 450 | K19: 9262 | L19: jocy | M19: Sim | R19: =IF(vend14[[#This Row],[Nº Venda]]>1,1,0) -> 0
B20: Total | C20: =SUM(C19:C19) -> 450 | K20: 9117 | L20: ariani | M20: Não | R20: =IF(vend14[[#This Row],[Nº Venda]]>1,1,0) -> 0
K21: 9238 | L21: taty | M21: Não
B22: Venda | C22: =C5 -> 6779.99 | K22: 9358 | L22: jocy | M22: Não
E24: Restante Entrada
E25: Nº Venda | F25: Cliente | G25: Forma de Pgto | H25: Valor Venda | I25: Entrada
E26: 9309 | F26: joao bosco | G26: DN | I26: 550
E27: 9313 | F27: gilberto gomes | G27: DN | I27: 1300
E28: 9262 | F28: silvia maria | G28: PIX | I28: 125
E29: 8932 | F29: maria imaculada | G29: DN | I29: 62.5
E30: 9217 | F30: arnelina de souza | G30: CTC | I30: 480
E33: Recebimento de Carnê | K33: Entrega de Carne
E34: OS | F34: Cliente | G34: Forma de Pgto | H34: Valor Parcela | I34: Nº Parcela | K34: OS | L34: Parcelas | M34: Valor Total
K35: 9262 | L35: 6 | M35: 450
Q40: Total de OS | R40: =SUM(R6:R21) -> 8

Sheet 15
B1: ='14'!B1+1 -> 45458
B2: Fechamento Diário do Caixa
B4: Saldo Inicial | C4: 0 | E4: Vendas | K4: Despesas
B5: Vendas | C5: =SUMIF(I6:I31,">0",H6:H31) -> 280 | E5: Nº Venda | F5: Cliente | G5: Forma de Pgto | H5: Valor Venda | I5: Entrada | K5: Descrição | L5: Tipo de Pagto | M5: Valor
B6: Entrada | C6: =SUM(I6:I41) -> 3500 | E6: 9359 | F6: angelica maria | G6: CTD | H6: 100 | I6: 100 | R6: =IF(vend15[[#This Row],[Nº Venda]]>1,1,0) -> 1
B7: Despesas | C7: =SUM(M6:M11) -> 0 | E7: 9360 | F7: misma oliveira | G7: CTD | H7: 40 | I7: 40 | R7: =IF(vend15[[#This Row],[Nº Venda]]>1,1,0) -> 1
B8: Total entrada | C8: =SUM(C6:C7) -> 3500 | E8: 9361 | F8: claudia rocha | G8: CTC | H8: 40 | I8: 40 | R8: =IF(vend15[[#This Row],[Nº Venda]]>1,1,0) -> 1
E9: 9362 | F9: edvaldo bispo | G9: GARANTIA | R9: =IF(vend15[[#This Row],[Nº Venda]]>1,1,0) -> 1
B10: Tipos de Pagtos | R10: =IF(vend15[[#This Row],[Nº Venda]]>1,1,0) -> 0
B11: DN | C11: =(SUMIF($G$2:$G$31,B11,$I$2:$I$31))+(SUMIF($G$35:$G$41,B11,$H$35:$H$41)) -> 0 | O11: =IF(C16=0,0,1) -> 1 | R11: =IF(vend15[[#This Row],[Nº Venda]]>1,1,0) -> 0
B12: CTD | C12: =(SUMIF($G$2:$G$31,B12,$I$2:$I$31))+(SUMIF($G$35:$G$41,B12,$H$35:$H$41)) -> 406.16 | R12: =IF(vend15[[#This Row],[Nº Venda]]>1,1,0) -> 0
B13: CTC | C13: =(SUMIF($G$2:$G$31,B13,$I$2:$I$31))+(SUMIF($G$35:$G$41,B13,$H$35:$H$41)) -> 140 | K13: OS Entregue no Dia | R13: =IF(vend15[[#This Row],[Nº Venda]]>1,1,0) -> 0
B14: PCTC | C14: =(SUMIF($G$2:$G$31,B14,$I$2:$I$31))+(SUMIF($G$35:$G$41,B14,$H$35:$H$41)) -> 0 | K14: OS | L14: Vendedor | M14: CARNE | R14: =IF(vend15[[#This Row],[Nº Venda]]>1,1,0) -> 0
B15: PIX | C15: =(SUMIF($G$2:$G$31,B15,$I$2:$I$31))+(SUMIF($G$35:$G$41,B15,$H$35:$H$41)) -> 3176.66 | K15: 9334 | L15: ariani | M15: Não | R15: =IF(vend15[[#This Row],[Nº Venda]]>1,1,0) -> 0
B16: Total | C16: =SUM(C11:C15) -> 3722.82 | K16: 9332 | L16: ariani | M16: Não | R16: =IF(vend15[[#This Row],[Nº Venda]]>1,1,0) -> 0
K17: 9325 | L17: ariani | M17: Não | R17: =IF(vend15[[#This Row],[Nº Venda]]>1,1,0) -> 0
B18: Entrega de Carne | K18: 9298 | L18: ariani | M18: Não | R18: =IF(vend15[[#This Row],[Nº Venda]]>1,1,0) -> 0
B19: =COUNT(entr_carn15[OS]) -> 0 | C19: =SUM(entr_carn15[Valor Total]) -> 0 | K19: 9297 | L19: ariani | M19: Não | R19: =IF(vend15[[#This Row],[Nº Venda]]>1,1,0) -> 0
B20: Total | C20: =SUM(C19:C19) -> 0 | K20: 9318 | L20: ariani | M20: Não | R20: =IF(vend15[[#This Row],[Nº Venda]]>1,1,0) -> 0
K21: 9323 | L21: ariani | M21: Não
B22: Venda | C22: =C5 -> 280 | K22: 9195 | L22: taty | M22: Não
K23: 9192 | L23: taty | M23: Não
E24: Restante Entrada | K24: 9196 | L24: taty | M24: Não
E25: Nº Venda | F25: Cliente | G25: Forma de Pgto | H25: Valor Venda | I25: Entrada | K25: 9227 | L25: taty | M25: Não
E26: 9334 | F26: sandra regina | G26: CTD | I26: 150 | K26: 9335 | L26: ariani | M26: Não
E27: 9325 | F27: adriana victorino | G27: CTC | H27: 100 | I27: 100
E28: 9192 | F28: marcos antonio | G28: PIX | I28: 2670
E29: 9227 | F29: marcos antonio | G29: PIX | I29: 400
E33: Recebimento de Carnê | K33: Entrega de Carne
E34: OS | F34: Cliente | G34: Forma de Pgto | H34: Valor Parcela | I34: Nº Parcela | K34: OS | L34: Parcelas | M34: Valor Total
E35: 9091 | F35: rosinete tavares | G35: CTD | H35: 116.16 | I35: PARC. 1/6
E36: 8669 | F36: sandra fernandes | G36: PIX | H36: 106.66 | I36: PARC. 4/6
Q40: Total de OS | R40: =SUM(R6:R21) -> 4

Sheet 16
B1: ='15'!B1+1 -> 45459
B2: Fechamento Diário do Caixa
B4: Saldo Inicial | C4: 0 | E4: Vendas | K4: Despesas
B5: Vendas | C5: =SUMIF(I6:I31,">0",H6:H31) -> 0 | E5: Nº Venda | F5: Cliente | G5: Forma de Pgto | H5: Valor Venda | I5: Entrada | K5: Descrição | L5: Tipo de Pagto | M5: Valor
B6: Entrada | C6: =SUM(I6:I41) -> 0 | R6: =IF(vend16[[#This Row],[Nº Venda]]>1,1,0) -> 0
B7: Despesas | C7: =SUM(M6:M11) -> 0 | R7: =IF(vend16[[#This Row],[Nº Venda]]>1,1,0) -> 0
B8: Total entrada | C8: =SUM(C6:C7) -> 0 | R8: =IF(vend16[[#This Row],[Nº Venda]]>1,1,0) -> 0
R9: =IF(vend16[[#This Row],[Nº Venda]]>1,1,0) -> 0
B10: Tipos de Pagtos | R10: =IF(vend16[[#This Row],[Nº Venda]]>1,1,0) -> 0
B11: DN | C11: =(SUMIF($G$2:$G$31,B11,$I$2:$I$31))+(SUMIF($G$35:$G$41,B11,$H$35:$H$41)) -> 0 | O11: =IF(C16=0,0,1) -> 0 | R11: =IF(vend16[[#This Row],[Nº Venda]]>1,1,0) -> 0
B12: CTD | C12: =(SUMIF($G$2:$G$31,B12,$I$2:$I$31))+(SUMIF($G$35:$G$41,B12,$H$35:$H$41)) -> 0 | R12: =IF(vend16[[#This Row],[Nº Venda]]>1,1,0) -> 0
B13: CTC | C13: =(SUMIF($G$2:$G$31,B13,$I$2:$I$31))+(SUMIF($G$35:$G$41,B13,$H$35:$H$41)) -> 0 | K13: OS Entregue no Dia | R13: =IF(vend16[[#This Row],[Nº Venda]]>1,1,0) -> 0
B14: PCTC | C14: =(SUMIF($G$2:$G$31,B14,$I$2:$I$31))+(SUMIF($G$35:$G$41,B14,$H$35:$H$41)) -> 0 | K14: OS | L14: Vendedor | M14: CARNE | R14: =IF(vend16[[#This Row],[Nº Venda]]>1,1,0) -> 0
B15: PIX | C15: =(SUMIF($G$2:$G$31,B15,$I$2:$I$31))+(SUMIF($G$35:$G$41,B15,$H$35:$H$41)) -> 0 | R15: =IF(vend16[[#This Row],[Nº Venda]]>1,1,0) -> 0
B16: Total | C16: =SUM(C11:C15) -> 0 | R16: =IF(vend16[[#This Row],[Nº Venda]]>1,1,0) -> 0
R17: =IF(vend16[[#This Row],[Nº Venda]]>1,1,0) -> 0
B18: Entrega de Carne | R18: =IF(vend16[[#This Row],[Nº Venda]]>1,1,0) -> 0
B19: =COUNT(entr_carn16[OS]) -> 0 | C19: =SUM(entr_carn16[Valor Total]) -> 0 | R19: =IF(vend16[[#This Row],[Nº Venda]]>1,1,0) -> 0
B20: Total | C20: =SUM(C19:C19) -> 0 | R20: =IF(vend16[[#This Row],[Nº Venda]]>1,1,0) -> 0
B22: Venda | C22: =C5 -> 0
E24: Restante Entrada
E25: Nº Venda | F25: Cliente | G25: Forma de Pgto | H25: Valor Venda | I25: Entrada
E33: Recebimento de Carnê | K33: Entrega de Carne
E34: OS | F34: Cliente | G34: Forma de Pgto | H34: Valor Parcela | I34: Nº Parcela | K34: OS | L34: Parcelas | M34: Valor Total
Q40: Total de OS | R40: =SUM(R6:R21) -> 0

Sheet 17
B1: ='16'!B1+1 -> 45460
B2: Fechamento Diário do Caixa
B4: Saldo Inicial | C4: 0 | E4: Vendas | K4: Despesas
B5: Vendas | C5: =SUMIF(I6:I31,">0",H6:H31) -> 850 | E5: Nº Venda | F5: Cliente | G5: Forma de Pgto | H5: Valor Venda | I5: Entrada | K5: Descrição | L5: Tipo de Pagto | M5: Valor
B6: Entrada | C6: =SUM(I6:I41) -> 995 | E6: 9363 | F6: vania campos | G6: CTC | H6: 500 | I6: 500 | R6: =IF(vend17[[#This Row],[Nº Venda]]>1,1,0) -> 1
B7: Despesas | C7: =SUM(M6:M11) -> 0 | E7: 9364 | F7: vania campos | G7: CTC | H7: 200 | I7: 200 | R7: =IF(vend17[[#This Row],[Nº Venda]]>1,1,0) -> 1
B8: Total entrada | C8: =SUM(C6:C7) -> 995 | E8: 9365 | F8: gilberto gomes | G8: GARANTIA | R8: =IF(vend17[[#This Row],[Nº Venda]]>1,1,0) -> 1
E9: 9366 | F9: katia maria | G9: GARANTIA | R9: =IF(vend17[[#This Row],[Nº Venda]]>1,1,0) -> 1
B10: Tipos de Pagtos | E10: 9367 | F10: rosinete tavares | G10: GARANTIA | R10: =IF(vend17[[#This Row],[Nº Venda]]>1,1,0) -> 1
B11: DN | C11: =(SUMIF($G$2:$G$31,B11,$I$2:$I$31))+(SUMIF($G$35:$G$41,B11,$H$35:$H$41)) -> 214 | E11: 9368 | F11: antonio benedito | G11: DN | H11: 150 | I11: 100 | O11: =IF(C16=0,0,1) -> 1 | R11: =IF(vend17[[#This Row],[Nº Venda]]>1,1,0) -> 1
B12: CTD | C12: =(SUMIF($G$2:$G$31,B12,$I$2:$I$31))+(SUMIF($G$35:$G$41,B12,$H$35:$H$41)) -> 50 | E12: 9368 | F12: antonio benedito | G12: CTD | I12: 50 | R12: =IF(vend17[[#This Row],[Nº Venda]]>1,1,0) -> 1
B13: CTC | C13: =(SUMIF($G$2:$G$31,B13,$I$2:$I$31))+(SUMIF($G$35:$G$41,B13,$H$35:$H$41)) -> 700 | K13: OS Entregue no Dia | R13: =IF(vend17[[#This Row],[Nº Venda]]>1,1,0) -> 0
B14: PCTC | C14: =(SUMIF($G$2:$G$31,B14,$I$2:$I$31))+(SUMIF($G$35:$G$41,B14,$H$35:$H$41)) -> 0 | K14: OS | L14: Vendedor | M14: CARNE | R14: =IF(vend17[[#This Row],[Nº Venda]]>1,1,0) -> 0
B15: PIX | C15: =(SUMIF($G$2:$G$31,B15,$I$2:$I$31))+(SUMIF($G$35:$G$41,B15,$H$35:$H$41)) -> 145 | K15: 9277 | L15: garantia | M15: Não | R15: =IF(vend17[[#This Row],[Nº Venda]]>1,1,0) -> 0
B16: Total | C16: =SUM(C11:C15) -> 1109 | K16: 9368 | L16: jocy | M16: Não | R16: =IF(vend17[[#This Row],[Nº Venda]]>1,1,0) -> 0
K17: 9186 | L17: jocy | M17: Não | R17: =IF(vend17[[#This Row],[Nº Venda]]>1,1,0) -> 0
B18: Entrega de Carne | R18: =IF(vend17[[#This Row],[Nº Venda]]>1,1,0) -> 0
B19: =COUNT(entr_carn17[OS]) -> 0 | C19: =SUM(entr_carn17[Valor Total]) -> 0 | R19: =IF(vend17[[#This Row],[Nº Venda]]>1,1,0) -> 0
B20: Total | C20: =SUM(C19:C19) -> 0 | R20: =IF(vend17[[#This Row],[Nº Venda]]>1,1,0) -> 0
B22: Venda | C22: =C5 -> 850
E24: Restante Entrada
E25: Nº Venda | F25: Cliente | G25: Forma de Pgto | H25: Valor Venda | I25: Entrada
E26: 9218 | F26: viviane eleuterio | G26: PIX | I26: 15
E28: 8992 | F28: nivalda rabelo | G28: PIX | I28: 30
E29: 9186 | F29: quispe sosa | G29: PIX | I29: 100
E33: Recebimento de Carnê | K33: Entrega de Carne
E34: OS | F34: Cliente | G34: Forma de Pgto | H34: Valor Parcela | I34: Nº Parcela | K34: OS | L34: Parcelas | M34: Valor Total
E35: 8253 | F35: velderese evaristo | G35: DN | H35: 56 | I35: PARC. 7/8
E36: 8253 | F36: velderese evaristo | G36: DN | H36: 58 | I36: PARC. 8/8
Q40: Total de OS | R40: =SUM(R6:R21) -> 7

Sheet 18
B1: ='17'!B1+1 -> 45461
B2: Fechamento Diário do Caixa
B4: Saldo Inicial | C4: 0 | E4: Vendas | K4: Despesas
B5: Vendas | C5: =SUMIF(I6:I31,">0",H6:H31) -> 6249.96 | E5: Nº Venda | F5: Cliente | G5: Forma de Pgto | H5: Valor Venda | I5: Entrada | K5: Descrição | L5: Tipo de Pagto | M5: Valor
B6: Entrada | C6: =SUM(I6:I41) -> 2023.99 | E6: 9369 | F6: tatiane gomes | G6: CTD | H6: 40 | I6: 40 | R6: =IF(vend18[[#This Row],[Nº Venda]]>1,1,0) -> 1
B7: Despesas | C7: =SUM(M6:M11) -> 0 | E7: 9370 | F7: marisa de araujo | G7: PIX | H7: 999.99 | I7: 150 | R7: =IF(vend18[[#This Row],[Nº Venda]]>1,1,0) -> 1
B8: Total entrada | C8: =SUM(C6:C7) -> 2023.99 | E8: 9371 | F8: thais furushima | G8: CTC | H8: 700 | I8: 700 | R8: =IF(vend18[[#This Row],[Nº Venda]]>1,1,0) -> 1
E9: 9372 | F9: valvi costa | G9: CTD | H9: 1800 | I9: 900 | R9: =IF(vend18[[#This Row],[Nº Venda]]>1,1,0) -> 1
B10: Tipos de Pagtos | E10: 9373 | F10: noemi regina | G10: PIX | H10: 899.99 | I10: 15 | R10: =IF(vend18[[#This Row],[Nº Venda]]>1,1,0) -> 1
B11: DN | C11: =(SUMIF($G$2:$G$31,B11,$I$2:$I$31))+(SUMIF($G$35:$G$41,B11,$H$35:$H$41)) -> 139 | E11: 9374 | F11: sara de quadros | G11: CTD | H11: 399.99 | I11: 10 | O11: =IF(C16=0,0,1) -> 1 | R11: =IF(vend18[[#This Row],[Nº Venda]]>1,1,0) -> 1
B12: CTD | C12: =(SUMIF($G$2:$G$31,B12,$I$2:$I$31))+(SUMIF($G$35:$G$41,B12,$H$35:$H$41)) -> 1069.99 | E12: 9375 | F12: carmelina | G12: CTC | H12: 1251 | I12: 50 | R12: =IF(vend18[[#This Row],[Nº Venda]]>1,1,0) -> 1
B13: CTC | C13: =(SUMIF($G$2:$G$31,B13,$I$2:$I$31))+(SUMIF($G$35:$G$41,B13,$H$35:$H$41)) -> 750 | E13: 9376 | F13: elen shechticiue | G13: DN | H13: 89 | I13: 89 | K13: OS Entregue no Dia | R13: =IF(vend18[[#This Row],[Nº Venda]]>1,1,0) -> 1
B14: PCTC | C14: =(SUMIF($G$2:$G$31,B14,$I$2:$I$31))+(SUMIF($G$35:$G$41,B14,$H$35:$H$41)) -> 0 | E14: 9377 | F14: maria de lourdes | G14: CTD | H14: 69.99 | I14: 69.99 | K14: OS | L14: Vendedor | M14: CARNE | R14: =IF(vend18[[#This Row],[Nº Venda]]>1,1,0) -> 1
B15: PIX | C15: =(SUMIF($G$2:$G$31,B15,$I$2:$I$31))+(SUMIF($G$35:$G$41,B15,$H$35:$H$41)) -> 512.33 | K15: 9376 | L15: taty | M15: Não | R15: =IF(vend18[[#This Row],[Nº Venda]]>1,1,0) -> 0
B16: Total | C16: =SUM(C11:C15) -> 2471.32 | K16: 9351 | L16: jocy | M16: Não | R16: =IF(vend18[[#This Row],[Nº Venda]]>1,1,0) -> 0
K17: 9377 | L17: taty | M17: Não | R17: =IF(vend18[[#This Row],[Nº Venda]]>1,1,0) -> 0
B18: Entrega de Carne | R18: =IF(vend18[[#This Row],[Nº Venda]]>1,1,0) -> 0
B19: =COUNT(entr_carn18[OS]) -> 0 | C19: =SUM(entr_carn18[Valor Total]) -> 0 | R19: =IF(vend18[[#This Row],[Nº Venda]]>1,1,0) -> 0
B20: Total | C20: =SUM(C19:C19) -> 0 | R20: =IF(vend18[[#This Row],[Nº Venda]]>1,1,0) -> 0
B22: Venda | C22: =C5 -> 6249.96
E24: Restante Entrada
E25: Nº Venda | F25: Cliente | G25: Forma de Pgto | H25: Valor Venda | I25: Entrada
E33: Recebimento de Carnê | K33: Entrega de Carne
E34: OS | F34: Cliente | G34: Forma de Pgto | H34: Valor Parcela | I34: Nº Parcela | K34: OS | L34: Parcelas | M34: Valor Total
E35: 9203 | F35: valdivo pereira | G35: PIX | H35: 199 | I35: PARC. 1/1
E36: 9208 | F36: patricia dos santos | G36: PIX | H36: 63.33 | I36: PARC. 1/6
E37: 8765 | F37: maria rosa | G37: DN | H37: 50 | I37: PARC. 4/6
E38: 8765 | F38: maria rosa | G38: CTD | H38: 50 | I38: PARC. 4/6
E39: 8468 | F39: llian coelho | G39: PIX | H39: 85 | I39: PARC. 5/6
Q40: Total de OS | R40: =SUM(R6:R21) -> 9

Sheet 19
B1: ='18'!B1+1 -> 45462
B2: Fechamento Diário do Caixa
B4: Saldo Inicial | C4: 0 | E4: Vendas | K4: Despesas
B5: Vendas | C5: =SUMIF(I6:I31,">0",H6:H31) -> 3410 | E5: Nº Venda | F5: Cliente | G5: Forma de Pgto | H5: Valor Venda | I5: Entrada | K5: Descrição | L5: Tipo de Pagto | M5: Valor
B6: Entrada | C6: =SUM(I6:I41) -> 1900 | E6: 9378 | F6: luizde araujo | G6: CTC | H6: 590 | I6: 390 | K6: envelopes | L6: dn | M6: 8.9 | R6: =IF(vend19[[#This Row],[Nº Venda]]>1,1,0) -> 1
B7: Despesas | C7: =SUM(M6:M11) -> 8.9 | E7: 9379 | F7: mario nezmah | G7: PIX | H7: 820 | I7: 820 | R7: =IF(vend19[[#This Row],[Nº Venda]]>1,1,0) -> 1
B8: Total entrada | C8: =SUM(C6:C7) -> 1908.9 | E8: 7380 | F8: sarah carolina | G8: DN | H8: 600 | I8: 5 | R8: =IF(vend19[[#This Row],[Nº Venda]]>1,1,0) -> 1
E9: 7381 | F9: sarah carolina | G9: DN | H9: 1400 | I9: 5 | R9: =IF(vend19[[#This Row],[Nº Venda]]>1,1,0) -> 1
B10: Tipos de Pagtos | R10: =IF(vend19[[#This Row],[Nº Venda]]>1,1,0) -> 0
B11: DN | C11: =(SUMIF($G$2:$G$31,B11,$I$2:$I$31))+(SUMIF($G$35:$G$41,B11,$H$35:$H$41)) -> 10 | O11: =IF(C16=0,0,1) -> 1 | R11: =IF(vend19[[#This Row],[Nº Venda]]>1,1,0) -> 0
B12: CTD | C12: =(SUMIF($G$2:$G$31,B12,$I$2:$I$31))+(SUMIF($G$35:$G$41,B12,$H$35:$H$41)) -> 158.55 | R12: =IF(vend19[[#This Row],[Nº Venda]]>1,1,0) -> 0
B13: CTC | C13: =(SUMIF($G$2:$G$31,B13,$I$2:$I$31))+(SUMIF($G$35:$G$41,B13,$H$35:$H$41)) -> 1070 | K13: OS Entregue no Dia | R13: =IF(vend19[[#This Row],[Nº Venda]]>1,1,0) -> 0
B14: PCTC | C14: =(SUMIF($G$2:$G$31,B14,$I$2:$I$31))+(SUMIF($G$35:$G$41,B14,$H$35:$H$41)) -> 0 | K14: OS | L14: Vendedor | M14: CARNE | R14: =IF(vend19[[#This Row],[Nº Venda]]>1,1,0) -> 0
B15: PIX | C15: =(SUMIF($G$2:$G$31,B15,$I$2:$I$31))+(SUMIF($G$35:$G$41,B15,$H$35:$H$41)) -> 820 | K15: 9344 | L15: ariani | M15: Não | R15: =IF(vend19[[#This Row],[Nº Venda]]>1,1,0) -> 0
B16: Total | C16: =SUM(C11:C15) -> 2058.55 | K16: 9324 | L16: ariani | M16: Não | R16: =IF(vend19[[#This Row],[Nº Venda]]>1,1,0) -> 0
R17: =IF(vend19[[#This Row],[Nº Venda]]>1,1,0) -> 0
B18: Entrega de Carne | R18: =IF(vend19[[#This Row],[Nº Venda]]>1,1,0) -> 0
B19: =COUNT(entr_carn19[OS]) -> 0 | C19: =SUM(entr_carn19[Valor Total]) -> 0 | R19: =IF(vend19[[#This Row],[Nº Venda]]>1,1,0) -> 0
B20: Total | C20: =SUM(C19:C19) -> 0 | R20: =IF(vend19[[#This Row],[Nº Venda]]>1,1,0) -> 0
B22: Venda | C22: =C5 -> 3410
E24: Restante Entrada
E25: Nº Venda | F25: Cliente | G25: Forma de Pgto | H25: Valor Venda | I25: Entrada
E26: 9324 | F26: massae yonamine | G26: CTC | H26: 0 | I26: 680
E33: Recebimento de Carnê | K33: Entrega de Carne
E34: OS | F34: Cliente | G34: Forma de Pgto | H34: Valor Parcela | I34: Nº Parcela | K34: OS | L34: Parcelas | M34: Valor Total
E35: 8862 | F35: sebastiao pereira | G35: CTD | H35: 158.55 | I35: PARC. 2/9
Q40: Total de OS | R40: =SUM(R6:R21) -> 4

Sheet 20
B1: ='19'!B1+1 -> 45463
B2: Fechamento Diário do Caixa
B4: Saldo Inicial | C4: 0 | E4: Vendas | K4: Despesas
B5: Vendas | C5: =SUMIF(I6:I31,">0",H6:H31) -> 650 | E5: Nº Venda | F5: Cliente | G5: Forma de Pgto | H5: Valor Venda | I5: Entrada | K5: Descrição | L5: Tipo de Pagto | M5: Valor
B6: Entrada | C6: =SUM(I6:I41) -> 1170 | E6: 9382 | F6: hendrix willian | G6: CTC | H6: 400 | I6: 400 | R6: =IF(vend20[[#This Row],[Nº Venda]]>1,1,0) -> 1
B7: Despesas | C7: =SUM(M6:M11) -> 0 | E7: 9383 | F7: manuela auzebio | G7: CTD | H7: 250 | I7: 250 | R7: =IF(vend20[[#This Row],[Nº Venda]]>1,1,0) -> 1
B8: Total entrada | C8: =SUM(C6:C7) -> 1170 | R8: =IF(vend20[[#This Row],[Nº Venda]]>1,1,0) -> 0
R9: =IF(vend20[[#This Row],[Nº Venda]]>1,1,0) -> 0
B10: Tipos de Pagtos | R10: =IF(vend20[[#This Row],[Nº Venda]]>1,1,0) -> 0
B11: DN | C11: =(SUMIF($G$2:$G$31,B11,$I$2:$I$31))+(SUMIF($G$35:$G$41,B11,$H$35:$H$41)) -> 0 | O11: =IF(C16=0,0,1) -> 1 | R11: =IF(vend20[[#This Row],[Nº Venda]]>1,1,0) -> 0
B12: CTD | C12: =(SUMIF($G$2:$G$31,B12,$I$2:$I$31))+(SUMIF($G$35:$G$41,B12,$H$35:$H$41)) -> 691.48 | R12: =IF(vend20[[#This Row],[Nº Venda]]>1,1,0) -> 0
B13: CTC | C13: =(SUMIF($G$2:$G$31,B13,$I$2:$I$31))+(SUMIF($G$35:$G$41,B13,$H$35:$H$41)) -> 478.52 | K13: OS Entregue no Dia | R13: =IF(vend20[[#This Row],[Nº Venda]]>1,1,0) -> 0
B14: PCTC | C14: =(SUMIF($G$2:$G$31,B14,$I$2:$I$31))+(SUMIF($G$35:$G$41,B14,$H$35:$H$41)) -> 0 | K14: OS | L14: Vendedor | M14: CARNE | R14: =IF(vend20[[#This Row],[Nº Venda]]>1,1,0) -> 0
B15: PIX | C15: =(SUMIF($G$2:$G$31,B15,$I$2:$I$31))+(SUMIF($G$35:$G$41,B15,$H$35:$H$41)) -> 170 | K15: 9369 | L15: jocy | M15: Não | R15: =IF(vend20[[#This Row],[Nº Venda]]>1,1,0) -> 0
B16: Total | C16: =SUM(C11:C15) -> 1340 | K16: 9369 | L16: ariani | M16: Sim | R16: =IF(vend20[[#This Row],[Nº Venda]]>1,1,0) -> 0
K17: 9303 | L17: jocy | M17: Sim | R17: =IF(vend20[[#This Row],[Nº Venda]]>1,1,0) -> 0
B18: Entrega de Carne | K18: 9307 | L18: ariani | M18: Sim | R18: =IF(vend20[[#This Row],[Nº Venda]]>1,1,0) -> 0
B19: =COUNT(entr_carn20[OS]) -> 3 | C19: =SUM(entr_carn20[Valor Total]) -> 2050 | R19: =IF(vend20[[#This Row],[Nº Venda]]>1,1,0) -> 0
B20: Total | C20: =SUM(C19:C19) -> 2050 | R20: =IF(vend20[[#This Row],[Nº Venda]]>1,1,0) -> 0
B22: Venda | C22: =C5 -> 650
E24: Restante Entrada
E25: Nº Venda | F25: Cliente | G25: Forma de Pgto | H25: Valor Venda | I25: Entrada
E26: 9375 | F26: carmelina | G26: CTD | H26: 0 | I26: 241.48
E27: 9375 | F27: carmelina | G27: CTC | H27: 0 | I27: 78.52
E28: 9307 | F28: edneusa aparecida | G28: CTD | H28: 0 | I28: 200
E33: Recebimento de Carnê | K33: Entrega de Carne
E34: OS | F34: Cliente | G34: Forma de Pgto | H34: Valor Parcela | I34: Nº Parcela | K34: OS | L34: Parcelas | M34: Valor Total
E35: 8468 | F35: liliane coelho | G35: PIX | H35: 85 | I35: PARC. 4/6 | K35: 9308 | L35: 6 | M35: 1000
E36: 8468 | F36: liliane coelho | G36: PIX | H36: 85 | I36: PARC. 5/6 | K36: 9003 | L36: 3 | M36: 350
K37: 9307 | L37: 6 | M37: 700
Q40: Total de OS | R40: =SUM(R6:R21) -> 2

Sheet 21
B1: ='20'!B1+1 -> 45464
B2: Fechamento Diário do Caixa
B4: Saldo Inicial | C4: 0 | E4: Vendas | K4: Despesas
B5: Vendas | C5: =SUMIF(I6:I31,">0",H6:H31) -> 7538.99 | E5: Nº Venda | F5: Cliente | G5: Forma de Pgto | H5: Valor Venda | I5: Entrada | K5: Descrição | L5: Tipo de Pagto | M5: Valor
B6: Entrada | C6: =SUM(I6:I41) -> 4693.99 | E6: 9385 | F6: SHIRLEI FACULDADE | G6: PIX | H6: 500 | I6: 250 | R6: =IF(vend21[[#This Row],[Nº Venda]]>1,1,0) -> 1
B7: Despesas | C7: =SUM(M6:M11) -> 0 | E7: 9386 | F7: FREDERICO MASASH | G7: DN | H7: 270 | I7: 25 | R7: =IF(vend21[[#This Row],[Nº Venda]]>1,1,0) -> 1
B8: Total entrada | C8: =SUM(C6:C7) -> 4693.99 | E8: 9387 | F8: WILSON BRAGA | G8: CTC | H8: 2100 | I8: 2100 | R8: =IF(vend21[[#This Row],[Nº Venda]]>1,1,0) -> 1
E9: 9388 | F9: FREDERICO MASASH | G9: DN | H9: 429 | I9: 25 | R9: =IF(vend21[[#This Row],[Nº Venda]]>1,1,0) -> 1
B10: Tipos de Pagtos | E10: 9389 | F10: NOEMI REGINA | G10: CTD | H10: 39.99 | I10: 39.99 | R10: =IF(vend21[[#This Row],[Nº Venda]]>1,1,0) -> 1
B11: DN | C11: =(SUMIF($G$2:$G$31,B11,$I$2:$I$31))+(SUMIF($G$35:$G$41,B11,$H$35:$H$41)) -> 1200 | E11: 9390 | F11: PAULO DO CARMO | G11: DN | H11: 550 | I11: 50 | O11: =IF(C16=0,0,1) -> 1 | R11: =IF(vend21[[#This Row],[Nº Venda]]>1,1,0) -> 1
B12: CTD | C12: =(SUMIF($G$2:$G$31,B12,$I$2:$I$31))+(SUMIF($G$35:$G$41,B12,$H$35:$H$41)) -> 559.99 | E12: 9391 | F12: MATHEUS LEONARDO | G12: DN | H12: 1000 | I12: 1000 | R12: =IF(vend21[[#This Row],[Nº Venda]]>1,1,0) -> 1
B13: CTC | C13: =(SUMIF($G$2:$G$31,B13,$I$2:$I$31))+(SUMIF($G$35:$G$41,B13,$H$35:$H$41)) -> 2984 | E13: 9392 | F13: MARIA ALVES | G13: DN | H13: 700 | I13: 50 | K13: OS Entregue no Dia | R13: =IF(vend21[[#This Row],[Nº Venda]]>1,1,0) -> 1
B14: PCTC | C14: =(SUMIF($G$2:$G$31,B14,$I$2:$I$31))+(SUMIF($G$35:$G$41,B14,$H$35:$H$41)) -> 0 | E14: 9393 | F14: MARIA ALVES | G14: DN | H14: 500 | I14: 50 | K14: OS | L14: Vendedor | M14: CARNE | R14: =IF(vend21[[#This Row],[Nº Venda]]>1,1,0) -> 1
B15: PIX | C15: =(SUMIF($G$2:$G$31,B15,$I$2:$I$31))+(SUMIF($G$35:$G$41,B15,$H$35:$H$41)) -> 387.5 | E15: 9394 | F15: CARLOS ALBERTO | G15: CTD | H15: 1299 | I15: 200 | K15: 9389 | L15: JOCY | M15: Não | R15: =IF(vend21[[#This Row],[Nº Venda]]>1,1,0) -> 1
B16: Total | C16: =SUM(C11:C15) -> 5131.49 | E16: 9395 | F16: CARLOS ALBERTO | G16: CTD | H16: 151 | I16: 20 | K16: 9349 | L16: ARIANI | M16: Não | R16: =IF(vend21[[#This Row],[Nº Venda]]>1,1,0) -> 1
R17: =IF(vend21[[#This Row],[Nº Venda]]>1,1,0) -> 0
B18: Entrega de Carne | R18: =IF(vend21[[#This Row],[Nº Venda]]>1,1,0) -> 0
B19: =COUNT(entr_carn21[OS]) -> 0 | C19: =SUM(entr_carn21[Valor Total]) -> 0 | R19: =IF(vend21[[#This Row],[Nº Venda]]>1,1,0) -> 0
B20: Total | C20: =SUM(C19:C19) -> 0 | R20: =IF(vend21[[#This Row],[Nº Venda]]>1,1,0) -> 0
B22: Venda | C22: =C5 -> 7538.99
E24: Restante Entrada
E25: Nº Venda | F25: Cliente | G25: Forma de Pgto | H25: Valor Venda | I25: Entrada
E26: 9373 | F26: NOEMI REGINA | G26: CTC | H26: 0 | I26: 884
E33: Recebimento de Carnê | K33: Entrega de Carne
E34: OS | F34: Cliente | G34: Forma de Pgto | H34: Valor Parcela | I34: Nº Parcela | K34: OS | L34: Parcelas | M34: Valor Total
E35: 3871 | F35: JUAN NILSON | G35: PIX | H35: 137.5 | I35: PARC. 3/8
E36: 8885 | F36: ZENILVA AUGUSTA | G36: CTD | H36: 300 | I36: PARC. 2/5
Q40: Total de OS | R40: =SUM(R6:R21) -> 11

Sheet 22
B1: ='21'!B1+1 -> 45465
B2: Fechamento Diário do Caixa
B4: Saldo Inicial | C4: 0 | E4: Vendas | K4: Despesas
B5: Vendas | C5: =SUMIF(I6:I31,">0",H6:H31) -> 1500 | E5: Nº Venda | F5: Cliente | G5: Forma de Pgto | H5: Valor Venda | I5: Entrada | K5: Descrição | L5: Tipo de Pagto | M5: Valor
B6: Entrada | C6: =SUM(I6:I41) -> 850 | E6: 9396 | F6: alercio serafim | G6: CTC | H6: 1500 | I6: 800 | R6: =IF(vend22[[#This Row],[Nº Venda]]>1,1,0) -> 1
B7: Despesas | C7: =SUM(M6:M11) -> 0 | R7: =IF(vend22[[#This Row],[Nº Venda]]>1,1,0) -> 0
B8: Total entrada | C8: =SUM(C6:C7) -> 850 | R8: =IF(vend22[[#This Row],[Nº Venda]]>1,1,0) -> 0
R9: =IF(vend22[[#This Row],[Nº Venda]]>1,1,0) -> 0
B10: Tipos de Pagtos | R10: =IF(vend22[[#This Row],[Nº Venda]]>1,1,0) -> 0
B11: DN | C11: =(SUMIF($G$2:$G$31,B11,$I$2:$I$31))+(SUMIF($G$35:$G$41,B11,$H$35:$H$41)) -> 0 | O11: =IF(C16=0,0,1) -> 1 | R11: =IF(vend22[[#This Row],[Nº Venda]]>1,1,0) -> 0
B12: CTD | C12: =(SUMIF($G$2:$G$31,B12,$I$2:$I$31))+(SUMIF($G$35:$G$41,B12,$H$35:$H$41)) -> 0 | R12: =IF(vend22[[#This Row],[Nº Venda]]>1,1,0) -> 0
B13: CTC | C13: =(SUMIF($G$2:$G$31,B13,$I$2:$I$31))+(SUMIF($G$35:$G$41,B13,$H$35:$H$41)) -> 800 | K13: OS Entregue no Dia | R13: =IF(vend22[[#This Row],[Nº Venda]]>1,1,0) -> 0
B14: PCTC | C14: =(SUMIF($G$2:$G$31,B14,$I$2:$I$31))+(SUMIF($G$35:$G$41,B14,$H$35:$H$41)) -> 0 | K14: OS | L14: Vendedor | M14: CARNE | R14: =IF(vend22[[#This Row],[Nº Venda]]>1,1,0) -> 0
B15: PIX | C15: =(SUMIF($G$2:$G$31,B15,$I$2:$I$31))+(SUMIF($G$35:$G$41,B15,$H$35:$H$41)) -> 421 | K15: 9342 | L15: ariani | M15: Sim | R15: =IF(vend22[[#This Row],[Nº Venda]]>1,1,0) -> 0
B16: Total | C16: =SUM(C11:C15) -> 1221 | K16: 9379 | L16: ariani | M16: Não | R16: =IF(vend22[[#This Row],[Nº Venda]]>1,1,0) -> 0
K17: 9339 | L17: jocy | M17: Não | R17: =IF(vend22[[#This Row],[Nº Venda]]>1,1,0) -> 0
B18: Entrega de Carne | K18: 9285 | L18: jocy | M18: Não | R18: =IF(vend22[[#This Row],[Nº Venda]]>1,1,0) -> 0
B19: =COUNT(entr_carn22[OS]) -> 1 | C19: =SUM(entr_carn22[Valor Total]) -> 350 | R19: =IF(vend22[[#This Row],[Nº Venda]]>1,1,0) -> 0
B20: Total | C20: =SUM(C19:C19) -> 350 | R20: =IF(vend22[[#This Row],[Nº Venda]]>1,1,0) -> 0
B22: Venda | C22: =C5 -> 1500
E24: Restante Entrada
E25: Nº Venda | F25: Cliente | G25: Forma de Pgto | H25: Valor Venda | I25: Entrada
E26: 9342 | F26: fabiana alves | G26: PIX | H26: 0 | I26: 50
E33: Recebimento de Carnê | K33: Entrega de Carne
E34: OS | F34: Cliente | G34: Forma de Pgto | H34: Valor Parcela | I34: Nº Parcela | K34: OS | L34: Parcelas | M34: Valor Total
E35: 8337 | F35: valdenice dias | G35: PIX | H35: 100 | I35: PARC. 3/4 | K35: 9342 | L35: 6 | M35: 350
E36: 8487 | F36: bruno da silva | G36: PIX | H36: 85 | I36: PARC. 6/6
E37: 8248 | F37: thais eduarda | G37: PIX | H37: 93 | I37: PARC. 6/7
E38: 8248 | F38: thais eduarda | G38: PIX | H38: 93 | I38: PARC. 7/7
Q40: Total de OS | R40: =SUM(R6:R21) -> 1

Sheet 23
B1: ='22'!B1+1 -> 45466
B2: Fechamento Diário do Caixa
B4: Saldo Inicial | C4: 0 | E4: Vendas | K4: Despesas
B5: Vendas | C5: =SUMIF(I6:I31,">0",H6:H31) -> 0 | E5: Nº Venda | F5: Cliente | G5: Forma de Pgto | H5: Valor Venda | I5: Entrada | K5: Descrição | L5: Tipo de Pagto | M5: Valor
B6: Entrada | C6: =SUM(I6:I41) -> 0 | R6: =IF(vend23[[#This Row],[Nº Venda]]>1,1,0) -> 0
B7: Despesas | C7: =SUM(M6:M11) -> 0 | R7: =IF(vend23[[#This Row],[Nº Venda]]>1,1,0) -> 0
B8: Total entrada | C8: =SUM(C6:C7) -> 0 | R8: =IF(vend23[[#This Row],[Nº Venda]]>1,1,0) -> 0
R9: =IF(vend23[[#This Row],[Nº Venda]]>1,1,0) -> 0
B10: Tipos de Pagtos | R10: =IF(vend23[[#This Row],[Nº Venda]]>1,1,0) -> 0
B11: DN | C11: =(SUMIF($G$2:$G$31,B11,$I$2:$I$31))+(SUMIF($G$35:$G$44,B11,$H$35:$H$44)) -> 0 | O11: =IF(C16=0,0,1) -> 0 | R11: =IF(vend23[[#This Row],[Nº Venda]]>1,1,0) -> 0
B12: CTD | C12: =(SUMIF($G$2:$G$31,B12,$I$2:$I$31))+(SUMIF($G$35:$G$44,B12,$H$35:$H$44)) -> 0 | R12: =IF(vend23[[#This Row],[Nº Venda]]>1,1,0) -> 0
B13: CTC | C13: =(SUMIF($G$2:$G$31,B13,$I$2:$I$31))+(SUMIF($G$35:$G$44,B13,$H$35:$H$44)) -> 0 | K13: OS Entregue no Dia | R13: =IF(vend23[[#This Row],[Nº Venda]]>1,1,0) -> 0
B14: PCTC | C14: =(SUMIF($G$2:$G$31,B14,$I$2:$I$31))+(SUMIF($G$35:$G$44,B14,$H$35:$H$44)) -> 0 | K14: OS | L14: Vendedor | M14: CARNE | R14: =IF(vend23[[#This Row],[Nº Venda]]>1,1,0) -> 0
B15: PIX | C15: =(SUMIF($G$2:$G$31,B15,$I$2:$I$31))+(SUMIF($G$35:$G$44,B15,$H$35:$H$44)) -> 0 | R15: =IF(vend23[[#This Row],[Nº Venda]]>1,1,0) -> 0
B16: Total | C16: =SUM(C11:C15) -> 0 | R16: =IF(vend23[[#This Row],[Nº Venda]]>1,1,0) -> 0
R17: =IF(vend23[[#This Row],[Nº Venda]]>1,1,0) -> 0
B18: Entrega de Carne | R18: =IF(vend23[[#This Row],[Nº Venda]]>1,1,0) -> 0
B19: =COUNT(entr_carn23[OS]) -> 0 | C19: =SUM(entr_carn23[Valor Total]) -> 0 | R19: =IF(vend23[[#This Row],[Nº Venda]]>1,1,0) -> 0
B20: Total | C20: =SUM(C19:C19) -> 0 | R20: =IF(vend23[[#This Row],[Nº Venda]]>1,1,0) -> 0
B22: Venda | C22: =C5 -> 0
E24: Restante Entrada
E25: Nº Venda | F25: Cliente | G25: Forma de Pgto | H25: Valor Venda | I25: Entrada
E33: Recebimento de Carnê | K33: Entrega de Carne
E34: OS | F34: Cliente | G34: Forma de Pgto | H34: Valor Parcela | I34: Nº Parcela | K34: OS | L34: Parcelas | M34: Valor Total
Q40: Total de OS | R40: =SUM(R6:R21) -> 0

Sheet 24
B1: ='23'!B1+1 -> 45467
B2: Fechamento Diário do Caixa
B4: Saldo Inicial | C4: 0 | E4: Vendas | K4: Despesas
B5: Vendas | C5: =SUMIF(I6:I31,">0",H6:H31) -> 5709 | E5: Nº Venda | F5: Cliente | G5: Forma de Pgto | H5: Valor Venda | I5: Entrada | K5: Descrição | L5: Tipo de Pagto | M5: Valor
B6: Entrada | C6: =SUM(I6:I41) -> 3369 | E6: 9397 | F6: manuel liberati | G6: GARANTIA | R6: =IF(vend24[[#This Row],[Nº Venda]]>1,1,0) -> 1
B7: Despesas | C7: =SUM(M6:M11) -> 0 | E7: 9398 | F7: ivanildo carvalho | G7: CTC | H7: 700 | I7: 200 | R7: =IF(vend24[[#This Row],[Nº Venda]]>1,1,0) -> 1
B8: Total entrada | C8: =SUM(C6:C7) -> 3369 | E8: 9399 | F8: maria neide | G8: DN | H8: 350 | I8: 50 | R8: =IF(vend24[[#This Row],[Nº Venda]]>1,1,0) -> 1
E9: 9400 | F9: gabriele rosa | G9: DN | H9: 850 | I9: 10 | R9: =IF(vend24[[#This Row],[Nº Venda]]>1,1,0) -> 1
B10: Tipos de Pagtos | E10: 9401 | F10: silvia regina | G10: CTC | H10: 1200 | I10: 500 | R10: =IF(vend24[[#This Row],[Nº Venda]]>1,1,0) -> 1
B11: DN | C11: =(SUMIF($G$2:$G$31,B11,$I$2:$I$31))+(SUMIF($G$35:$G$41,B11,$H$35:$H$41)) -> 70 | E11: 9402 | F11: carolina setti | G11: CTC | H11: 600 | I11: 600 | O11: =IF(C16=0,0,1) -> 1 | R11: =IF(vend24[[#This Row],[Nº Venda]]>1,1,0) -> 1
B12: CTD | C12: =(SUMIF($G$2:$G$31,B12,$I$2:$I$31))+(SUMIF($G$35:$G$41,B12,$H$35:$H$41)) -> 99 | E12: 9403 | F12: carolina setti | G12: CTC | H12: 600 | I12: 600 | R12: =IF(vend24[[#This Row],[Nº Venda]]>1,1,0) -> 1
B13: CTC | C13: =(SUMIF($G$2:$G$31,B13,$I$2:$I$31))+(SUMIF($G$35:$G$41,B13,$H$35:$H$41)) -> 3119 | E13: 9404 | F13: carolina setti | G13: CTC | H13: 270 | I13: 270 | K13: OS Entregue no Dia | R13: =IF(vend24[[#This Row],[Nº Venda]]>1,1,0) -> 1
B14: PCTC | C14: =(SUMIF($G$2:$G$31,B14,$I$2:$I$31))+(SUMIF($G$35:$G$41,B14,$H$35:$H$41)) -> 0 | E14: 9405 | F14: carolina setti | G14: CTC | H14: 99 | I14: 99 | K14: OS | L14: Vendedor | M14: CARNE | R14: =IF(vend24[[#This Row],[Nº Venda]]>1,1,0) -> 1
B15: PIX | C15: =(SUMIF($G$2:$G$31,B15,$I$2:$I$31))+(SUMIF($G$35:$G$41,B15,$H$35:$H$41)) -> 475 | E15: 9406 | F15: joselma ferreira | G15: CTC | H15: 850 | I15: 850 | K15: 9355 | L15: jocy | M15: Não | R15: =IF(vend24[[#This Row],[Nº Venda]]>1,1,0) -> 1
B16: Total | C16: =SUM(C11:C15) -> 3763 | E16: 9407 | F16: joselma ferreira | G16: CTC | H16: 0 | I16: 0 | K16: 9238 | L16: taty | M16: Não | R16: =IF(vend24[[#This Row],[Nº Venda]]>1,1,0) -> 1
E17: 9408 | F17: veronice ciberlina | G17: DN | H17: 40 | I17: 10 | R17: =IF(vend24[[#This Row],[Nº Venda]]>1,1,0) -> 1
B18: Entrega de Carne | E18: 9408 | F18: veronice ciberlina | G18: CTD | H18: 0 | I18: 30 | R18: =IF(vend24[[#This Row],[Nº Venda]]>1,1,0) -> 1
B19: =COUNT(entr_carn24[OS]) -> 0 | C19: =SUM(entr_carn24[Valor Total]) -> 0 | E19: 9409 | F19: marcos luis gusmão | G19: PIX | H19: 150 | I19: 150 | R19: =IF(vend24[[#This Row],[Nº Venda]]>1,1,0) -> 1
B20: Total | C20: =SUM(C19:C19) -> 0 | R20: =IF(vend24[[#This Row],[Nº Venda]]>1,1,0) -> 0
B22: Venda | C22: =C5 -> 5709
E24: Restante Entrada
E25: Nº Venda | F25: Cliente | G25: Forma de Pgto | H25: Valor Venda | I25: Entrada
E33: Recebimento de Carnê | K33: Entrega de Carne
E34: OS | F34: Cliente | G34: Forma de Pgto | H34: Valor Parcela | I34: Nº Parcela | K34: OS | L34: Parcelas | M34: Valor Total
E35: 9200 | F35: andre alves | G35: CTD | H35: 69 | I35: PARC. 5/6
E36: 7675 | F36: camila andrade | G36: PIX | H36: 325 | I36: PARC. 8/8
Q40: Total de OS | R40: =SUM(R6:R21) -> 14

Sheet 25
B1: ='24'!B1+1 -> 45468
B2: Fechamento Diário do Caixa
B4: Saldo Inicial | C4: 0 | E4: Vendas | K4: Despesas
B5: Vendas | C5: =SUMIF(I6:I31,">0",H6:H31) -> 430 | E5: Nº Venda | F5: Cliente | G5: Forma de Pgto | H5: Valor Venda | I5: Entrada | K5: Descrição | L5: Tipo de Pagto | M5: Valor
B6: Entrada | C6: =SUM(I6:I41) -> 895 | E6: 9410 | F6: rita de cassia | G6: CTC | H6: 200 | I6: 200 | R6: =IF(vend26[[#This Row],[Nº Venda]]>1,1,0) -> 1
B7: Despesas | C7: =SUM(M6:M11) -> 0 | E7: 9411 | F7: simone fragnan | G7: GARANTIA | R7: =IF(vend26[[#This Row],[Nº Venda]]>1,1,0) -> 1
B8: Total entrada | C8: =SUM(C6:C7) -> 895 | E8: 9412 | F8: gustavo andrade | G8: PIX | H8: 40 | I8: 40 | R8: =IF(vend26[[#This Row],[Nº Venda]]>1,1,0) -> 1
E9: 9413 | F9: simone fragnan | G9: GARANTIA | R9: =IF(vend26[[#This Row],[Nº Venda]]>1,1,0) -> 1
B10: Tipos de Pagtos | E10: 9414 | F10: rosana mabel | G10: PIX | H10: 40 | I10: 40 | R10: =IF(vend26[[#This Row],[Nº Venda]]>1,1,0) -> 1
B11: DN | C11: =(SUMIF($G$2:$G$31,B11,$I$2:$I$31))+(SUMIF($G$35:$G$41,B11,$H$35:$H$41)) -> 196 | E11: 9415 | F11: paulo barbosa | G11: PIX | H11: 150 | I11: 150 | O11: =IF(C16=0,0,1) -> 1 | R11: =IF(vend26[[#This Row],[Nº Venda]]>1,1,0) -> 1
B12: CTD | C12: =(SUMIF($G$2:$G$31,B12,$I$2:$I$31))+(SUMIF($G$35:$G$41,B12,$H$35:$H$41)) -> 340 | R12: =IF(vend26[[#This Row],[Nº Venda]]>1,1,0) -> 0
B13: CTC | C13: =(SUMIF($G$2:$G$31,B13,$I$2:$I$31))+(SUMIF($G$35:$G$41,B13,$H$35:$H$41)) -> 200 | K13: OS Entregue no Dia | R13: =IF(vend26[[#This Row],[Nº Venda]]>1,1,0) -> 0
B14: PCTC | C14: =(SUMIF($G$2:$G$31,B14,$I$2:$I$31))+(SUMIF($G$35:$G$41,B14,$H$35:$H$41)) -> 0 | K14: OS | L14: Vendedor | M14: CARNE | R14: =IF(vend26[[#This Row],[Nº Venda]]>1,1,0) -> 0
B15: PIX | C15: =(SUMIF($G$2:$G$31,B15,$I$2:$I$31))+(SUMIF($G$35:$G$41,B15,$H$35:$H$41)) -> 355 | K15: 9242 | L15: jocy | M15: Sim | R15: =IF(vend26[[#This Row],[Nº Venda]]>1,1,0) -> 0
B16: Total | C16: =SUM(C11:C15) -> 1091 | K16: 9243 | L16: jocy | M16: Não | R16: =IF(vend26[[#This Row],[Nº Venda]]>1,1,0) -> 0
K17: 9347 | L17: ariani | M17: Não | R17: =IF(vend26[[#This Row],[Nº Venda]]>1,1,0) -> 0
B18: Entrega de Carne | K18: 9346 | L18: jocy | M18: Não | R18: =IF(vend26[[#This Row],[Nº Venda]]>1,1,0) -> 0
B19: =COUNT(entr_carn26[OS]) -> 2 | C19: =SUM(entr_carn26[Valor Total]) -> 1204 | K19: 9397 | L19: ariani | M19: Não | R19: =IF(vend26[[#This Row],[Nº Venda]]>1,1,0) -> 0
B20: Total | C20: =SUM(C19:C19) -> 1204 | K20: 9415 | L20: jocy | M20: Não | R20: =IF(vend26[[#This Row],[Nº Venda]]>1,1,0) -> 0
K21: 9305 | L21: ariani | M21: Sim
B22: Venda | C22: =C5 -> 430
E24: Restante Entrada
E25: Nº Venda | F25: Cliente | G25: Forma de Pgto | H25: Valor Venda | I25: Entrada
E26: 9028 | F26: RENILZA DA SILVA | G26: PIX | H26: 0 | I26: 125
E27: 9305 | F27: ailton barbosa | G27: CTD | H27: 0 | I27: 240
E28: 9388 | F28: frederico masashi | G28: CTD | H28: 0 | I28: 100
E33: Recebimento de Carnê | K33: Entrega de Carne
E34: OS | F34: Cliente | G34: Forma de Pgto | H34: Valor Parcela | I34: Nº Parcela | K34: OS | L34: Parcelas | M34: Valor Total
E35: 9242 | F35: helena rodrigues | G35: DN | H35: 196 | I35: PARC. 1/4 | K35: 9242 | L35: 4 | M35: 784
K36: 9305 | L36: 6 | M36: 420
Q40: Total de OS | R40: =SUM(R6:R21) -> 6

Sheet 26
B1: ='25'!B1+1 -> 45469
B2: Fechamento Diário do Caixa
B4: Saldo Inicial | C4: 0 | E4: Vendas | K4: Despesas
B5: Vendas | C5: =SUMIF(I6:I31,">0",H6:H31) -> 1300 | E5: Nº Venda | F5: Cliente | G5: Forma de Pgto | H5: Valor Venda | I5: Entrada | K5: Descrição | L5: Tipo de Pagto | M5: Valor
B6: Entrada | C6: =SUM(I6:I41) -> 1300 | E6: 9416 | F6: lucelia da rocha | G6: SS | H6: 150
B7: Despesas | C7: =SUM(M6:M11) -> 0 | E7: 9417 | F7: manuel liberati | G7: CTC | H7: 250 | I7: 250
B8: Total entrada | C8: =SUM(C6:C7) -> 1300 | E8: 9418 | F8: guiseppe maza | G8: CTC | H8: 900 | I8: 900
B10: Tipos de Pagtos
B11: DN | C11: =(SUMIF($G$2:$G$31,B11,$I$2:$I$31))+(SUMIF($G$35:$G$41,B11,$H$35:$H$41)) -> 130
B12: CTD | C12: =(SUMIF($G$2:$G$31,B12,$I$2:$I$31))+(SUMIF($G$35:$G$41,B12,$H$35:$H$41)) -> 0
B13: CTC | C13: =(SUMIF($G$2:$G$31,B13,$I$2:$I$31))+(SUMIF($G$35:$G$41,B13,$H$35:$H$41)) -> 1300 | K13: OS Entregue no Dia
B14: PCTC | C14: =(SUMIF($G$2:$G$31,B14,$I$2:$I$31))+(SUMIF($G$35:$G$41,B14,$H$35:$H$41)) -> 0 | K14: OS | L14: Vendedor | M14: CARNE
B15: PIX | C15: =(SUMIF($G$2:$G$31,B15,$I$2:$I$31))+(SUMIF($G$35:$G$41,B15,$H$35:$H$41)) -> 425 | K15: 9416 | L15: ariani | M15: Não
B16: Total | C16: =SUM(C11:C15) -> 1855 | K16: 9412 | L16: jocy | M16: Não
K17: 9319 | L17: garantia
B18: Entrega de Carne
B19: =COUNT(entr_carn26211[OS]) -> 0 | C19: =SUM(entr_carn26211[Valor Total]) -> 0
B20: Total | C20: =SUM(C19:C19) -> 0
B22: Venda | C22: =C5 -> 1300
E24: Restante Entrada
E25: Nº Venda | F25: Cliente | G25: Forma de Pgto | H25: Valor Venda | I25: Entrada
E26: 9416 | F26: lucelia da rocha | G26: CTC | H26: 150 | I26: 150
E33: Recebimento de Carnê | K33: Entrega de Carne
E34: OS | F34: Cliente | G34: Forma de Pgto | H34: Valor Parcela | I34: Nº Parcela | K34: OS | L34: Parcelas | M34: Valor Total
E35: 7954 | F35: eliana saboia | G35: PIX | H35: 100 | I35: PARC. 6/7
E36: 9150 | F36: elza de paula | G36: DN | H36: 130 | I36: PARC. 2/5
E37: 9012 | F37: silas diego | G37: PIX | H37: 225 | I37: PARC. 1/8
E38: 9258 | F38: benedito de almeida | G38: PIX | H38: 100 | I38: PARC. 1/6

Sheet 27
B1: ='25'!B1+1 -> 45469
B2: Fechamento Diário do Caixa
B4: Saldo Inicial | C4: 0 | E4: Vendas | K4: Despesas
B5: Vendas | C5: =SUMIF(I6:I31,">0",H6:H31) -> 649 | E5: Nº Venda | F5: Cliente | G5: Forma de Pgto | H5: Valor Venda | I5: Entrada | K5: Descrição | L5: Tipo de Pagto | M5: Valor
B6: Entrada | C6: =SUM(I6:I41) -> 1049 | E6: 9419 | F6: silvia rozendo | G6: CTC | H6: 99 | I6: 99 | R6: =IF(vend27[[#This Row],[Nº Venda]]>1,1,0) -> 1
B7: Despesas | C7: =SUM(M6:M11) -> 0 | E7: 9420 | F7: vera maria | G7: GARANTIA | R7: =IF(vend27[[#This Row],[Nº Venda]]>1,1,0) -> 1
B8: Total entrada | C8: =SUM(C6:C7) -> 1049 | E8: 9421 | F8: rodrigo dos santos | G8: DN | H8: 550 | I8: 550 | R8: =IF(vend27[[#This Row],[Nº Venda]]>1,1,0) -> 1
R9: =IF(vend27[[#This Row],[Nº Venda]]>1,1,0) -> 0
B10: Tipos de Pagtos | R10: =IF(vend27[[#This Row],[Nº Venda]]>1,1,0) -> 0
B11: DN | C11: =(SUMIF($G$2:$G$31,B11,$I$2:$I$31))+(SUMIF($G$35:$G$41,B11,$H$35:$H$41)) -> 950 | O11: =IF(C16=0,0,1) -> 1 | R11: =IF(vend27[[#This Row],[Nº Venda]]>1,1,0) -> 0
B12: CTD | C12: =(SUMIF($G$2:$G$31,B12,$I$2:$I$31))+(SUMIF($G$35:$G$41,B12,$H$35:$H$41)) -> 260 | R12: =IF(vend27[[#This Row],[Nº Venda]]>1,1,0) -> 0
B13: CTC | C13: =(SUMIF($G$2:$G$31,B13,$I$2:$I$31))+(SUMIF($G$35:$G$41,B13,$H$35:$H$41)) -> 99 | K13: OS Entregue no Dia | R13: =IF(vend27[[#This Row],[Nº Venda]]>1,1,0) -> 0
B14: PCTC | C14: =(SUMIF($G$2:$G$31,B14,$I$2:$I$31))+(SUMIF($G$35:$G$41,B14,$H$35:$H$41)) -> 0 | K14: OS | L14: Vendedor | M14: CARNE | R14: =IF(vend27[[#This Row],[Nº Venda]]>1,1,0) -> 0
B15: PIX | C15: =(SUMIF($G$2:$G$31,B15,$I$2:$I$31))+(SUMIF($G$35:$G$41,B15,$H$35:$H$41)) -> 0 | K15: 9354 | L15: jocy | M15: Não | R15: =IF(vend27[[#This Row],[Nº Venda]]>1,1,0) -> 0
B16: Total | C16: =SUM(C11:C15) -> 1309 | R16: =IF(vend27[[#This Row],[Nº Venda]]>1,1,0) -> 0
R17: =IF(vend27[[#This Row],[Nº Venda]]>1,1,0) -> 0
B18: Entrega de Carne | R18: =IF(vend27[[#This Row],[Nº Venda]]>1,1,0) -> 0
B19: =COUNT(entr_carn27[OS]) -> 0 | C19: =SUM(entr_carn27[Valor Total]) -> 0 | R19: =IF(vend27[[#This Row],[Nº Venda]]>1,1,0) -> 0
B20: Total | C20: =SUM(C19:C19) -> 0 | R20: =IF(vend27[[#This Row],[Nº Venda]]>1,1,0) -> 0
B22: Venda | C22: =C5 -> 649
E24: Restante Entrada
E25: Nº Venda | F25: Cliente | G25: Forma de Pgto | H25: Valor Venda | I25: Entrada
E26: 9354 | F26: antonio rodrigues | G26: DN | H26: 0 | I26: 400
E33: Recebimento de Carnê | K33: Entrega de Carne
E34: OS | F34: Cliente | G34: Forma de Pgto | H34: Valor Parcela | I34: Nº Parcela | K34: OS | L34: Parcelas | M34: Valor Total
E35: 8493 | F35: monica miyasshiro | G35: CTD | H35: 130 | I35: PARC. 3/5
E36: 8493 | F36: monica miyasshiro | G36: CTD | H36: 130 | I36: PARC. 4/5
Q40: Total de OS | R40: =SUM(R6:R21) -> 3

Sheet 28
B1: ='27'!B1+1 -> 45470
B2: Fechamento Diário do Caixa
B4: Saldo Inicial | C4: 0 | E4: Vendas | K4: Despesas
B5: Vendas | C5: =SUMIF(I6:I31,">0",H6:H31) -> 9139 | E5: Nº Venda | F5: Cliente | G5: Forma de Pgto | H5: Valor Venda | I5: Entrada | K5: Descrição | L5: Tipo de Pagto | M5: Valor
B6: Entrada | C6: =SUM(I6:I41) -> 6625 | E6: 9422 | F6: douglas shimiz | G6: CTC | H6: 50 | I6: 50 | R6: =IF(vend28[[#This Row],[Nº Venda]]>1,1,0) -> 1
B7: Despesas | C7: =SUM(M6:M11) -> 0 | E7: 9423 | F7: monica mamani | G7: CTC | H7: 40 | I7: 40 | R7: =IF(vend28[[#This Row],[Nº Venda]]>1,1,0) -> 1
B8: Total entrada | C8: =SUM(C6:C7) -> 6625 | E8: 9424 | F8: andrea alves | G8: PIX | H8: 580 | I8: 25 | R8: =IF(vend28[[#This Row],[Nº Venda]]>1,1,0) -> 1
E9: 9425 | F9: andrea alves | G9: PIX | H9: 299 | I9: 25 | R9: =IF(vend28[[#This Row],[Nº Venda]]>1,1,0) -> 1
B10: Tipos de Pagtos | E10: 9426 | F10: gilvania maria | G10: CTC | H10: 700 | I10: 700 | R10: =IF(vend28[[#This Row],[Nº Venda]]>1,1,0) -> 1
B11: DN | C11: =(SUMIF($G$2:$G$31,B11,$I$2:$I$31))+(SUMIF($G$35:$G$41,B11,$H$35:$H$41)) -> 58.33 | E11: 9427 | F11: gilvania maria | G11: CTC | H11: 600 | I11: 600 | O11: =IF(C16=0,0,1) -> 1 | R11: =IF(vend28[[#This Row],[Nº Venda]]>1,1,0) -> 1
B12: CTD | C12: =(SUMIF($G$2:$G$31,B12,$I$2:$I$31))+(SUMIF($G$35:$G$41,B12,$H$35:$H$41)) -> 2460 | E12: 9428 | F12: cicero francisco | G12: PIX | H12: 570 | I12: 400 | R12: =IF(vend28[[#This Row],[Nº Venda]]>1,1,0) -> 1
B13: CTC | C13: =(SUMIF($G$2:$G$31,B13,$I$2:$I$31))+(SUMIF($G$35:$G$41,B13,$H$35:$H$41)) -> 3715 | E13: 9429 | F13: nilson amancio | G13: CTD | H13: 2450 | I13: 2450 | K13: OS Entregue no Dia | R13: =IF(vend28[[#This Row],[Nº Venda]]>1,1,0) -> 1
B14: PCTC | C14: =(SUMIF($G$2:$G$31,B14,$I$2:$I$31))+(SUMIF($G$35:$G$41,B14,$H$35:$H$41)) -> 0 | E14: 9430 | F14: nilson amancio filho | G14: SS | H14: 0 | K14: OS | L14: Vendedor | M14: CARNE | R14: =IF(vend28[[#This Row],[Nº Venda]]>1,1,0) -> 1
B15: PIX | C15: =(SUMIF($G$2:$G$31,B15,$I$2:$I$31))+(SUMIF($G$35:$G$41,B15,$H$35:$H$41)) -> 450 | E15: 9431 | F15: teruyo otami | G15: CTC | H15: 600 | I15: 600 | K15: 9382 | L15: jocy | M15: Não | R15: =IF(vend28[[#This Row],[Nº Venda]]>1,1,0) -> 1
B16: Total | C16: =SUM(C11:C15) -> 6683.33 | E16: 9432 | F16: osmando silveira | G16: CTC | H16: 1050 | I16: 1050 | K16: 9214 | L16: ariani | M16: Não | R16: =IF(vend28[[#This Row],[Nº Venda]]>1,1,0) -> 1
E17: 9433 | F17: jucimeire barbosa | G17: CTD | H17: 2200 | I17: 10 | K17: 9419 | L17: ariani | M17: Não | R17: =IF(vend28[[#This Row],[Nº Venda]]>1,1,0) -> 1
B18: Entrega de Carne | K18: 9364 | L18: ariani | M18: Não | R18: =IF(vend28[[#This Row],[Nº Venda]]>1,1,0) -> 0
B19: =COUNT(entr_carn28[OS]) -> 0 | C19: =SUM(entr_carn28[Valor Total]) -> 0 | K19: 9383 | L19: jocy | M19: Não | R19: =IF(vend28[[#This Row],[Nº Venda]]>1,1,0) -> 0
B20: Total | C20: =SUM(C19:C19) -> 0 | K20: 9420 | L20: jocy | M20: Não | R20: =IF(vend28[[#This Row],[Nº Venda]]>1,1,0) -> 0
K21: 9423 | L21: jocy | M21: Não
B22: Venda | C22: =C5 -> 9139
E24: Restante Entrada
E25: Nº Venda | F25: Cliente | G25: Forma de Pgto | H25: Valor Venda | I25: Entrada
E26: 9214 | F26: vitoriano pereira | G26: CTC | I26: 675
E33: Recebimento de Carnê | K33: Entrega de Carne
E34: OS | F34: Cliente | G34: Forma de Pgto | H34: Valor Parcela | I34: Nº Parcela | K34: OS | L34: Parcelas | M34: Valor Total
E35: 9093 | F35: Veraci heloisa | G35: DN | H35: 58.33 | I35: PARC. 2/6
Q40: Total de OS | R40: =SUM(R6:R21) -> 12

Sheet 29
B1: ='28'!B1+1 -> 45471
B2: Fechamento Diário do Caixa
B4: Saldo Inicial | C4: 0 | E4: Vendas | K4: Despesas
B5: Vendas | C5: =SUMIF(I6:I31,">0",H6:H31) -> 7008 | E5: Nº Venda | F5: Cliente | G5: Forma de Pgto | H5: Valor Venda | I5: Entrada | K5: Descrição | L5: Tipo de Pagto | M5: Valor
B6: Entrada | C6: =SUM(I6:I41) -> 2509 | E6: 9434 | F6: antonio armando | G6: SS | R6: =IF(vend29[[#This Row],[Nº Venda]]>1,1,0) -> 1
B7: Despesas | C7: =SUM(M6:M11) -> 0 | E7: 9435 | F7: stefany aparecida | G7: SS | R7: =IF(vend29[[#This Row],[Nº Venda]]>1,1,0) -> 1
B8: Total entrada | C8: =SUM(C6:C7) -> 2509 | E8: 9436 | F8: luiza jaqueline | G8: CTC | H8: 1399 | I8: 200 | R8: =IF(vend29[[#This Row],[Nº Venda]]>1,1,0) -> 1
E9: 9437 | F9: ana maria | G9: CTC | H9: 300 | I9: 300 | R9: =IF(vend29[[#This Row],[Nº Venda]]>1,1,0) -> 1
B10: Tipos de Pagtos | E10: 9438 | F10: ana cristina | G10: DN | H10: 680 | I10: 600 | R10: =IF(vend29[[#This Row],[Nº Venda]]>1,1,0) -> 1
B11: DN | C11: =(SUMIF($G$2:$G$31,B11,$I$2:$I$31))+(SUMIF($G$35:$G$41,B11,$H$35:$H$41)) -> 600 | E11: 9438 | F11: ana cristina | G11: CTC | I11: 80 | O11: =IF(C16=0,0,1) -> 1 | R11: =IF(vend29[[#This Row],[Nº Venda]]>1,1,0) -> 1
B12: CTD | C12: =(SUMIF($G$2:$G$31,B12,$I$2:$I$31))+(SUMIF($G$35:$G$41,B12,$H$35:$H$41)) -> 0 | E12: 9439 | F12: giovana froes | G12: PIX | H12: 280 | I12: 280 | R12: =IF(vend29[[#This Row],[Nº Venda]]>1,1,0) -> 1
B13: CTC | C13: =(SUMIF($G$2:$G$31,B13,$I$2:$I$31))+(SUMIF($G$35:$G$41,B13,$H$35:$H$41)) -> 580 | E13: 9440 | F13: giovana froes | G13: PIX | H13: 200 | I13: 200 | K13: OS Entregue no Dia | R13: =IF(vend29[[#This Row],[Nº Venda]]>1,1,0) -> 1
B14: PCTC | C14: =(SUMIF($G$2:$G$31,B14,$I$2:$I$31))+(SUMIF($G$35:$G$41,B14,$H$35:$H$41)) -> 0 | E14: 9441 | F14: gilmar lopes | G14: PIX | H14: 1600 | I14: 200 | K14: OS | L14: Vendedor | M14: CARNE | R14: =IF(vend29[[#This Row],[Nº Venda]]>1,1,0) -> 1
B15: PIX | C15: =(SUMIF($G$2:$G$31,B15,$I$2:$I$31))+(SUMIF($G$35:$G$41,B15,$H$35:$H$41)) -> 1466.14 | E15: 9442 | F15: gilmar lopes | G15: PIX | H15: 700 | I15: 100 | K15: 9422 | L15: jocy | M15: Não | R15: =IF(vend29[[#This Row],[Nº Venda]]>1,1,0) -> 1
B16: Total | C16: =SUM(C11:C15) -> 2646.14 | E16: 9443 | F16: gilmar lopes | G16: PIX | H16: 1450 | I16: 150 | K16: 9421 | L16: jocy | M16: Não | R16: =IF(vend29[[#This Row],[Nº Venda]]>1,1,0) -> 1
E17: 9444 | F17: rosimeire silva | G17: PIX | H17: 399 | I17: 399 | R17: =IF(vend29[[#This Row],[Nº Venda]]>1,1,0) -> 1
B18: Entrega de Carne | R18: =IF(vend29[[#This Row],[Nº Venda]]>1,1,0) -> 0
B19: =COUNT(entr_carn29[OS]) -> 0 | C19: =SUM(entr_carn29[Valor Total]) -> 0 | R19: =IF(vend29[[#This Row],[Nº Venda]]>1,1,0) -> 0
B20: Total | C20: =SUM(C19:C19) -> 0 | R20: =IF(vend29[[#This Row],[Nº Venda]]>1,1,0) -> 0
B22: Venda | C22: =C5 -> 7008
E24: Restante Entrada
E25: Nº Venda | F25: Cliente | G25: Forma de Pgto | H25: Valor Venda | I25: Entrada
E33: Recebimento de Carnê | K33: Entrega de Carne
E34: OS | F34: Cliente | G34: Forma de Pgto | H34: Valor Parcela | I34: Nº Parcela | K34: OS | L34: Parcelas | M34: Valor Total
E35: 8456 | F35: gilmar lopes | G35: PIX | H35: 68.57 | I35: PARC. 5/7
E36: 8456 | F36: gilmar lopes | G36: PIX | H36: 68.57 | I36: PARC. 6/7
E37: 8456 | F37: gilmar lopes | G37: PIX | H37: 68,,57 | I37: PARC. 7/7
Q40: Total de OS | R40: =SUM(R6:R21) -> 12

Sheet 30
B1: ='29'!B1+1 -> 45472
B2: Fechamento Diário do Caixa
B4: Saldo Inicial | C4: 0 | E4: Vendas | K4: Despesas
B5: Vendas | C5: =SUMIF(I6:I31,">0",H6:H31) -> 0 | E5: Nº Venda | F5: Cliente | G5: Forma de Pgto | H5: Valor Venda | I5: Entrada | K5: Descrição | L5: Tipo de Pagto | M5: Valor
B6: Entrada | C6: =SUM(I6:I41) -> 0 | R6: =IF(vend30[[#This Row],[Nº Venda]]>1,1,0) -> 0
B7: Despesas | C7: =SUM(M6:M11) -> 0 | R7: =IF(vend30[[#This Row],[Nº Venda]]>1,1,0) -> 0
B8: Total entrada | C8: =SUM(C6:C7) -> 0 | R8: =IF(vend30[[#This Row],[Nº Venda]]>1,1,0) -> 0
R9: =IF(vend30[[#This Row],[Nº Venda]]>1,1,0) -> 0
B10: Tipos de Pagtos | R10: =IF(vend30[[#This Row],[Nº Venda]]>1,1,0) -> 0
B11: DN | C11: =(SUMIF($G$2:$G$31,B11,$I$2:$I$31))+(SUMIF($G$35:$G$41,B11,$H$35:$H$41)) -> 0 | O11: =IF(C16=0,0,1) -> 0 | R11: =IF(vend30[[#This Row],[Nº Venda]]>1,1,0) -> 0
B12: CTD | C12: =(SUMIF($G$2:$G$31,B12,$I$2:$I$31))+(SUMIF($G$35:$G$41,B12,$H$35:$H$41)) -> 0 | R12: =IF(vend30[[#This Row],[Nº Venda]]>1,1,0) -> 0
B13: CTC | C13: =(SUMIF($G$2:$G$31,B13,$I$2:$I$31))+(SUMIF($G$35:$G$41,B13,$H$35:$H$41)) -> 0 | K13: OS Entregue no Dia | R13: =IF(vend30[[#This Row],[Nº Venda]]>1,1,0) -> 0
B14: PCTC | C14: =(SUMIF($G$2:$G$31,B14,$I$2:$I$31))+(SUMIF($G$35:$G$41,B14,$H$35:$H$41)) -> 0 | K14: OS | L14: Vendedor | M14: CARNE | R14: =IF(vend30[[#This Row],[Nº Venda]]>1,1,0) -> 0
B15: PIX | C15: =(SUMIF($G$2:$G$31,B15,$I$2:$I$31))+(SUMIF($G$35:$G$41,B15,$H$35:$H$41)) -> 0 | R15: =IF(vend30[[#This Row],[Nº Venda]]>1,1,0) -> 0
B16: Total | C16: =SUM(C11:C15) -> 0 | R16: =IF(vend30[[#This Row],[Nº Venda]]>1,1,0) -> 0
R17: =IF(vend30[[#This Row],[Nº Venda]]>1,1,0) -> 0
B18: Entrega de Carne | R18: =IF(vend30[[#This Row],[Nº Venda]]>1,1,0) -> 0
B19: =COUNT(entr_carn30[OS]) -> 0 | C19: =SUM(entr_carn30[Valor Total]) -> 0 | R19: =IF(vend30[[#This Row],[Nº Venda]]>1,1,0) -> 0
B20: Total | C20: =SUM(C19:C19) -> 0 | R20: =IF(vend30[[#This Row],[Nº Venda]]>1,1,0) -> 0
B22: Venda | C22: =C5 -> 0
E24: Restante Entrada
E25: Nº Venda | F25: Cliente | G25: Forma de Pgto | H25: Valor Venda | I25: Entrada
E33: Recebimento de Carnê | K33: Entrega de Carne
E34: OS | F34: Cliente | G34: Forma de Pgto | H34: Valor Parcela | I34: Nº Parcela | K34: OS | L34: Parcelas | M34: Valor Total
Q40: Total de OS | R40: =SUM(R6:R21) -> 0

Sheet 31
B1: ='30'!B1+1 -> 45473
B2: Fechamento Diário do Caixa
B4: Saldo Inicial | C4: 0 | E4: Vendas | K4: Despesas
B5: Vendas | C5: =SUMIF(I6:I31,">0",H6:H31) -> 0 | E5: Nº Venda | F5: Cliente | G5: Forma de Pgto | H5: Valor Venda | I5: Entrada | K5: Descrição | L5: Tipo de Pagto | M5: Valor
B6: Entrada | C6: =SUM(I6:I41) -> 0 | R6: =IF(vend31[[#This Row],[Nº Venda]]>1,1,0) -> 0
B7: Despesas | C7: =SUM(M6:M11) -> 0 | R7: =IF(vend31[[#This Row],[Nº Venda]]>1,1,0) -> 0
B8: Total entrada | C8: =SUM(C6:C7) -> 0 | R8: =IF(vend31[[#This Row],[Nº Venda]]>1,1,0) -> 0
R9: =IF(vend31[[#This Row],[Nº Venda]]>1,1,0) -> 0
B10: Tipos de Pagtos | R10: =IF(vend31[[#This Row],[Nº Venda]]>1,1,0) -> 0
B11: DN | C11: =(SUMIF($G$2:$G$31,B11,$I$2:$I$31))+(SUMIF($G$35:$G$41,B11,$H$35:$H$41)) -> 0 | O11: =IF(C16=0,0,1) -> 0 | R11: =IF(vend31[[#This Row],[Nº Venda]]>1,1,0) -> 0
B12: CTD | C12: =(SUMIF($G$2:$G$31,B12,$I$2:$I$31))+(SUMIF($G$35:$G$41,B12,$H$35:$H$41)) -> 0 | R12: =IF(vend31[[#This Row],[Nº Venda]]>1,1,0) -> 0
B13: CTC | C13: =(SUMIF($G$2:$G$31,B13,$I$2:$I$31))+(SUMIF($G$35:$G$41,B13,$H$35:$H$41)) -> 0 | K13: OS Entregue no Dia | R13: =IF(vend31[[#This Row],[Nº Venda]]>1,1,0) -> 0
B14: PCTC | C14: =(SUMIF($G$2:$G$31,B14,$I$2:$I$31))+(SUMIF($G$35:$G$41,B14,$H$35:$H$41)) -> 0 | K14: OS | L14: Vendedor | M14: CARNE | R14: =IF(vend31[[#This Row],[Nº Venda]]>1,1,0) -> 0
B15: PIX | C15: =(SUMIF($G$2:$G$31,B15,$I$2:$I$31))+(SUMIF($G$35:$G$41,B15,$H$35:$H$41)) -> 0 | R15: =IF(vend31[[#This Row],[Nº Venda]]>1,1,0) -> 0
B16: Total | C16: =SUM(C11:C15) -> 0 | R16: =IF(vend31[[#This Row],[Nº Venda]]>1,1,0) -> 0
R17: =IF(vend31[[#This Row],[Nº Venda]]>1,1,0) -> 0
B18: Entrega de Carne | R18: =IF(vend31[[#This Row],[Nº Venda]]>1,1,0) -> 0
B19: =COUNT(entr_carn31[OS]) -> 0 | C19: =SUM(entr_carn31[Valor Total]) -> 0 | R19: =IF(vend31[[#This Row],[Nº Venda]]>1,1,0) -> 0
B20: Total | C20: =SUM(C19:C19) -> 0 | R20: =IF(vend31[[#This Row],[Nº Venda]]>1,1,0) -> 0
B22: Venda | C22: =C5 -> 0
E24: Restante Entrada
E25: Nº Venda | F25: Cliente | G25: Forma de Pgto | H25: Valor Venda | I25: Entrada
E33: Recebimento de Carnê | K33: Entrega de Carne
E34: OS | F34: Cliente | G34: Forma de Pgto | H34: Valor Parcela | I34: Nº Parcela | K34: OS | L34: Parcelas | M34: Valor Total
Q40: Total de OS | R40: =SUM(R6:R21) -> 0

Sheet base
A1: Tipo Pagto | B1: descricao | E1: Parcelas
A2: DN | B2: Dinheiro | E2: PARC. 1/1
A3: CTD | B3: Cartão Débito | E3: PARC. 1/2
A4: CTC | B4: Cartão Crédito | E4: PARC. 2/2
A5: PCTC | B5: Parcelado Cartão Crédito | E5: PARC. 1/3
A6: PIX | B6: PIX | E6: PARC. 2/3
A7: SS | B7: Sem Sinal | E7: PARC. 3/3
A8: CARNE | B8: Carne | E8: PARC. 1/4
A9: GARANTIA | B9: Todas as Garantias | E9: PARC. 2/4
E10: PARC. 3/4
E11: PARC. 4/4
E12: PARC. 1/5
E13: PARC. 2/5
E14: PARC. 3/5
E15: PARC. 4/5
E16: PARC. 5/5
E17: PARC. 1/6
E18: PARC. 2/6
E19: PARC. 3/6
E20: PARC. 4/6
E21: PARC. 5/6
... E79: PARC. 12/12
