Workbook

Sheet resumo_cx
P1: Colaboradores
A2: Saldo Inicial | B2: 0 | P2: ROGÉRIO
A3: Vendas | B3: =SUM('01'!C5,'02'!C5,'03'!C5,'04'!C5,'05'!C5,'06'!C5,'07'!C5,'08'!C5,'09'!C5,'10'!C5,'11'!C5,'12'!C5,'13'!C5,'14'!C5,'15'!C5,'16'!C5,'17'!C5,'18'!C5,'19'!C5,'20'!C5,'21'!C5,'22'!C5,'23'!C5,'24'!C5,'25'!C5,'26'!C5,'27'!C5,'28'!C5,'29'!C5,'30'!C5,'31'!C5) -> 51537.86 | P3: JOCY
A4: Entrada | B4: =SUM('01'!C6,'02'!C6,'03'!C6,'04'!C6,'05'!C6,'06'!C6,'07'!C6,'08'!C6,'09'!C6,'10'!C6,'11'!C6,'12'!C6,'13'!C6,'14'!C6,'15'!C6,'16'!C6,'17'!C6,'18'!C6,'19'!C6,'20'!C6,'21'!C6,'22'!C6,'23'!C6,'24'!C6,'25'!C6,'26'!C6,'27'!C6,'28'!C6,'29'!C6,'30'!C6,'31'!C6) -> 56893.41 | P4: MARIA
A5: Despesas | B5: =SUM('01'!C7,'02'!C7,'03'!C7,'04'!C7,'05'!C7,'06'!C7,'07'!C7,'08'!C7,'09'!C7,'10'!C7,'11'!C7,'12'!C7,'13'!C7,'14'!C7,'15'!C7,'16'!C7,'17'!C7,'18'!C7,'19'!C7,'20'!C7,'21'!C7,'22'!C7,'23'!C7,'24'!C7,'25'!C7,'26'!C7,'27'!C7,'28'!C7,'29'!C7,'30'!C7,'31'!C7) -> 0 | P5: WEVILLY
A6: Entr_Desp | B6: =SUM(B4:B5) -> 56893.41 | P6: BETH
P7: ARIANI
A8: Tipos de Pagtos | P8: ROSÂNGELA
A9: DN | B9: =SUM('01'!C11,'02'!C11,'03'!C11,'04'!C11,'05'!C11,'06'!C11,'07'!C11,'08'!C11,'09'!C11,'10'!C11,'11'!C11,'12'!C11,'13'!C11,'14'!C11,'15'!C11,'16'!C11,'17'!C11,'18'!C11,'19'!C11,'20'!C11,'21'!C11,'22'!C11,'23'!C11,'24'!C11,'25'!C11,'26'!C11,'27'!C11,'28'!C11,'29'!C11,'30'!C11,'31'!C11) -> 3459.2 | P9: TATY
A10: CTD | B10: =SUM('01'!C12,'02'!C12,'03'!C12,'04'!C12,'05'!C12,'06'!C12,'07'!C12,'08'!C12,'09'!C12,'10'!C12,'11'!C12,'12'!C12,'13'!C12,'14'!C12,'15'!C12,'16'!C12,'17'!C12,'18'!C12,'19'!C12,'20'!C12,'21'!C12,'22'!C12,'23'!C12,'24'!C12,'25'!C12,'26'!C12,'27'!C12,'28'!C12,'29'!C12,'30'!C12,'31'!C12) -> 9906.5 | P10: LARISSA
A11: CTC | B11: =SUM('01'!C13,'02'!C13,'03'!C13,'04'!C13,'05'!C13,'06'!C13,'07'!C13,'08'!C13,'09'!C13,'10'!C13,'11'!C13,'12'!C13,'13'!C13,'14'!C13,'15'!C13,'16'!C13,'17'!C13,'18'!C13,'19'!C13,'20'!C13,'21'!C13,'22'!C13,'23'!C13,'24'!C13,'25'!C13,'26'!C13,'27'!C13,'28'!C13,'29'!C13,'30'!C13,'31'!C13) -> 29932.3 | P11: ERIKA
A12: PCTC | B12: =SUM('01'!C14,'02'!C14,'03'!C14,'04'!C14,'05'!C14,'06'!C14,'07'!C14,'08'!C14,'09'!C14,'10'!C14,'11'!C14,'12'!C14,'13'!C14,'14'!C14,'15'!C14,'16'!C14,'17'!C14,'18'!C14,'19'!C14,'20'!C14,'21'!C14,'22'!C14,'23'!C14,'24'!C14,'25'!C14,'26'!C14,'27'!C14,'28'!C14,'29'!C14,'30'!C14,'31'!C14) -> 0 | P12: LUANA
A13: PIX | B13: =SUM('01'!C15,'02'!C15,'03'!C15,'04'!C15,'05'!C15,'06'!C15,'07'!C15,'08'!C15,'09'!C15,'10'!C15,'11'!C15,'12'!C15,'13'!C15,'14'!C15,'15'!C15,'16'!C15,'17'!C15,'18'!C15,'19'!C15,'20'!C15,'21'!C15,'22'!C15,'23'!C15,'24'!C15,'25'!C15,'26'!C15,'27'!C15,'28'!C15,'29'!C15,'30'!C15,'31'!C15) -> 13595.41 | P13: FELIPE
A14: Total | B14: =SUM(B9:B13) -> 56893.41
A16: Entrega de Carne
A17: =COUNT(#REF!) -> 0 | B17: =SUM('01'!C19,'02'!C19,'03'!C19,'04'!C19,'05'!C19,'06'!C19,'07'!C19,'08'!C19,'09'!C19,'10'!C19,'11'!C19,'12'!C19,'13'!C19,'14'!C19,'15'!C19,'16'!C19,'17'!C19,'18'!C19,'19'!C19,'20'!C19,'21'!C19,'22'!C19,'23'!C19,'24'!C19,'25'!C19,'26'!C19,'27'!C19,'28'!C19,'29'!C19,'30'!C19,'31'!C19) -> 3234.99
A18: Total | B18: =SUM(B17:B17) -> 3234.99

Sheet 02
B1: ='01'!B1+1 -> 45718
B2: Fechamento Diário do Caixa
B4: Saldo Inicial | C4: 0 | E4: Vendas | K4: Despesas
B5: Vendas | C5: =SUMIF(I6:I31,">0",H6:H31) -> 0 | E5: Nº Venda | F5: Cliente | G5: Forma de Pgto | H5: Valor Venda | I5: Entrada | K5: Descrição | L5: Tipo de Pagto | M5: Valor
B6: Entrada | C6: =C16 -> 0 | R6: =IF(vend2[[#This Row],[Nº Venda]]>1,1,0) -> 0
B7: Despesas | C7: =SUM(M6:M11) -> 0 | R7: =IF(vend2[[#This Row],[Nº Venda]]>1,1,0) -> 0
B8: Total entrada | C8: =SUM(C6:C7) -> 0 | R8: =IF(vend2[[#This Row],[Nº Venda]]>1,1,0) -> 0
R9: =IF(vend2[[#This Row],[Nº Venda]]>1,1,0) -> 0
B10: Tipos de Pagtos | R10: =IF(vend2[[#This Row],[Nº Venda]]>1,1,0) -> 0
B11: DN | C11: =(SUMIF($G$2:$G$31,B11,$I$2:$I$31))+(SUMIF($G$35:$G$41,B11,$H$35:$H$41)) -> 0 | O11: =IF(C16=0,0,1) -> 0 | R11: =IF(vend2[[#This Row],[Nº Venda]]>1,1,0) -> 0
B12: CTD | C12: =(SUMIF($G$2:$G$31,B12,$I$2:$I$31))+(SUMIF($G$35:$G$41,B12,$H$35:$H$41)) -> 0 | R12: =IF(vend2[[#This Row],[Nº Venda]]>1,1,0) -> 0
B13: CTC | C13: =(SUMIF($G$2:$G$31,B13,$I$2:$I$31))+(SUMIF($G$35:$G$41,B13,$H$35:$H$41)) -> 0 | K13: OS Entregue no Dia | R13: =IF(vend2[[#This Row],[Nº Venda]]>1,1,0) -> 0
B14: PCTC | C14: =(SUMIF($G$2:$G$31,B14,$I$2:$I$31))+(SUMIF($G$35:$G$41,B14,$H$35:$H$41)) -> 0 | K14: OS | L14: Vendedor | M14: CARNE | R14: =IF(vend2[[#This Row],[Nº Venda]]>1,1,0) -> 0
B15: PIX | C15: =(SUMIF($G$2:$G$31,B15,$I$2:$I$31))+(SUMIF($G$35:$G$41,B15,$H$35:$H$41)) -> 0 | R15: =IF(vend2[[#This Row],[Nº Venda]]>1,1,0) -> 0
B16: Total | C16: =SUM(C11:C15) -> 0 | R16: =IF(vend2[[#This Row],[Nº Venda]]>1,1,0) -> 0
R17: =IF(vend2[[#This Row],[Nº Venda]]>1,1,0) -> 0
B18: Entrega de Carne | R18: =IF(vend2[[#This Row],[Nº Venda]]>1,1,0) -> 0
B19: =COUNT(entr_carn2[OS]) -> 0 | C19: =SUM(entr_carn2[Valor Total]) -> 0 | R19: =IF(vend2[[#This Row],[Nº Venda]]>1,1,0) -> 0
B20: Total | C20: =SUM(C19:C19) -> 0 | R20: =IF(vend2[[#This Row],[Nº Venda]]>1,1,0) -> 0
B22: Venda | C22: =C5 -> 0
E24: Restante Entrada
E25: Nº Venda | F25: Cliente | G25: Forma de Pgto | H25: Valor Venda | I25: Entrada
E33: Recebimento de Carnê | K33: Entrega de Carne
E34: OS | F34: Cliente | G34: Forma de Pgto | H34: Valor Parcela | I34: Nº Parcela | K34: OS | L34: Parcelas | M34: Valor Total | U34: V
Q40: Total de OS | R40: =SUM(R6:R21) -> 0

Sheet 01
B1: 45717
B2: Fechamento Diário do Caixa - Escritório
B4: Saldo Inicial | C4: 0 | E4: Vendas | K4: Despesas
B5: Vendas | C5: =SUMIF(I6:I31,">0",H6:H31) -> 1485 | E5: Nº Venda | F5: Cliente | G5: Forma de Pgto | H5: Valor Venda | I5: Entrada | K5: Descrição | L5: Tipo de Pagto | M5: Valor
B6: Entrada | C6: =C16 -> 1566.5 | E6: 10625 | F6: jose roberto de moura | G6: CTC | H6: 105 | I6: 105 | R6: =IF(vend1[[#This Row],[Nº Venda]]>1,1,0) -> 1
B7: Despesas | C7: =SUM(M6:M11) -> 0 | E7: 10626 | F7: andrea cristina | G7: CTD | H7: 245 | I7: 245 | R7: =IF(vend1[[#This Row],[Nº Venda]]>1,1,0) -> 1
B8: Total entrada | C8: =SUM(C6:C7) -> 1566.5 | E8: 10627 | F8: andrea cristina | G8: CTD | H8: 245 | I8: 245 | R8: =IF(vend1[[#This Row],[Nº Venda]]>1,1,0) -> 1
E9: 10628 | F9: jose roberto de moura | G9: CTD | H9: 100 | I9: 100 | R9: =IF(vend1[[#This Row],[Nº Venda]]>1,1,0) -> 1
B10: Tipos de Pagtos | E10: 10629 | F10: aline duarte | G10: PIX | H10: 790 | I10: 200 | R10: =IF(vend1[[#This Row],[Nº Venda]]>1,1,0) -> 1
B11: DN | C11: =(SUMIF($G$2:$G$31,B11,$I$2:$I$31))+(SUMIF($G$35:$G$41,B11,$H$35:$H$41)) -> 0 | O11: =IF(C16=0,0,1) -> 1 | R11: =IF(vend1[[#This Row],[Nº Venda]]>1,1,0) -> 0
B12: CTD | C12: =(SUMIF($G$2:$G$31,B12,$I$2:$I$31))+(SUMIF($G$35:$G$41,B12,$H$35:$H$41)) -> 590 | R12: =IF(vend1[[#This Row],[Nº Venda]]>1,1,0) -> 0
B13: CTC | C13: =(SUMIF($G$2:$G$31,B13,$I$2:$I$31))+(SUMIF($G$35:$G$41,B13,$H$35:$H$41)) -> 604 | K13: OS Entregue no Dia | R13: =IF(vend1[[#This Row],[Nº Venda]]>1,1,0) -> 0
B14: PCTC | C14: =(SUMIF($G$2:$G$31,B14,$I$2:$I$31))+(SUMIF($G$35:$G$41,B14,$H$35:$H$41)) -> 0 | K14: OS | L14: Vendedor | M14: CARNE | R14: =IF(vend1[[#This Row],[Nº Venda]]>1,1,0) -> 0
B15: PIX | C15: =(SUMIF($G$2:$G$31,B15,$I$2:$I$31))+(SUMIF($G$35:$G$41,B15,$H$35:$H$41)) -> 372.5 | K15: 10583 | L15: ROGÉRIO | M15: Não | R15: =IF(vend1[[#This Row],[Nº Venda]]>1,1,0) -> 0
B16: Total | C16: =SUM(C11:C15) -> 1566.5 | K16: 10595 | L16: ROGÉRIO | M16: Não | R16: =IF(vend1[[#This Row],[Nº Venda]]>1,1,0) -> 0
K17: 10388 | L17: TATY | M17: Não | R17: =IF(vend1[[#This Row],[Nº Venda]]>1,1,0) -> 0
B18: Entrega de Carne | K18: 10568 | L18: ROGÉRIO | M18: Não | R18: =IF(vend1[[#This Row],[Nº Venda]]>1,1,0) -> 0
B19: =COUNT(entr_carn1[OS]) -> 0 | C19: =SUM(entr_carn1[Valor Total]) -> 0 | K19: 10628 | L19: ROGÉRIO | M19: Não | R19: =IF(vend1[[#This Row],[Nº Venda]]>1,1,0) -> 0
B20: Total | C20: =SUM(C19:C19) -> 0 | K20: 10569 | L20: ROGÉRIO | M20: Não | R20: =IF(vend1[[#This Row],[Nº Venda]]>1,1,0) -> 0
K21: 10549 | L21: ROGÉRIO | M21: Não
B22: Venda | C22: =C5 -> 1485
E24: Restante Entrada
E25: Nº Venda | F25: Cliente | G25: Forma de Pgto | H25: Valor Venda | I25: Entrada
E26: 10549 | F26: maria imaculada | G26: CTC | I26: 499
E33: Recebimento de Carnê | K33: Entrega de Carne
E34: OS | F34: Cliente | G34: Forma de Pgto | H34: Valor Parcela | I34: Nº Parcela | K34: OS | L34: Parcelas | M34: Valor Total
E35: 9845 | F35: deisyane de castro | G35: PIX | H35: 72.5 | I35: PARC. 5/8
E36: 9565 | F36: victoria nhoque | G36: PIX | H36: 100 | I36: PARC. 7/8
Q40: Total de OS | R40: =SUM(R6:R21) -> 5

Sheet 03
B1: ='02'!B1+1 -> 45719
B2: Fechamento Diário do Caixa
B4: Saldo Inicial | C4: 0 | E4: Vendas | K4: Despesas
B5: Vendas | C5: =SUMIF(I6:I31,">0",H6:H31) -> 1240 | E5: Nº Venda | F5: Cliente | G5: Forma de Pgto | H5: Valor Venda | I5: Entrada | K5: Descrição | L5: Tipo de Pagto | M5: Valor
B6: Entrada | C6: =C16 -> 1746.66 | E6: 10630 | F6: jose ferreira | G6: CTC | H6: 600 | I6: 600 | R6: =IF(vend3[[#This Row],[Nº Venda]]>1,1,0) -> 1
B7: Despesas | C7: =SUM(M6:M11) -> 0 | E7: 10631 | F7: jose ferreira | G7: CTC | H7: 600 | I7: 600 | R7: =IF(vend3[[#This Row],[Nº Venda]]>1,1,0) -> 1
B8: Total entrada | C8: =SUM(C6:C7) -> 1746.66 | E8: 10632 | F8: maria antonia | G8: CTD | H8: 40 | I8: 40 | R8: =IF(vend3[[#This Row],[Nº Venda]]>1,1,0) -> 1
E9: 10633 | F9: maria jose | G9: GARANTIA | H9: 0 | I9: 0 | R9: =IF(vend3[[#This Row],[Nº Venda]]>1,1,0) -> 1
B10: Tipos de Pagtos | R10: =IF(vend3[[#This Row],[Nº Venda]]>1,1,0) -> 0
B11: DN | C11: =(SUMIF($G$2:$G$31,B11,$I$2:$I$31))+(SUMIF($G$35:$G$41,B11,$H$35:$H$41)) -> 130 | O11: =IF(C16=0,0,1) -> 1 | R11: =IF(vend3[[#This Row],[Nº Venda]]>1,1,0) -> 0
B12: CTD | C12: =(SUMIF($G$2:$G$31,B12,$I$2:$I$31))+(SUMIF($G$35:$G$41,B12,$H$35:$H$41)) -> 40 | R12: =IF(vend3[[#This Row],[Nº Venda]]>1,1,0) -> 0
B13: CTC | C13: =(SUMIF($G$2:$G$31,B13,$I$2:$I$31))+(SUMIF($G$35:$G$41,B13,$H$35:$H$41)) -> 1200 | K13: OS Entregue no Dia | R13: =IF(vend3[[#This Row],[Nº Venda]]>1,1,0) -> 0
B14: PCTC | C14: =(SUMIF($G$2:$G$31,B14,$I$2:$I$31))+(SUMIF($G$35:$G$41,B14,$H$35:$H$41)) -> 0 | K14: OS | L14: Vendedor | M14: CARNE | R14: =IF(vend3[[#This Row],[Nº Venda]]>1,1,0) -> 0
B15: PIX | C15: =(SUMIF($G$2:$G$31,B15,$I$2:$I$31))+(SUMIF($G$35:$G$41,B15,$H$35:$H$41)) -> 376.66 | K15: 10495 | L15: ROGÉRIO | M15: Não | R15: =IF(vend3[[#This Row],[Nº Venda]]>1,1,0) -> 0
B16: Total | C16: =SUM(C11:C15) -> 1746.66 | K16: 10536 | L16: ROGÉRIO | M16: Não | R16: =IF(vend3[[#This Row],[Nº Venda]]>1,1,0) -> 0
K17: 10547 | L17: ROGÉRIO | M17: Não | R17: =IF(vend3[[#This Row],[Nº Venda]]>1,1,0) -> 0
B18: Entrega de Carne | K18: 10553 | L18: ROGÉRIO | M18: Sim | R18: =IF(vend3[[#This Row],[Nº Venda]]>1,1,0) -> 0
B19: =COUNT(entr_carn3[OS]) -> 1 | C19: =SUM(entr_carn3[Valor Total]) -> 580 | K19: 10597 | L19: ROGÉRIO | M19: Não | R19: =IF(vend3[[#This Row],[Nº Venda]]>1,1,0) -> 0
B20: Total | C20: =SUM(C19:C19) -> 580 | R20: =IF(vend3[[#This Row],[Nº Venda]]>1,1,0) -> 0
B22: Venda | C22: =C5 -> 1240
E24: Restante Entrada
E25: Nº Venda | F25: Cliente | G25: Forma de Pgto | H25: Valor Venda | I25: Entrada
E26: 10553 | F26: ana paula verginia | G26: PIX | I26: 180
E33: Recebimento de Carnê | K33: Entrega de Carne
E34: OS | F34: Cliente | G34: Forma de Pgto | H34: Valor Parcela | I34: Nº Parcela | K34: OS | L34: Parcelas | M34: Valor Total
E35: 9764 | F35: elisangela alves | G35: DN | H35: 130 | I35: PARC. 5/6 | K35: 10553 | M35: 580
E36: 9764 | F36: elisangela alves | G36: PIX | H36: 36.66 | I36: PARC. 5/6
E37: 9800 | F37: sueli ribeiro | G37: PIX | H37: 92 | I37: PARC. 5/6
E38: 10125 | F38: jaqueline melo | G38: PIX | H38: 68 | I38: PARC. 2/6
Q40: Total de OS | R40: =SUM(R6:R21) -> 4

Sheet 04
B1: ='03'!B1+1 -> 45720
B2: Fechamento Diário do Caixa
B4: Saldo Inicial | C4: 0 | E4: Vendas | K4: Despesas
B5: Vendas | C5: =SUMIF(I6:I31,">0",H6:H31) -> 0 | E5: Nº Venda | F5: Cliente | G5: Forma de Pgto | H5: Valor Venda | I5: Entrada | K5: Descrição | L5: Tipo de Pagto | M5: Valor
B6: Entrada | C6: =C16 -> 0 | R6: =IF(vend4[[#This Row],[Nº Venda]]>1,1,0) -> 0
B7: Despesas | C7: =SUM(M6:M11) -> 0 | R7: =IF(vend4[[#This Row],[Nº Venda]]>1,1,0) -> 0
B8: Total entrada | C8: =SUM(C6:C7) -> 0 | R8: =IF(vend4[[#This Row],[Nº Venda]]>1,1,0) -> 0
R9: =IF(vend4[[#This Row],[Nº Venda]]>1,1,0) -> 0
B10: Tipos de Pagtos | R10: =IF(vend4[[#This Row],[Nº Venda]]>1,1,0) -> 0
B11: DN | C11: =(SUMIF($G$2:$G$31,B11,$I$2:$I$31))+(SUMIF($G$35:$G$41,B11,$H$35:$H$41)) -> 0 | O11: =IF(C16=0,0,1) -> 0 | R11: =IF(vend4[[#This Row],[Nº Venda]]>1,1,0) -> 0
B12: CTD | C12: =(SUMIF($G$2:$G$31,B12,$I$2:$I$31))+(SUMIF($G$35:$G$41,B12,$H$35:$H$41)) -> 0 | R12: =IF(vend4[[#This Row],[Nº Venda]]>1,1,0) -> 0
B13: CTC | C13: =(SUMIF($G$2:$G$31,B13,$I$2:$I$31))+(SUMIF($G$35:$G$41,B13,$H$35:$H$41)) -> 0 | K13: OS Entregue no Dia | R13: =IF(vend4[[#This Row],[Nº Venda]]>1,1,0) -> 0
B14: PCTC | C14: =(SUMIF($G$2:$G$31,B14,$I$2:$I$31))+(SUMIF($G$35:$G$41,B14,$H$35:$H$41)) -> 0 | K14: OS | L14: Vendedor | M14: CARNE | R14: =IF(vend4[[#This Row],[Nº Venda]]>1,1,0) -> 0
B15: PIX | C15: =(SUMIF($G$2:$G$31,B15,$I$2:$I$31))+(SUMIF($G$35:$G$41,B15,$H$35:$H$41)) -> 0 | R15: =IF(vend4[[#This Row],[Nº Venda]]>1,1,0) -> 0
B16: Total | C16: =SUM(C11:C15) -> 0 | R16: =IF(vend4[[#This Row],[Nº Venda]]>1,1,0) -> 0
R17: =IF(vend4[[#This Row],[Nº Venda]]>1,1,0) -> 0
B18: Entrega de Carne | R18: =IF(vend4[[#This Row],[Nº Venda]]>1,1,0) -> 0
B19: =COUNT(entr_carn4[OS]) -> 0 | C19: =SUM(entr_carn4[Valor Total]) -> 0 | R19: =IF(vend4[[#This Row],[Nº Venda]]>1,1,0) -> 0
B20: Total | C20: =SUM(C19:C19) -> 0 | R20: =IF(vend4[[#This Row],[Nº Venda]]>1,1,0) -> 0
B22: Venda | C22: =C5 -> 0
E24: Restante Entrada
E25: Nº Venda | F25: Cliente | G25: Forma de Pgto | H25: Valor Venda | I25: Entrada
E33: Recebimento de Carnê | K33: Entrega de Carne
E34: OS | F34: Cliente | G34: Forma de Pgto | H34: Valor Parcela | I34: Nº Parcela | K34: OS | L34: Parcelas | M34: Valor Total
Q40: Total de OS | R40: =SUM(R6:R21) -> 0

Sheet 05
B1: ='04'!B1+1 -> 45721
B2: Fechamento Diário do Caixa
B4: Saldo Inicial | C4: 0 | E4: Vendas | K4: Despesas
B5: Vendas | C5: =SUMIF(I6:I31,">0",H6:H31) -> 700 | E5: Nº Venda | F5: Cliente | G5: Forma de Pgto | H5: Valor Venda | I5: Entrada | K5: Descrição | L5: Tipo de Pagto | M5: Valor
B6: Entrada | C6: =C16 -> 912.37 | E6: 10634 | F6: roberto dos santos | G6: DN | H6: 200 | I6: 10 | Q6: =IF(vend5[[#This Row],[Nº Venda]]>1,1,0) -> 1
B7: Despesas | C7: =SUM(M6:M11) -> 0 | E7: 10635 | F7: roberto dos santos | G7: DN | H7: 450 | I7: 10 | Q7: =IF(vend5[[#This Row],[Nº Venda]]>1,1,0) -> 1
B8: Total entrada | C8: =SUM(C6:C7) -> 912.37 | E8: 10636 | F8: joaquim vicente | G8: CTC | H8: 50 | I8: 50 | Q8: =IF(vend5[[#This Row],[Nº Venda]]>1,1,0) -> 1
Q9: =IF(vend5[[#This Row],[Nº Venda]]>1,1,0) -> 0
B10: Tipos de Pagtos | Q10: =IF(vend5[[#This Row],[Nº Venda]]>1,1,0) -> 0
B11: DN | C11: =(SUMIF($G$2:$G$31,B11,$I$2:$I$31))+(SUMIF($G$35:$G$41,B11,$H$35:$H$41)) -> 145 | N11: =IF(C16=0,0,1) -> 1 | Q11: =IF(vend5[[#This Row],[Nº Venda]]>1,1,0) -> 0
B12: CTD | C12: =(SUMIF($G$2:$G$31,B12,$I$2:$I$31))+(SUMIF($G$35:$G$41,B12,$H$35:$H$41)) -> 100 | Q12: =IF(vend5[[#This Row],[Nº Venda]]>1,1,0) -> 0
B13: CTC | C13: =(SUMIF($G$2:$G$31,B13,$I$2:$I$31))+(SUMIF($G$35:$G$41,B13,$H$35:$H$41)) -> 50 | K13: OS Entregue no Dia | Q13: =IF(vend5[[#This Row],[Nº Venda]]>1,1,0) -> 0
B14: PCTC | C14: =(SUMIF($G$2:$G$31,B14,$I$2:$I$31))+(SUMIF($G$35:$G$41,B14,$H$35:$H$41)) -> 0 | K14: OS | L14: Vendedor | M14: CARNE | Q14: =IF(vend5[[#This Row],[Nº Venda]]>1,1,0) -> 0
B15: PIX | C15: =(SUMIF($G$2:$G$31,B15,$I$2:$I$31))+(SUMIF($G$35:$G$41,B15,$H$35:$H$41)) -> 617.37 | K15: 10531 | L15: TATY | M15: Não | Q15: =IF(vend5[[#This Row],[Nº Venda]]>1,1,0) -> 0
B16: Total | C16: =SUM(C11:C15) -> 912.37 | K16: 10636 | L16: ROGÉRIO | M16: Não | Q16: =IF(vend5[[#This Row],[Nº Venda]]>1,1,0) -> 0
Q17: =IF(vend5[[#This Row],[Nº Venda]]>1,1,0) -> 0
B18: Entrega de Carne | Q18: =IF(vend5[[#This Row],[Nº Venda]]>1,1,0) -> 0
B19: =COUNT(entr_carn5[OS]) -> 0 | C19: =SUM(entr_carn5[Valor Total]) -> 0 | Q19: =IF(vend5[[#This Row],[Nº Venda]]>1,1,0) -> 0
B20: Total | C20: =SUM(C19:C19) -> 0 | Q20: =IF(vend5[[#This Row],[Nº Venda]]>1,1,0) -> 0
B22: Venda | C22: =C5 -> 700
E24: Restante Entrada
E25: Nº Venda | F25: Cliente | G25: Forma de Pgto | H25: Valor Venda | I25: Entrada
E33: Recebimento de Carnê | K33: Entrega de Carne
E34: OS | F34: Cliente | G34: Forma de Pgto | H34: Valor Parcela | I34: Nº Parcela | K34: OS | L34: Parcelas | M34: Valor Total
E35: 9375 | F35: carmelina da conceição | G35: PIX | H35: 110.12 | I35: PARC. 8/8
E36: 9436 | F36: luiza jaqueline | G36: DN | H36: 125 | I36: PARC. 8/8
E37: 9441 | F37: gilmar lopes | G37: PIX | H37: 356.25 | I37: PARC. 6/8
E38: 9916 | F38: rosana glecia | G38: PIX | H38: 151 | I38: PARC. 4/6
E39: 10353 | F39: cecilia boaventura | G39: CTD | H39: 100 | I39: PARC. 2/5
P40: Total de OS | Q40: =SUM(Q6:Q21) -> 3

Sheet 06
B1: ='05'!B1+1 -> 45722
B2: Fechamento Diário do Caixa
B4: Saldo Inicial | C4: 0 | E4: Vendas | K4: Despesas
B5: Vendas | C5: =SUMIF(I6:I26,">0",H6:H26) -> 339.99 | E5: Nº Venda | F5: Cliente | G5: Forma de Pgto | H5: Valor Venda | I5: Entrada | K5: Descrição | L5: Tipo de Pagto | M5: Valor
B6: Entrada | C6: =C16 -> 2363.38 | E6: 10637 | F6: roberto dos santos | G6: CTD | H6: 40 | I6: 40 | R6: =IF(vend[[#This Row],[Nº Venda]]>1,1,0) -> 1
B7: Despesas | C7: =SUM(M6:M11) -> 0 | E7: 10638 | F7: maria jose | G7: CTD | H7: 50 | I7: 50 | R7: =IF(vend[[#This Row],[Nº Venda]]>1,1,0) -> 1
B8: Total entrada | C8: =SUM(C6:C7) -> 2363.38 | E8: 10639 | F8: andreza souza | G8: CTC | H8: 150 | I8: 150 | R8: =IF(vend[[#This Row],[Nº Venda]]>1,1,0) -> 1
E9: 10640 | F9: diego gomes | G9: CTC | H9: 99.99 | I9: 99.9 | R9: =IF(vend[[#This Row],[Nº Venda]]>1,1,0) -> 1
B10: Tipos de Pagtos | R10: =IF(vend[[#This Row],[Nº Venda]]>1,1,0) -> 0
B11: DN | C11: =(SUMIF($G$2:$G$26,B11,$I$2:$I$26))+(SUMIF($G$30:$G$42,B11,$H$30:$H$42)) -> 0 | O11: =IF(C16=0,0,1) -> 1 | R11: =IF(vend[[#This Row],[Nº Venda]]>1,1,0) -> 0
B12: CTD | C12: =(SUMIF($G$2:$G$26,B12,$I$2:$I$26))+(SUMIF($G$30:$G$42,B12,$H$30:$H$42)) -> 779.4 | R12: =IF(vend[[#This Row],[Nº Venda]]>1,1,0) -> 0
B13: CTC | C13: =(SUMIF($G$2:$G$26,B13,$I$2:$I$26))+(SUMIF($G$30:$G$42,B13,$H$30:$H$42)) -> 249.9 | K13: OS Entregue no Dia | R13: =IF(vend[[#This Row],[Nº Venda]]>1,1,0) -> 0
B14: PCTC | C14: =(SUMIF($G$2:$G$26,B14,$I$2:$I$26))+(SUMIF($G$30:$G$42,B14,$H$30:$H$42)) -> 0 | K14: OS | L14: Vendedor | M14: CARNE | R14: =IF(vend[[#This Row],[Nº Venda]]>1,1,0) -> 0
B15: PIX | C15: =(SUMIF($G$2:$G$26,B15,$I$2:$I$26))+(SUMIF($G$30:$G$42,B15,$H$30:$H$42)) -> 1334.08 | K15: 10594 | L15: JOCY | M15: Não | R15: =IF(vend[[#This Row],[Nº Venda]]>1,1,0) -> 0
B16: Total | C16: =SUM(C11:C15) -> 2363.38 | K16: 10600 | L16: TATY | M16: Não | R16: =IF(vend[[#This Row],[Nº Venda]]>1,1,0) -> 0
K17: 10625 | L17: ROGÉRIO | M17: Não | R17: =IF(vend[[#This Row],[Nº Venda]]>1,1,0) -> 0
B18: Entrega de Carne | K18: 10637 | L18: ROGÉRIO | M18: Não | R18: =IF(vend[[#This Row],[Nº Venda]]>1,1,0) -> 0
B19: =COUNT(entr_carn6[OS]) -> 0 | C19: =SUM(entr_carn6[Valor Total]) -> 0 | K19: 10638 | L19: JOCY | M19: Não | R19: =IF(vend[[#This Row],[Nº Venda]]>1,1,0) -> 0
B20: Total | C20: =SUM(C19:C19) -> 0 | K20: 10639 | L20: JOCY | M20: Não | R20: =IF(vend[[#This Row],[Nº Venda]]>1,1,0) -> #VALUE!
E21: Restante Entrada | K21: 10640 | L21: TATY | M21: Não
B22: Venda | C22: =C5 -> 339.99 | E22: Nº Venda | F22: Cliente | G22: Forma de Pgto | H22: Valor Venda | I22: Entrada
E23: 10634 | F23: roberto dos santos | G23: CTD | H23: 0 | I23: 100
E24: 10635 | F24: roberto dos santos | G24: CTD | H24: 0 | I24: 100
E28: Recebimento de Carnê | K28: Entrega de Carne
E29: OS | F29: Cliente | G29: Forma de Pgto | H29: Valor Parcela | I29: Nº Parcela | K29: OS | L29: Parcelas | M29: Valor Total
E30: 9494 | F30: mariana rosa | G30: PIX | H30: 150 | I30: PARC. 5/6
E31: 9686 | F31: jaqueline santos | G31: CTD | H31: 225 | I31: PARC. 6/8
E32: 9716 | F32: ronivaldo pereira | G32: PIX | H32: 120 | I32: PARC. 5/6
E33: 9746 | F33: jaqueline santos | G33: CTD | H33: 61.25 | I33: PARC. 6/8
E34: 9860 | F34: adriana aparecida | G34: PIX | H34: 110 | I34: PARC. 5/5
E35: 9973 | F35: eladio julio | G35: PIX | H35: 103.33 | I35: PARC. 4/6
E36: 9981 | F36: quiteria maria | G36: PIX | H36: 150 | I36: PARC. 3/7
E37: 10001 | F37: fernando de andrade | G37: CTD | H37: 97.15 | I37: PARC. 4/7
E38: 10012 | F38: ricardo campani | G38: PIX | H38: 243.75 | I38: PARC. 4/8
E39: 10301 | F39: custodio silva | G39: PIX | H39: 200 | I39: PARC. 1/3
E40: 10309 | F40: teresinha mendes | G40: CTD | H40: 106 | I40: PARC. 2/5 | Q40: Total de OS | R40: =SUM(R6:R21) -> #VALUE!
E41: 10323 | F41: ruan dos santos lima | G41: PIX | H41: 133 | I41: PARC. 1/3
E42: 10386 | F42: kettlyn araujo | G42: PIX | H42: 124 | I42: PARC. 2/7

Sheet 07
B1: ='06'!B1+1 -> 45723
B2: Fechamento Diário do Caixa
B4: Saldo Inicial | C4: 0 | E4: Vendas | K4: Despesas | U4: 0
B5: Vendas | C5: =SUMIF(I6:I31,">0",H6:H31) -> 4217.9 | E5: Nº Venda | F5: Cliente | G5: Forma de Pgto | H5: Valor Venda | I5: Entrada | K5: Descrição | L5: Tipo de Pagto | M5: Valor
B6: Entrada | C6: =C16 -> 4970.88 | E6: 10641 | F6: QUEREN SANTOS | G6: SS | H6: 800 | R6: =IF(vend7[[#This Row],[Nº Venda]]>1,1,0) -> 1
B7: Despesas | C7: =SUM(M6:M11) -> 0 | E7: 10642 | F7: REINALDO DE SANTANA | G7: CTD | H7: 999 | I7: 999 | R7: =IF(vend7[[#This Row],[Nº Venda]]>1,1,0) -> 1
B8: Total entrada | C8: =SUM(C6:C7) -> 4970.88 | E8: 10643 | F8: FRANCIELE ALEXANDRE | G8: CTC | H8: 500 | I8: 500 | R8: =IF(vend7[[#This Row],[Nº Venda]]>1,1,0) -> 1
E9: 10644 | F9: MARIA DAS GRACAS | G9: CTC | H9: 1999 | I9: 1999 | R9: =IF(vend7[[#This Row],[Nº Venda]]>1,1,0) -> 1
B10: Tipos de Pagtos | E10: 10645 | F10: SIMONE MARISTELA | G10: CTC | H10: 699.9 | I10: 699.9 | R10: =IF(vend7[[#This Row],[Nº Venda]]>1,1,0) -> 1
B11: DN | C11: =(SUMIF($G$2:$G$31,B11,$I$2:$I$31))+(SUMIF($G$35:$G$41,B11,$H$35:$H$41)) -> 134.28 | E11: 10646 | F11: ADRIANO DOS SANTOS | G11: DN | H11: 20 | I11: 20 | O11: =IF(C16=0,0,1) -> 1 | R11: =IF(vend7[[#This Row],[Nº Venda]]>1,1,0) -> 1
B12: CTD | C12: =(SUMIF($G$2:$G$31,B12,$I$2:$I$31))+(SUMIF($G$35:$G$41,B12,$H$35:$H$41)) -> 1077.33 | R12: =IF(vend7[[#This Row],[Nº Venda]]>1,1,0) -> 0
B13: CTC | C13: =(SUMIF($G$2:$G$31,B13,$I$2:$I$31))+(SUMIF($G$35:$G$41,B13,$H$35:$H$41)) -> 3198.9 | K13: OS Entregue no Dia | R13: =IF(vend7[[#This Row],[Nº Venda]]>1,1,0) -> 0
B14: PCTC | C14: =(SUMIF($G$2:$G$31,B14,$I$2:$I$31))+(SUMIF($G$35:$G$41,B14,$H$35:$H$41)) -> 0 | K14: OS | L14: Vendedor | M14: CARNE | R14: =IF(vend7[[#This Row],[Nº Venda]]>1,1,0) -> 0
B15: PIX | C15: =(SUMIF($G$2:$G$31,B15,$I$2:$I$31))+(SUMIF($G$35:$G$41,B15,$H$35:$H$41)) -> 560.37 | K15: 10533 | L15: TATY | M15: Não | R15: =IF(vend7[[#This Row],[Nº Venda]]>1,1,0) -> 0
B16: Total | C16: =SUM(C11:C15) -> 4970.88 | K16: 10646 | L16: ROGÉRIO | M16: Não | R16: =IF(vend7[[#This Row],[Nº Venda]]>1,1,0) -> 0
K17: 10345 | L17: TATY | M17: Não | R17: =IF(vend7[[#This Row],[Nº Venda]]>1,1,0) -> 0
B18: Entrega de Carne | R18: =IF(vend7[[#This Row],[Nº Venda]]>1,1,0) -> 0
B19: =COUNT(entr_carn7[OS]) -> 0 | C19: =SUM(entr_carn7[Valor Total]) -> 0 | R19: =IF(vend7[[#This Row],[Nº Venda]]>1,1,0) -> 0
B20: Total | C20: =SUM(C19:C19) -> 0 | R20: =IF(vend7[[#This Row],[Nº Venda]]>1,1,0) -> 0
B22: Venda | C22: =C5 -> 4217.9
E24: Restante Entrada
E25: Nº Venda | F25: Cliente | G25: Forma de Pgto | H25: Valor Venda | I25: Entrada
E33: Recebimento de Carnê | K33: Entrega de Carne
E34: R$9.615,00 | F34: Cliente | G34: Forma de Pgto | H34: Valor Parcela | I34: Nº Parcela | K34: OS | L34: Parcelas | M34: Valor Total
E35: 9699 | F35: HENRIQUE LIMA | G35: PIX | H35: 80 | I35: PARC. 6/6
E36: 9711 | F36: ANDREZA SOUZA | G36: PIX | H36: 100 | I36: PARC. 6/8
E37: 9711 | F37: ANDREZA SOUZA | G37: PIX | H37: 100 | I37: PARC. 7/8
E38: 10336 | F38: SIMINE IGNACIO | G38: DN | H38: 114.28 | I38: PARC. 1/7
E39: 10202 | F39: JOSE LUIZ | G39: PIX | H39: 156.25 | I39: PARC. 1/8
E40: 10495 | F40: EDUARDO ADRIANO | G40: PIX | H40: 124.12 | I40: PARC. 1/8 | Q40: Total de OS | R40: =SUM(R6:R21) -> 6
E41: 9615 | F41: CICERO FERREIRA | G41: CTD | H41: 78.33 | I41: PARC. 6/6

Sheet 08
B1: ='07'!B1+1 -> 45724
B2: Fechamento Diário do Caixa
B4: Saldo Inicial | C4: 0 | E4: Vendas | K4: Despesas
B5: Vendas | C5: =SUMIF(I6:I31,">0",H6:H31) -> 3490 | E5: Nº Venda | F5: Cliente | G5: Forma de Pgto | H5: Valor Venda | I5: Entrada | K5: Descrição | L5: Tipo de Pagto | M5: Valor
B6: Entrada | C6: =C16 -> 2799.75 | E6: 10647 | F6: JOSE APARECIDO | G6: CTC | H6: 250 | I6: 250 | R6: =IF(vend8[[#This Row],[Nº Venda]]>1,1,0) -> 1
B7: Despesas | C7: =SUM(M6:M11) -> 0 | E7: 10648 | F7: JOSE APARECIDO | G7: DN | H7: 1050 | I7: 50 | R7: =IF(vend8[[#This Row],[Nº Venda]]>1,1,0) -> 1
B8: Total entrada | C8: =SUM(C6:C7) -> 2799.75 | E8: 10649 | F8: PRISCILA | G8: CTC | H8: 380 | I8: 10 | R8: =IF(vend8[[#This Row],[Nº Venda]]>1,1,0) -> 1
E9: 10650 | F9: PRISCILA | G9: CTC | H9: 230 | I9: 230 | R9: =IF(vend8[[#This Row],[Nº Venda]]>1,1,0) -> 1
B10: Tipos de Pagtos | E10: 10651 | F10: JULIANA SANTOS | G10: PIX | H10: 381 | I10: 50 | R10: =IF(vend8[[#This Row],[Nº Venda]]>1,1,0) -> 1
B11: DN | C11: =(SUMIF($G$2:$G$31,B11,$I$2:$I$31))+(SUMIF($G$35:$G$41,B11,$H$35:$H$41)) -> 50 | E11: 10652 | F11: JULIANA SANTOS | G11: PIX | H11: 499 | I11: 50 | O11: =IF(C16=0,0,1) -> 1 | R11: =IF(vend8[[#This Row],[Nº Venda]]>1,1,0) -> 1
B12: CTD | C12: =(SUMIF($G$2:$G$31,B12,$I$2:$I$31))+(SUMIF($G$35:$G$41,B12,$H$35:$H$41)) -> 459.75 | E12: 10653 | F12: JULIANA SANTOS | G12: PIX | H12: 700 | I12: 100 | R12: =IF(vend8[[#This Row],[Nº Venda]]>1,1,0) -> 1
B13: CTC | C13: =(SUMIF($G$2:$G$31,B13,$I$2:$I$31))+(SUMIF($G$35:$G$41,B13,$H$35:$H$41)) -> 1990 | K13: OS Entregue no Dia | R13: =IF(vend8[[#This Row],[Nº Venda]]>1,1,0) -> 0
B14: PCTC | C14: =(SUMIF($G$2:$G$31,B14,$I$2:$I$31))+(SUMIF($G$35:$G$41,B14,$H$35:$H$41)) -> 0 | K14: OS | L14: Vendedor | M14: CARNE | R14: =IF(vend8[[#This Row],[Nº Venda]]>1,1,0) -> 0
B15: PIX | C15: =(SUMIF($G$2:$G$31,B15,$I$2:$I$31))+(SUMIF($G$35:$G$41,B15,$H$35:$H$41)) -> 300 | K15: 10327 | L15: ROGÉRIO | M15: Não | R15: =IF(vend8[[#This Row],[Nº Venda]]>1,1,0) -> 0
B16: Total | C16: =SUM(C11:C15) -> 2799.75 | K16: 10447 | L16: ROGÉRIO | M16: Não | R16: =IF(vend8[[#This Row],[Nº Venda]]>1,1,0) -> 0
K17: 10610 | L17: JOCY | M17: Não | R17: =IF(vend8[[#This Row],[Nº Venda]]>1,1,0) -> 0
B18: Entrega de Carne | K18: 10611 | L18: JOCY | M18: Não | R18: =IF(vend8[[#This Row],[Nº Venda]]>1,1,0) -> 0
B19: =COUNT(entr_carn8[OS]) -> 0 | C19: =SUM(entr_carn8[Valor Total]) -> 0 | K19: 10647 | L19: JOCY | M19: Não | R19: =IF(vend8[[#This Row],[Nº Venda]]>1,1,0) -> 0
B20: Total | C20: =SUM(C19:C19) -> 0 | R20: =IF(vend8[[#This Row],[Nº Venda]]>1,1,0) -> 0
B22: Venda | C22: =C5 -> 3490
E24: Restante Entrada
E25: Nº Venda | F25: Cliente | G25: Forma de Pgto | H25: Valor Venda | I25: Entrada
E26: 10447 | F26: ROSANGELA APARECIDA | G26: CTC | H26: 0 | I26: 1500
E33: Recebimento de Carnê | K33: Entrega de Carne
E34: OS | F34: Cliente | G34: Forma de Pgto | H34: Valor Parcela | I34: Nº Parcela | K34: OS | L34: Parcelas | M34: Valor Total
E35: 9887 | F35: aline santana | G35: PIX | H35: 100 | I35: PARC. 5/5
E36: 9936 | F36: rodrigo bispo | G36: CTD | H36: 69.75 | I36: PARC. 4/8
E37: 10058 | F37: pedro alves | G37: CTD | H37: 290 | I37: PARC. 3/10
E38: 10085 | F38: tatiana gomes | G38: CTD | H38: 100 | I38: PARC. 3/6
Q40: Total de OS | R40: =SUM(R6:R21) -> 7

Sheet 09
B1: ='08'!B1+1 -> 45725
B2: Fechamento Diário do Caixa
B4: Saldo Inicial | C4: 0 | E4: Vendas | K4: Despesas
B5: Vendas | C5: =SUMIF(I6:I31,">0",H6:H31) -> 0 | E5: Nº Venda | F5: Cliente | G5: Forma de Pgto | H5: Valor Venda | I5: Entrada | K5: Descrição | L5: Tipo de Pagto | M5: Valor
B6: Entrada | C6: =C16 -> 0 | R6: =IF(vend9[[#This Row],[Nº Venda]]>1,1,0) -> 0
B7: Despesas | C7: =SUM(M6:M11) -> 0 | R7: =IF(vend9[[#This Row],[Nº Venda]]>1,1,0) -> 0
B8: Total entrada | C8: =SUM(C6:C7) -> 0 | R8: =IF(vend9[[#This Row],[Nº Venda]]>1,1,0) -> 0
R9: =IF(vend9[[#This Row],[Nº Venda]]>1,1,0) -> 0
B10: Tipos de Pagtos | R10: =IF(vend9[[#This Row],[Nº Venda]]>1,1,0) -> 0
B11: DN | C11: =(SUMIF($G$2:$G$31,B11,$I$2:$I$31))+(SUMIF($G$35:$G$41,B11,$H$35:$H$41)) -> 0 | O11: =IF(C16=0,0,1) -> 0 | R11: =IF(vend9[[#This Row],[Nº Venda]]>1,1,0) -> 0
B12: CTD | C12: =(SUMIF($G$2:$G$31,B12,$I$2:$I$31))+(SUMIF($G$35:$G$41,B12,$H$35:$H$41)) -> 0 | R12: =IF(vend9[[#This Row],[Nº Venda]]>1,1,0) -> 0 | V12: 0
B13: CTC | C13: =(SUMIF($G$2:$G$31,B13,$I$2:$I$31))+(SUMIF($G$35:$G$41,B13,$H$35:$H$41)) -> 0 | K13: OS Entregue no Dia | R13: =IF(vend9[[#This Row],[Nº Venda]]>1,1,0) -> 0
B14: PCTC | C14: =(SUMIF($G$2:$G$31,B14,$I$2:$I$31))+(SUMIF($G$35:$G$41,B14,$H$35:$H$41)) -> 0 | K14: OS | L14: Vendedor | M14: CARNE | R14: =IF(vend9[[#This Row],[Nº Venda]]>1,1,0) -> 0
B15: PIX | C15: =(SUMIF($G$2:$G$31,B15,$I$2:$I$31))+(SUMIF($G$35:$G$41,B15,$H$35:$H$41)) -> 0 | R15: =IF(vend9[[#This Row],[Nº Venda]]>1,1,0) -> 0
B16: Total | C16: =SUM(C11:C15) -> 0 | R16: =IF(vend9[[#This Row],[Nº Venda]]>1,1,0) -> 0
R17: =IF(vend9[[#This Row],[Nº Venda]]>1,1,0) -> 0
B18: Entrega de Carne | R18: =IF(vend9[[#This Row],[Nº Venda]]>1,1,0) -> 0
B19: =COUNT(entr_carn9[OS]) -> 0 | C19: =SUM(entr_carn9[Valor Total]) -> 0 | R19: =IF(vend9[[#This Row],[Nº Venda]]>1,1,0) -> 0
B20: Total | C20: =SUM(C19:C19) -> 0 | R20: =IF(vend9[[#This Row],[Nº Venda]]>1,1,0) -> 0
B22: Venda | C22: =C5 -> 0
E24: Restante Entrada
E25: Nº Venda | F25: Cliente | G25: Forma de Pgto | H25: Valor Venda | I25: Entrada
E33: Recebimento de Carnê | K33: Entrega de Carne
E34: OS | F34: Cliente | G34: Forma de Pgto | H34: Valor Parcela | I34: Nº Parcela | K34: OS | L34: Parcelas | M34: Valor Total
Q40: Total de OS | R40: =SUM(R6:R21) -> 0

Sheet 10
B1: ='09'!B1+1 -> 45726
B2: Fechamento Diário do Caixa
B4: Saldo Inicial | C4: 0 | E4: Vendas | K4: Despesas
B5: Vendas | C5: =SUMIF(I6:I25,">0",H6:H25) -> 1874 | E5: Nº Venda | F5: Cliente | G5: Forma de Pgto | H5: Valor Venda | I5: Entrada | K5: Descrição | L5: Tipo de Pagto | M5: Valor
B6: Entrada | C6: =C16 -> 2765.06 | E6: 10654 | F6: salmir fernandes | G6: PIX | H6: 150 | I6: 150 | R6: =IF(vend10[[#This Row],[Nº Venda]]>1,1,0) -> 1
B7: Despesas | C7: =SUM(M6:M11) -> 0 | E7: 10655 | F7: fernanda aparecida | G7: DN | H7: 35 | I7: 35 | R7: =IF(vend10[[#This Row],[Nº Venda]]>1,1,0) -> 1
B8: Total entrada | C8: =SUM(C6:C7) -> 2765.06 | E8: 10656 | F8: ricardo henrique | G8: GARANTIA | R8: =IF(vend10[[#This Row],[Nº Venda]]>1,1,0) -> 1
E9: 10657 | F9: marcia de alcantara | G9: CTD | H9: 989 | I9: 500 | R9: =IF(vend10[[#This Row],[Nº Venda]]>1,1,0) -> 1
B10: Tipos de Pagtos | E10: 10658 | F10: maria neusa | G10: DN | H10: 400 | I10: 40 | R10: =IF(vend10[[#This Row],[Nº Venda]]>1,1,0) -> 1
B11: DN | C11: =(SUMIF($G$2:$G$25,B11,$I$2:$I$25))+(SUMIF($G$29:$G$44,B11,$H$29:$H$44)) -> 514.42 | E11: 10659 | F11: maria neusa | G11: DN | H11: 300 | I11: 10 | O11: =IF(C16=0,0,1) -> 1 | R11: =IF(vend10[[#This Row],[Nº Venda]]>1,1,0) -> 1
B12: CTD | C12: =(SUMIF($G$2:$G$25,B12,$I$2:$I$25))+(SUMIF($G$29:$G$44,B12,$H$29:$H$44)) -> 1147.48 | R12: =IF(vend10[[#This Row],[Nº Venda]]>1,1,0) -> 0
B13: CTC | C13: =(SUMIF($G$2:$G$25,B13,$I$2:$I$25))+(SUMIF($G$29:$G$44,B13,$H$29:$H$44)) -> 0 | K13: OS Entregue no Dia | R13: =IF(vend10[[#This Row],[Nº Venda]]>1,1,0) -> 0
B14: PCTC | C14: =(SUMIF($G$2:$G$25,B14,$I$2:$I$25))+(SUMIF($G$29:$G$44,B14,$H$29:$H$44)) -> 0 | K14: OS | L14: Vendedor | M14: CARNE | R14: =IF(vend10[[#This Row],[Nº Venda]]>1,1,0) -> 0
B15: PIX | C15: =(SUMIF($G$2:$G$25,B15,$I$2:$I$25))+(SUMIF($G$29:$G$44,B15,$H$29:$H$44)) -> 1103.16 | K15: 10449 | L15: ROGÉRIO | M15: Não | R15: =IF(vend10[[#This Row],[Nº Venda]]>1,1,0) -> 0
B16: Total | C16: =SUM(C11:C15) -> 2765.06 | K16: 10603 | L16: ROGÉRIO | M16: Não | R16: =IF(vend10[[#This Row],[Nº Venda]]>1,1,0) -> 0
K17: 10624 | L17: TATY | M17: Não | R17: =IF(vend10[[#This Row],[Nº Venda]]>1,1,0) -> 0
B18: Entrega de Carne | K18: 10654 | L18: ROGÉRIO | M18: Não | R18: =IF(vend10[[#This Row],[Nº Venda]]>1,1,0) -> #VALUE!
B19: =COUNT(entr_carn10[OS]) -> 0 | C19: =SUM(entr_carn10[Valor Total]) -> 0 | E19: Restante Entrada | K19: 10655 | L19: ROGÉRIO | M19: Não | R19: =IF(vend10[[#This Row],[Nº Venda]]>1,1,0) -> #VALUE!
B20: Total | C20: =SUM(C19:C19) -> 0 | E20: Nº Venda | F20: Cliente | G20: Forma de Pgto | H20: Valor Venda | I20: Entrada | K20: 10656 | L20: JOCY | M20: Não | R20: =IF(vend10[[#This Row],[Nº Venda]]>1,1,0) -> #VALUE!
B22: Venda | C22: =C5 -> 1874
E27: Recebimento de Carnê | K27: Entrega de Carne
E28: OS | F28: Cliente | G28: Forma de Pgto | H28: Valor Parcela | I28: Nº Parcela | K28: OS | L28: Parcelas | M28: Valor Total
E29: 8862 | F29: sebastão pereira | G29: CTD | H29: 158.55 | I29: PARC. 9/9
E30: 9018 | F30: Ilda Soares Ventura Rodrigues (acordo) | G30: DN | H30: 25 | I30: PARC. 3/6
E31: 9118 | F31: lilian cristina | G31: PIX | H31: 120 | I31: PARC. 7/8
E32: 9472 | F32: Ilda Soares Ventura Rodrigues (acordo) | G32: DN | H32: 25 | I32: PARC. 3/6
E33: 9723 | F33: darci alice | G33: PIX | H33: 91.66 | I33: PARC. 6/6
E34: 9728 | F34: eliel duarte | G34: PIX | H34: 162.5 | I34: PARC. 7/8
E35: 9836 | F35: ana lucia | G35: CTD | H35: 150 | I35: PARC. 5/8
E36: 9891 | F36: ana lucia | G36: CTD | H36: 82.37 | I36: PARC. 5/8
E37: 10041 | F37: erica da silva | G37: PIX | H37: 200 | I37: PARC. 3/8
E38: 10137 | F38: sirlei bueno | G38: DN | H38: 123.75 | I38: PARC. 3/8
E39: 10151 | F39: sandra maria alves | G39: PIX | H39: 92.5 | I39: PARC. 2/4
E40: 10210 | F40: walter alves | G40: PIX | H40: 161 | I40: PARC. 3/10 | Q40: Total de OS | R40: =SUM(R6:R21) -> #VALUE!
E41: 10340 | F41: maria vitória gino | G41: DN | H41: 255.67 | I41: PARC. 2/3
E42: 10442 | F42: katia de oliveira | G42: PIX | H42: 125.5 | I42: PARC. 1/10
E43: 10449 | F43: daniela maria | G43: CTD | H43: 128.71 | I43: PARC. 1/7
E44: 10468 | F44: valdemice batista | G44: CTD | H44: 127.85 | I44: PARC. 1/7

Sheet 11
B1: ='10'!B1+1 -> 45727
B2: Fechamento Diário do Caixa
B4: Saldo Inicial | C4: 0 | E4: Vendas | K4: Despesas
B5: Vendas | C5: =SUMIF(I6:I31,">0",H6:H31) -> 4369 | E5: Nº Venda | F5: Cliente | G5: Forma de Pgto | H5: Valor Venda | I5: Entrada | K5: Descrição | L5: Tipo de Pagto | M5: Valor
B6: Entrada | C6: =C16 -> 2939 | E6: 10660 | F6: Fabiana Regina Silva dos Santos | G6: CTD | H6: 30 | I6: 30 | R6: =IF(vend11[[#This Row],[Nº Venda]]>1,1,0) -> 1
B7: Despesas | C7: =SUM(M6:M11) -> 0 | E7: 10661 | F7: Milton Donizete Costa | G7: PIX | H7: 890 | I7: 890 | R7: =IF(vend11[[#This Row],[Nº Venda]]>1,1,0) -> 1
B8: Total entrada | C8: =SUM(C6:C7) -> 2939 | E8: 10662 | F8: Milton Donizete Costa | G8: PIX | H8: 950 | I8: 950 | R8: =IF(vend11[[#This Row],[Nº Venda]]>1,1,0) -> 1
E9: 10663 | F9: Milton Donizete Costa | G9: PIX | H9: 800 | I9: 535 | R9: =IF(vend11[[#This Row],[Nº Venda]]>1,1,0) -> 1
B10: Tipos de Pagtos | E10: 10664 | F10: Talita de Freitas | G10: CTD | H10: 624.5 | I10: 40 | R10: =IF(vend11[[#This Row],[Nº Venda]]>1,1,0) -> 1
B11: DN | C11: =(SUMIF($G$2:$G$31,B11,$I$2:$I$31))+(SUMIF($G$35:$G$41,B11,$H$35:$H$41)) -> 0 | E11: 10664 | F11: Talita de Freitas | G11: CTC | H11: 0 | I11: 60 | O11: =IF(C16=0,0,1) -> 1 | R11: =IF(vend11[[#This Row],[Nº Venda]]>1,1,0) -> 1
B12: CTD | C12: =(SUMIF($G$2:$G$31,B12,$I$2:$I$31))+(SUMIF($G$35:$G$41,B12,$H$35:$H$41)) -> 169 | E12: 10665 | F12: Talita de Freitas | G12: CTC | H12: 550 | I12: 100 | R12: =IF(vend11[[#This Row],[Nº Venda]]>1,1,0) -> 1
B13: CTC | C13: =(SUMIF($G$2:$G$31,B13,$I$2:$I$31))+(SUMIF($G$35:$G$41,B13,$H$35:$H$41)) -> 260 | E13: 10666 | F13: Talita de Freitas | G13: CTC | H13: 524.5 | I13: 100 | K13: OS Entregue no Dia | R13: =IF(vend11[[#This Row],[Nº Venda]]>1,1,0) -> 1
B14: PCTC | C14: =(SUMIF($G$2:$G$31,B14,$I$2:$I$31))+(SUMIF($G$35:$G$41,B14,$H$35:$H$41)) -> 0 | K14: OS | L14: Vendedor | M14: CARNE | R14: =IF(vend11[[#This Row],[Nº Venda]]>1,1,0) -> 0
B15: PIX | C15: =(SUMIF($G$2:$G$31,B15,$I$2:$I$31))+(SUMIF($G$35:$G$41,B15,$H$35:$H$41)) -> 2510 | K15: 10334 | L15: TATY | M15: Sim | R15: =IF(vend11[[#This Row],[Nº Venda]]>1,1,0) -> 0
B16: Total | C16: =SUM(C11:C15) -> 2939 | K16: 10587 | L16: ROGÉRIO | M16: Não | R16: =IF(vend11[[#This Row],[Nº Venda]]>1,1,0) -> 0
K17: 10590 | L17: JOCY | M17: Não | R17: =IF(vend11[[#This Row],[Nº Venda]]>1,1,0) -> 0
B18: Entrega de Carne | K18: 10620 | L18: TATY | M18: Não | R18: =IF(vend11[[#This Row],[Nº Venda]]>1,1,0) -> 0
B19: =COUNT(entr_carn11[OS]) -> 1 | C19: =SUM(entr_carn11[Valor Total]) -> 69.99 | K19: 10626 | L19: ARIANI | M19: Não | R19: =IF(vend11[[#This Row],[Nº Venda]]>1,1,0) -> 0
B20: Total | C20: =SUM(C19:C19) -> 69.99 | K20: 10627 | L20: ARIANI | M20: Não | R20: =IF(vend11[[#This Row],[Nº Venda]]>1,1,0) -> 0
K21: 10630 | L21: ROGÉRIO | M21: Não
B22: Venda | C22: =C5 -> 4369
E24: Restante Entrada
E25: Nº Venda | F25: Cliente | G25: Forma de Pgto | H25: Valor Venda | I25: Entrada
E33: Recebimento de Carnê | K33: Entrega de Carne
E34: OS | F34: Cliente | G34: Forma de Pgto | H34: Valor Parcela | I34: Nº Parcela | K34: OS | L34: Parcelas | M34: Valor Total
E35: 9018 | F35: Ilda Soares Ventura Rodrigues (acordo) | G35: CTD | H35: 42.5 | I35: PARC. 4/6 | K35: 10334 | L35: 5 | M35: 69.99
E36: 9472 | F36: Ilda Soares Ventura Rodrigues (acordo) | G36: CTD | H36: 42.5 | I36: PARC. 4/6
E37: 10319 | F37: Aguinaldo Nascimento | G37: PIX | H37: 135 | I37: PARC. 2/2
E38: 10334 | F38: Ilda Soares Ventura Rodrigues | G38: CTD | H38: 14 | I38: PARC. 1/5
Q40: Total de OS | R40: =SUM(R6:R21) -> 8

Sheet 12
B1: ='11'!B1+1 -> 45728
B2: Fechamento Diário do Caixa
B4: Saldo Inicial | C4: 0 | E4: Vendas | K4: Despesas
B5: Vendas | C5: =SUMIF(I6:I31,">0",H6:H31) -> 1827.9 | E5: Nº Venda | F5: Cliente | G5: Forma de Pgto | H5: Valor Venda | I5: Entrada | K5: Descrição | L5: Tipo de Pagto | M5: Valor
B6: Entrada | C6: =C16 -> 2457.9 | E6: 10667 | F6: JOSE ROBERTO | G6: DN | H6: 170 | I6: 170 | R6: =IF(vend12[[#This Row],[Nº Venda]]>1,1,0) -> 1
B7: Despesas | C7: =SUM(M6:M11) -> 0 | E7: 10668 | F7: VALDECIR DE SOUZA | G7: CTD | H7: 69.9 | I7: 69.9 | R7: =IF(vend12[[#This Row],[Nº Venda]]>1,1,0) -> 1
B8: Total entrada | C8: =SUM(C6:C7) -> 2457.9 | E8: 10669 | F8: ERICA KIYOMI SENZAKI | G8: PIX | H8: 589 | I8: 589 | R8: =IF(vend12[[#This Row],[Nº Venda]]>1,1,0) -> 1
E9: 10670 | F9: ISABELA BRITO OLIVEIRA | G9: GARANTIA | H9: 0 | I9: 0 | R9: =IF(vend12[[#This Row],[Nº Venda]]>1,1,0) -> 1
B10: Tipos de Pagtos | E10: 10671 | F10: VALDECIR DE SOUZA | G10: CTC | H10: 999 | I10: 999 | R10: =IF(vend12[[#This Row],[Nº Venda]]>1,1,0) -> 1
B11: DN | C11: =(SUMIF($G$2:$G$31,B11,$I$2:$I$31))+(SUMIF($G$35:$G$41,B11,$H$35:$H$41)) -> 170 | O11: =IF(C16=0,0,1) -> 1 | R11: =IF(vend12[[#This Row],[Nº Venda]]>1,1,0) -> 0
B12: CTD | C12: =(SUMIF($G$2:$G$31,B12,$I$2:$I$31))+(SUMIF($G$35:$G$41,B12,$H$35:$H$41)) -> 69.9 | R12: =IF(vend12[[#This Row],[Nº Venda]]>1,1,0) -> 0
B13: CTC | C13: =(SUMIF($G$2:$G$31,B13,$I$2:$I$31))+(SUMIF($G$35:$G$41,B13,$H$35:$H$41)) -> 1429 | K13: OS Entregue no Dia | R13: =IF(vend12[[#This Row],[Nº Venda]]>1,1,0) -> 0
B14: PCTC | C14: =(SUMIF($G$2:$G$31,B14,$I$2:$I$31))+(SUMIF($G$35:$G$41,B14,$H$35:$H$41)) -> 0 | K14: OS | L14: Vendedor | M14: CARNE | R14: =IF(vend12[[#This Row],[Nº Venda]]>1,1,0) -> 0
B15: PIX | C15: =(SUMIF($G$2:$G$31,B15,$I$2:$I$31))+(SUMIF($G$35:$G$41,B15,$H$35:$H$41)) -> 789 | K15: 10510 | L15: ROGÉRIO | M15: Não | R15: =IF(vend12[[#This Row],[Nº Venda]]>1,1,0) -> 0
B16: Total | C16: =SUM(C11:C15) -> 2457.9 | K16: 10618 | L16: TATY | M16: Não | R16: =IF(vend12[[#This Row],[Nº Venda]]>1,1,0) -> 0
K17: 10634 | L17: ROGÉRIO | M17: Não | R17: =IF(vend12[[#This Row],[Nº Venda]]>1,1,0) -> 0
B18: Entrega de Carne | K18: 10635 | L18: ROGÉRIO | M18: Não | R18: =IF(vend12[[#This Row],[Nº Venda]]>1,1,0) -> 0
B19: =COUNT(entr_carn12[OS]) -> 0 | C19: =SUM(entr_carn12[Valor Total]) -> 0 | K19: 10667 | L19: ROGÉRIO | M19: Não | R19: =IF(vend12[[#This Row],[Nº Venda]]>1,1,0) -> 0
B20: Total | C20: =SUM(C19:C19) -> 0 | K20: 10668 | L20: ROGÉRIO | M20: Não | R20: =IF(vend12[[#This Row],[Nº Venda]]>1,1,0) -> 0
B22: Venda | C22: =C5 -> 1827.9
E24: Restante Entrada
E25: Nº Venda | F25: Cliente | G25: Forma de Pgto | H25: Valor Venda | I25: Entrada
E26: 10629 | F26: ALINE DUARTE | G26: PIX | H26: 0 | I26: 200
E27: 10634 | F27: ROBERTO DOS SANTOS | G27: CTC | H27: 0 | I27: 90
E28: 10635 | F28: ROBERTO DOS SANTOS | G28: CTC | H28: 0 | I28: 340
E33: Recebimento de Carnê | K33: Entrega de Carne
E34: OS | F34: Cliente | G34: Forma de Pgto | H34: Valor Parcela | I34: Nº Parcela | K34: OS | L34: Parcelas | M34: Valor Total
Q40: Total de OS | R40: =SUM(R6:R21) -> 5

Sheet 13
B1: ='12'!B1+1 -> 45729
B2: Fechamento Diário do Caixa
B4: Saldo Inicial | C4: 0 | E4: Vendas | K4: Despesas
B5: Vendas | C5: =SUMIF(I6:I31,">0",H6:H31) -> 2300 | E5: Nº Venda | F5: Cliente | G5: Forma de Pgto | H5: Valor Venda | I5: Entrada | K5: Descrição | L5: Tipo de Pagto | M5: Valor
B6: Entrada | C6: =C16 -> 3674.56 | E6: 10672 | F6: SILVANA REJANE | G6: CTD | H6: 600 | I6: 300 | R6: =IF(vend13[[#This Row],[Nº Venda]]>1,1,0) -> 1
B7: Despesas | C7: =SUM(M6:M11) -> 0 | E7: 10673 | F7: IVONE PEREIRA | G7: CTC | H7: 600 | I7: 1999.9 | R7: =IF(vend13[[#This Row],[Nº Venda]]>1,1,0) -> 1
B8: Total entrada | C8: =SUM(C6:C7) -> 3674.56 | E8: 10674 | F8: LUIZ CLAUDIO | G8: CTC | H8: 400 | I8: 400 | R8: =IF(vend13[[#This Row],[Nº Venda]]>1,1,0) -> 1
E9: 10675 | F9: JOSE CLAUDIO | G9: CTC | H9: 700 | I9: 700 | R9: =IF(vend13[[#This Row],[Nº Venda]]>1,1,0) -> 1
B10: Tipos de Pagtos | R10: =IF(vend13[[#This Row],[Nº Venda]]>1,1,0) -> 0
B11: DN | C11: =(SUMIF($G$2:$G$31,B11,$I$2:$I$31))+(SUMIF($G$35:$G$41,B11,$H$35:$H$41)) -> 40 | O11: =IF(C16=0,0,1) -> 1 | R11: =IF(vend13[[#This Row],[Nº Venda]]>1,1,0) -> 0
B12: CTD | C12: =(SUMIF($G$2:$G$31,B12,$I$2:$I$31))+(SUMIF($G$35:$G$41,B12,$H$35:$H$41)) -> 344 | R12: =IF(vend13[[#This Row],[Nº Venda]]>1,1,0) -> 0
B13: CTC | C13: =(SUMIF($G$2:$G$31,B13,$I$2:$I$31))+(SUMIF($G$35:$G$41,B13,$H$35:$H$41)) -> 3099.9 | K13: OS Entregue no Dia | R13: =IF(vend13[[#This Row],[Nº Venda]]>1,1,0) -> 0
B14: PCTC | C14: =(SUMIF($G$2:$G$31,B14,$I$2:$I$31))+(SUMIF($G$35:$G$41,B14,$H$35:$H$41)) -> 0 | K14: OS | L14: Vendedor | M14: CARNE | R14: =IF(vend13[[#This Row],[Nº Venda]]>1,1,0) -> 0
B15: PIX | C15: =(SUMIF($G$2:$G$31,B15,$I$2:$I$31))+(SUMIF($G$35:$G$41,B15,$H$35:$H$41)) -> 190.66 | K15: 10619 | L15: TATY | M15: Não | R15: =IF(vend13[[#This Row],[Nº Venda]]>1,1,0) -> 0
B16: Total | C16: =SUM(C11:C15) -> 3674.56 | K16: 10617 | L16: TATY | M16: Não | R16: =IF(vend13[[#This Row],[Nº Venda]]>1,1,0) -> 0
R17: =IF(vend13[[#This Row],[Nº Venda]]>1,1,0) -> 0
B18: Entrega de Carne | R18: =IF(vend13[[#This Row],[Nº Venda]]>1,1,0) -> 0
B19: =COUNT(entr_carn13[OS]) -> 0 | C19: =SUM(entr_carn13[Valor Total]) -> 0 | R19: =IF(vend13[[#This Row],[Nº Venda]]>1,1,0) -> 0
B20: Total | C20: =SUM(C19:C19) -> 0 | R20: =IF(vend13[[#This Row],[Nº Venda]]>1,1,0) -> 0
B22: Venda | C22: =C5 -> 2300
E24: Restante Entrada
E25: Nº Venda | F25: Cliente | G25: Forma de Pgto | H25: Valor Venda | I25: Entrada
E33: Recebimento de Carnê | K33: Entrega de Carne
E34: OS | F34: Cliente | G34: Forma de Pgto | H34: Valor Parcela | I34: Nº Parcela | K34: OS | L34: Parcelas | M34: Valor Total
E35: 10360 | F35: GILBERTO DE ALMEIDA | G35: CTD | H35: 44 | I35: PARC. 2/5
E36: 10360 | F36: GILBERTO DE ALMEIDA | G36: DN | H36: 40 | I36: PARC. 2/5
E37: 9307 | F37: EDNEUSA APARECIDA | G37: PIX | H37: 117 | I37: PARC. 1/5
E38: 10492 | F38: WILLI SOUZA | G38: PIX | H38: 73.66 | I38: PARC. 1/3
Q40: Total de OS | R40: =SUM(R6:R21) -> 4

Sheet 14
B1: ='13'!B1+1 -> 45730
B2: Fechamento Diário do Caixa
B4: Saldo Inicial | C4: 0 | E4: Vendas | K4: Despesas
B5: Vendas | C5: =SUMIF(I6:I31,">0",H6:H31) -> 650 | E5: Nº Venda | F5: Cliente | G5: Forma de Pgto | H5: Valor Venda | I5: Entrada | K5: Descrição | L5: Tipo de Pagto | M5: Valor
B6: Entrada | C6: =C16 -> 1300 | E6: 10676 | F6: LEANDRO DA SILVA | G6: GARANTIA | R6: =IF(vend14[[#This Row],[Nº Venda]]>1,1,0) -> 1
B7: Despesas | C7: =SUM(M6:M11) -> 0 | E7: 10677 | F7: NELCIMARA VENTURA | G7: CTD | H7: 100 | I7: 100 | R7: =IF(vend14[[#This Row],[Nº Venda]]>1,1,0) -> 1
B8: Total entrada | C8: =SUM(C6:C7) -> 1300 | E8: 10678 | F8: VALDIVO SOUZA | G8: CTC | H8: 150 | I8: 150 | R8: =IF(vend14[[#This Row],[Nº Venda]]>1,1,0) -> 1
E9: 10679 | F9: JOSE ROBERTO | G9: CTC | H9: 350 | I9: 350 | R9: =IF(vend14[[#This Row],[Nº Venda]]>1,1,0) -> 1
B10: Tipos de Pagtos | E10: 10680 | F10: JOSE ROBERTO | G10: CTC | H10: 50 | I10: 40 | R10: =IF(vend14[[#This Row],[Nº Venda]]>1,1,0) -> 1
B11: DN | C11: =(SUMIF($G$2:$G$31,B11,$I$2:$I$31))+(SUMIF($G$35:$G$41,B11,$H$35:$H$41)) -> 0 | G11: PIX | I11: 10 | O11: =IF(C16=0,0,1) -> 1 | R11: =IF(vend14[[#This Row],[Nº Venda]]>1,1,0) -> 0
B12: CTD | C12: =(SUMIF($G$2:$G$31,B12,$I$2:$I$31))+(SUMIF($G$35:$G$41,B12,$H$35:$H$41)) -> 600 | R12: =IF(vend14[[#This Row],[Nº Venda]]>1,1,0) -> 0
B13: CTC | C13: =(SUMIF($G$2:$G$31,B13,$I$2:$I$31))+(SUMIF($G$35:$G$41,B13,$H$35:$H$41)) -> 540 | K13: OS Entregue no Dia | R13: =IF(vend14[[#This Row],[Nº Venda]]>1,1,0) -> 0
B14: PCTC | C14: =(SUMIF($G$2:$G$31,B14,$I$2:$I$31))+(SUMIF($G$35:$G$41,B14,$H$35:$H$41)) -> 0 | K14: OS | L14: Vendedor | M14: CARNE | R14: =IF(vend14[[#This Row],[Nº Venda]]>1,1,0) -> 0
B15: PIX | C15: =(SUMIF($G$2:$G$31,B15,$I$2:$I$31))+(SUMIF($G$35:$G$41,B15,$H$35:$H$41)) -> 160 | K15: 10072 | L15: TATY | M15: Não | R15: =IF(vend14[[#This Row],[Nº Venda]]>1,1,0) -> 0
B16: Total | C16: =SUM(C11:C15) -> 1300 | K16: 10437 | L16: ROGÉRIO | M16: Não | R16: =IF(vend14[[#This Row],[Nº Venda]]>1,1,0) -> 0
K17: 10548 | L17: ROGÉRIO | M17: Não | R17: =IF(vend14[[#This Row],[Nº Venda]]>1,1,0) -> 0
B18: Entrega de Carne | K18: 10599 | L18: ROGÉRIO | M18: Não | R18: =IF(vend14[[#This Row],[Nº Venda]]>1,1,0) -> 0
B19: =COUNT(entr_carn14[OS]) -> 0 | C19: =SUM(entr_carn14[Valor Total]) -> 0 | K19: 10650 | L19: TATY | M19: Não | R19: =IF(vend14[[#This Row],[Nº Venda]]>1,1,0) -> 0
B20: Total | C20: =SUM(C19:C19) -> 0 | K20: 10677 | L20: ROGÉRIO | M20: Não | R20: =IF(vend14[[#This Row],[Nº Venda]]>1,1,0) -> 0
K21: 10678 | L21: ROGÉRIO | M21: Não
B22: Venda | C22: =C5 -> 650 | K22: 10680 | L22: ROGÉRIO | M22: Não
E24: Restante Entrada
E25: Nº Venda | F25: Cliente | G25: Forma de Pgto | H25: Valor Venda | I25: Entrada
E26: 10599 | F26: VIVIAN SAORI | G26: CTD | I26: 500
E33: Recebimento de Carnê | K33: Entrega de Carne
E34: OS | F34: Cliente | G34: Forma de Pgto | H34: Valor Parcela | I34: Nº Parcela | K34: OS | L34: Parcelas | M34: Valor Total
E35: 10192 | F35: MARTA VAZ | G35: PIX | H35: 150 | I35: PARC. 2/6
Q40: Total de OS | R40: =SUM(R6:R21) -> 5

Sheet 15
B1: ='14'!B1+1 -> 45731
B2: Fechamento Diário do Caixa
B4: Saldo Inicial | C4: 0 | E4: Vendas | K4: Despesas
B5: Vendas | C5: =SUMIF(I6:I31,">0",H6:H31) -> 965 | E5: Nº Venda | F5: Cliente | G5: Forma de Pgto | H5: Valor Venda | I5: Entrada | K5: Descrição | L5: Tipo de Pagto | M5: Valor
B6: Entrada | C6: =C16 -> 600 | E6: 10727 | F6: SABRINA CARVALHO CRESPO | G6: CTC | H6: 220 | I6: 220 | R6: =IF(vend15[[#This Row],[Nº Venda]]>1,1,0) -> 1
B7: Despesas | C7: =SUM(M6:M11) -> 0 | E7: 10728 | F7: NICOLE PAULINO DOS SANTOS | G7: DN | H7: 745 | I7: 200 | R7: =IF(vend15[[#This Row],[Nº Venda]]>1,1,0) -> 1
B8: Total entrada | C8: =SUM(C6:C7) -> 600 | R8: =IF(vend15[[#This Row],[Nº Venda]]>1,1,0) -> 0
R9: =IF(vend15[[#This Row],[Nº Venda]]>1,1,0) -> 0
B10: Tipos de Pagtos | R10: =IF(vend15[[#This Row],[Nº Venda]]>1,1,0) -> 0
B11: DN | C11: =(SUMIF($G$2:$G$31,B11,$I$2:$I$31))+(SUMIF($G$35:$G$41,B11,$H$35:$H$41)) -> 200 | O11: =IF(C16=0,0,1) -> 1 | R11: =IF(vend15[[#This Row],[Nº Venda]]>1,1,0) -> 0
B12: CTD | C12: =(SUMIF($G$2:$G$31,B12,$I$2:$I$31))+(SUMIF($G$35:$G$41,B12,$H$35:$H$41)) -> 0 | R12: =IF(vend15[[#This Row],[Nº Venda]]>1,1,0) -> 0
B13: CTC | C13: =(SUMIF($G$2:$G$31,B13,$I$2:$I$31))+(SUMIF($G$35:$G$41,B13,$H$35:$H$41)) -> 220 | K13: OS Entregue no Dia | R13: =IF(vend15[[#This Row],[Nº Venda]]>1,1,0) -> 0
B14: PCTC | C14: =(SUMIF($G$2:$G$31,B14,$I$2:$I$31))+(SUMIF($G$35:$G$41,B14,$H$35:$H$41)) -> 0 | K14: OS | L14: Vendedor | M14: CARNE | R14: =IF(vend15[[#This Row],[Nº Venda]]>1,1,0) -> 0
B15: PIX | C15: =(SUMIF($G$2:$G$31,B15,$I$2:$I$31))+(SUMIF($G$35:$G$41,B15,$H$35:$H$41)) -> 180 | K15: 10552 | L15: ROGÉRIO | M15: Não | R15: =IF(vend15[[#This Row],[Nº Venda]]>1,1,0) -> 0
B16: Total | C16: =SUM(C11:C15) -> 600 | K16: 10676 | L16: ROGÉRIO | M16: Não | R16: =IF(vend15[[#This Row],[Nº Venda]]>1,1,0) -> 0
K17: 10631 | L17: ROGÉRIO | M17: Não | R17: =IF(vend15[[#This Row],[Nº Venda]]>1,1,0) -> 0
B18: Entrega de Carne | K18: 10588 | L18: ROGÉRIO | M18: Não | R18: =IF(vend15[[#This Row],[Nº Venda]]>1,1,0) -> 0
B19: =COUNT(entr_carn15[OS]) -> 0 | C19: =SUM(entr_carn15[Valor Total]) -> 0 | K19: 10662 | L19: TATY | M19: Não | R19: =IF(vend15[[#This Row],[Nº Venda]]>1,1,0) -> 0
B20: Total | C20: =SUM(C19:C19) -> 0 | K20: 10663 | L20: TATY | M20: Não | R20: =IF(vend15[[#This Row],[Nº Venda]]>1,1,0) -> 0
B22: Venda | C22: =C5 -> 965
E24: Restante Entrada
E25: Nº Venda | F25: Cliente | G25: Forma de Pgto | H25: Valor Venda | I25: Entrada
E33: Recebimento de Carnê | K33: Entrega de Carne
E34: OS | F34: Cliente | G34: Forma de Pgto | H34: Valor Parcela | I34: Nº Parcela | K34: OS | L34: Parcelas | M34: Valor Total
E35: 9757 | F35: CARLINHOS FERREIRA | G35: PIX | H35: 180 | I35: PARC. 6/6
Q40: Total de OS | R40: =SUM(R6:R21) -> 2

Sheet 17
B1: ='16'!B1+1 -> 45733
B2: Fechamento Diário do Caixa
B4: Saldo Inicial | C4: 0 | E4: Vendas | K4: Despesas
B5: Vendas | C5: =SUMIF(I6:I31,">0",H6:H31) -> 438.9 | E5: Nº Venda | F5: Cliente | G5: Forma de Pgto | H5: Valor Venda | I5: Entrada | K5: Descrição | L5: Tipo de Pagto | M5: Valor
B6: Entrada | C6: =C16 -> 642.04 | E6: 10681 | F6: ANA PAULA VERGINIA DA SILVA | G6: PIX | H6: 30 | I6: 10 | R6: =IF(vend17[[#This Row],[Nº Venda]]>1,1,0) -> 1
B7: Despesas | C7: =SUM(M6:M11) -> 0 | E7: 10682 | F7: GERTRUDES MADALENA BARBETA MORIJASU | G7: CTC | H7: 200 | I7: 200 | R7: =IF(vend17[[#This Row],[Nº Venda]]>1,1,0) -> 1
B8: Total entrada | C8: =SUM(C6:C7) -> 642.04 | E8: 10683 | F8: MARIA JOSE BORGES DOS SANTOS | G8: CTC | H8: 179.9 | I8: 179.9 | R8: =IF(vend17[[#This Row],[Nº Venda]]>1,1,0) -> 1
E9: 10684 | F9: MARIA JOSE SOUZA OLIVEIRA | G9: DN | H9: 29 | I9: 15 | R9: =IF(vend17[[#This Row],[Nº Venda]]>1,1,0) -> 1
B10: Tipos de Pagtos | R10: =IF(vend17[[#This Row],[Nº Venda]]>1,1,0) -> 0
B11: DN | C11: =(SUMIF($G$2:$G$31,B11,$I$2:$I$31))+(SUMIF($G$35:$G$41,B11,$H$35:$H$41)) -> 115 | O11: =IF(C16=0,0,1) -> 1 | R11: =IF(vend17[[#This Row],[Nº Venda]]>1,1,0) -> 0
B12: CTD | C12: =(SUMIF($G$2:$G$31,B12,$I$2:$I$31))+(SUMIF($G$35:$G$41,B12,$H$35:$H$41)) -> 117.14 | R12: =IF(vend17[[#This Row],[Nº Venda]]>1,1,0) -> 0
B13: CTC | C13: =(SUMIF($G$2:$G$31,B13,$I$2:$I$31))+(SUMIF($G$35:$G$41,B13,$H$35:$H$41)) -> 379.9 | K13: OS Entregue no Dia | R13: =IF(vend17[[#This Row],[Nº Venda]]>1,1,0) -> 0
B14: PCTC | C14: =(SUMIF($G$2:$G$31,B14,$I$2:$I$31))+(SUMIF($G$35:$G$41,B14,$H$35:$H$41)) -> 0 | K14: OS | L14: Vendedor | M14: CARNE | R14: =IF(vend17[[#This Row],[Nº Venda]]>1,1,0) -> 0
B15: PIX | C15: =(SUMIF($G$2:$G$31,B15,$I$2:$I$31))+(SUMIF($G$35:$G$41,B15,$H$35:$H$41)) -> 30 | K15: 10479 | L15: TATY | M15: Não | R15: =IF(vend17[[#This Row],[Nº Venda]]>1,1,0) -> 0
B16: Total | C16: =SUM(C11:C15) -> 642.04 | K16: 10684 | L16: TATY | M16: Não | R16: =IF(vend17[[#This Row],[Nº Venda]]>1,1,0) -> 0
R17: =IF(vend17[[#This Row],[Nº Venda]]>1,1,0) -> 0
B18: Entrega de Carne | R18: =IF(vend17[[#This Row],[Nº Venda]]>1,1,0) -> 0
B19: =COUNT(entr_carn17[OS]) -> 0 | C19: =SUM(entr_carn17[Valor Total]) -> 0 | R19: =IF(vend17[[#This Row],[Nº Venda]]>1,1,0) -> 0
B20: Total | C20: =SUM(C19:C19) -> 0 | R20: =IF(vend17[[#This Row],[Nº Venda]]>1,1,0) -> 0
B22: Venda | C22: =C5 -> 438.9
E24: Restante Entrada
E25: Nº Venda | F25: Cliente | G25: Forma de Pgto | H25: Valor Venda | I25: Entrada
E33: Recebimento de Carnê | K33: Entrega de Carne
E34: OS | F34: Cliente | G34: Forma de Pgto | H34: Valor Parcela | I34: Nº Parcela | K34: OS | L34: Parcelas | M34: Valor Total
E35: 9894 | F35: ANTONIO MARIM | G35: CTD | H35: 117.14 | I35: PARC. 5/7
E36: 10456 | F36: MARIA JOSE SOUZA OLIVEIRA | G36: DN | H36: 100 | I36: PARC. 1/1
E37: 10553 | F37: ANA PAULA VERGINIA DA SILVA | G37: PIX | H37: 20 | I37: PARC. 1/1
Q40: Total de OS | R40: =SUM(R6:R21) -> 4

Sheet 16
B1: ='15'!B1+1 -> 45732
B2: Fechamento Diário do Caixa
B4: Saldo Inicial | C4: 0 | E4: Vendas | K4: Despesas
B5: Vendas | C5: =SUMIF(I6:I31,">0",H6:H31) -> 0 | E5: Nº Venda | F5: Cliente | G5: Forma de Pgto | H5: Valor Venda | I5: Entrada | K5: Descrição | L5: Tipo de Pagto | M5: Valor
B6: Entrada | C6: =C16 -> 0 | R6: =IF(vend16[[#This Row],[Nº Venda]]>1,1,0) -> 0
B7: Despesas | C7: =SUM(M6:M11) -> 0 | R7: =IF(vend16[[#This Row],[Nº Venda]]>1,1,0) -> 0
B8: Total entrada | C8: =SUM(C6:C7) -> 0 | R8: =IF(vend16[[#This Row],[Nº Venda]]>1,1,0) -> 0
R9: =IF(vend16[[#This Row],[Nº Venda]]>1,1,0) -> 0
B10: Tipos de Pagtos | R10: =IF(vend16[[#This Row],[Nº Venda]]>1,1,0) -> 0
B11: DN | C11: =(SUMIF($G$2:$G$31,B11,$I$2:$I$31))+(SUMIF($G$35:$G$41,B11,$H$35:$H$41)) -> 0 | O11: =IF(C16=0,0,1) -> 0 | R11: =IF(vend16[[#This Row],[Nº Venda]]>1,1,0) -> 0
B12: CTD | C12: =(SUMIF($G$2:$G$31,B12,$I$2:$I$31))+(SUMIF($G$35:$G$41,B12,$H$35:$H$41)) -> 0 | R12: =IF(vend16[[#This Row],[Nº Venda]]>1,1,0) -> 0
B13: CTC | C13: =(SUMIF($G$2:$G$31,B13,$I$2:$I$31))+(SUMIF($G$35:$G$41,B13,$H$35:$H$41)) -> 0 | K13: OS Entregue no Dia | R13: =IF(vend16[[#This Row],[Nº Venda]]>1,1,0) -> 0
B14: PCTC | C14: =(SUMIF($G$2:$G$31,B14,$I$2:$I$31))+(SUMIF($G$35:$G$41,B14,$H$35:$H$41)) -> 0 | K14: OS | L14: Vendedor | M14: CARNE | R14: =IF(vend16[[#This Row],[Nº Venda]]>1,1,0) -> 0
B15: PIX | C15: =(SUMIF($G$2:$G$31,B15,$I$2:$I$31))+(SUMIF($G$35:$G$41,B15,$H$35:$H$41)) -> 0 | R15: =IF(vend16[[#This Row],[Nº Venda]]>1,1,0) -> 0
B16: Total | C16: =SUM(C11:C15) -> 0 | R16: =IF(vend16[[#This Row],[Nº Venda]]>1,1,0) -> 0
R17: =IF(vend16[[#This Row],[Nº Venda]]>1,1,0) -> 0
B18: Entrega de Carne | R18: =IF(vend16[[#This Row],[Nº Venda]]>1,1,0) -> 0
B19: =COUNT(entr_carn16[OS]) -> 0 | C19: =SUM(entr_carn16[Valor Total]) -> 0 | R19: =IF(vend16[[#This Row],[Nº Venda]]>1,1,0) -> 0
B20: Total | C20: =SUM(C19:C19) -> 0 | R20: =IF(vend16[[#This Row],[Nº Venda]]>1,1,0) -> 0
B22: Venda | C22: =C5 -> 0
E24: Restante Entrada
E25: Nº Venda | F25: Cliente | G25: Forma de Pgto | H25: Valor Venda | I25: Entrada
E33: Recebimento de Carnê | K33: Entrega de Carne
E34: OS | F34: Cliente | G34: Forma de Pgto | H34: Valor Parcela | I34: Nº Parcela | K34: OS | L34: Parcelas | M34: Valor Total
Q40: Total de OS | R40: =SUM(R6:R21) -> 0

Sheet 18
B1: ='17'!B1+1 -> 45734
B2: Fechamento Diário do Caixa
B4: Saldo Inicial | C4: 0 | E4: Vendas | K4: Despesas
B5: Vendas | C5: =SUMIF(I6:I31,">0",H6:H31) -> 380 | E5: Nº Venda | F5: Cliente | G5: Forma de Pgto | H5: Valor Venda | I5: Entrada | K5: Descrição | L5: Tipo de Pagto | M5: Valor
B6: Entrada | C6: =C16 -> 630 | E6: 10685 | F6: MARCOS FERNANDO DA SILVA | G6: CTC | H6: 350 | I6: 350 | R6: =IF(vend18[[#This Row],[Nº Venda]]>1,1,0) -> 1
B7: Despesas | C7: =SUM(M6:M11) -> 0 | E7: 10686 | F7: VALDEMICE BATISTA DOS SANTOS | G7: GARANTIA | H7: 0 | I7: 0 | R7: =IF(vend18[[#This Row],[Nº Venda]]>1,1,0) -> 1
B8: Total entrada | C8: =SUM(C6:C7) -> 630 | E8: 10687 | F8: JOÃO FERNANDO DE ANDRADE | G8: CTD | H8: 30 | I8: 30 | R8: =IF(vend18[[#This Row],[Nº Venda]]>1,1,0) -> 1
R9: =IF(vend18[[#This Row],[Nº Venda]]>1,1,0) -> 0
B10: Tipos de Pagtos | R10: =IF(vend18[[#This Row],[Nº Venda]]>1,1,0) -> 0
B11: DN | C11: =(SUMIF($G$2:$G$31,B11,$I$2:$I$31))+(SUMIF($G$35:$G$41,B11,$H$35:$H$41)) -> 150 | O11: =IF(C16=0,0,1) -> 1 | R11: =IF(vend18[[#This Row],[Nº Venda]]>1,1,0) -> 0
B12: CTD | C12: =(SUMIF($G$2:$G$31,B12,$I$2:$I$31))+(SUMIF($G$35:$G$41,B12,$H$35:$H$41)) -> 30 | R12: =IF(vend18[[#This Row],[Nº Venda]]>1,1,0) -> 0
B13: CTC | C13: =(SUMIF($G$2:$G$31,B13,$I$2:$I$31))+(SUMIF($G$35:$G$41,B13,$H$35:$H$41)) -> 350 | K13: OS Entregue no Dia | R13: =IF(vend18[[#This Row],[Nº Venda]]>1,1,0) -> 0
B14: PCTC | C14: =(SUMIF($G$2:$G$31,B14,$I$2:$I$31))+(SUMIF($G$35:$G$41,B14,$H$35:$H$41)) -> 0 | K14: OS | L14: Vendedor | M14: CARNE | R14: =IF(vend18[[#This Row],[Nº Venda]]>1,1,0) -> 0
B15: PIX | C15: =(SUMIF($G$2:$G$31,B15,$I$2:$I$31))+(SUMIF($G$35:$G$41,B15,$H$35:$H$41)) -> 100 | K15: 10614 | L15: TATY | M15: Não | R15: =IF(vend18[[#This Row],[Nº Venda]]>1,1,0) -> 0
B16: Total | C16: =SUM(C11:C15) -> 630 | K16: 10651 | L16: TATY | M16: Sim | R16: =IF(vend18[[#This Row],[Nº Venda]]>1,1,0) -> 0
K17: 10652 | L17: TATY | M17: Não | R17: =IF(vend18[[#This Row],[Nº Venda]]>1,1,0) -> 0
B18: Entrega de Carne | K18: 10653 | L18: TATY | M18: Não | R18: =IF(vend18[[#This Row],[Nº Venda]]>1,1,0) -> 0
B19: =COUNT(entr_carn18[OS]) -> 2 | C19: =SUM(entr_carn18[Valor Total]) -> 1485 | K19: 10659 | L19: ROGÉRIO | M19: Sim | R19: =IF(vend18[[#This Row],[Nº Venda]]>1,1,0) -> 0
B20: Total | C20: =SUM(C19:C19) -> 1485 | K20: 10682 | L20: ROGÉRIO | M20: Não | R20: =IF(vend18[[#This Row],[Nº Venda]]>1,1,0) -> 0
K21: 10687 | L21: TATY | M21: Não
B22: Venda | C22: =C5 -> 380
E24: Restante Entrada
E25: Nº Venda | F25: Cliente | G25: Forma de Pgto | H25: Valor Venda | I25: Entrada
E26: 10658 | F26: MARIA NEUSA DOS SANTOS | G26: DN | H26: 0 | I26: 75
E27: 10659 | F27: MARIA NEUSA DOS SANTOS | G27: DN | H27: 0 | I27: 75
E33: Recebimento de Carnê | K33: Entrega de Carne
E34: OS | F34: Cliente | G34: Forma de Pgto | H34: Valor Parcela | I34: Nº Parcela | K34: OS | L34: Parcelas | M34: Valor Total
E35: 9960 | F35: RONÉLIA DA SILVA | G35: PIX | H35: 100 | I35: PARC. 4/8 | K35: 10651 | L35: 7 | M35: 1085
K36: 10659 | L36: 4 | M36: 400
Q40: Total de OS | R40: =SUM(R6:R21) -> 3

Sheet 19
B1: ='18'!B1+1 -> 45735
B2: Fechamento Diário do Caixa
B4: Saldo Inicial | C4: 0 | E4: Vendas | K4: Despesas
B5: Vendas | C5: =SUMIF(I6:I31,">0",H6:H31) -> 3419.6 | E5: Nº Venda | F5: Cliente | G5: Forma de Pgto | H5: Valor Venda | I5: Entrada | K5: Descrição | L5: Tipo de Pagto | M5: Valor
B6: Entrada | C6: =C16 -> 3739.6 | E6: 10688 | F6: Claudia Bertoldo dos Santos | G6: CTD | H6: 450 | I6: 450 | R6: =IF(vend19[[#This Row],[Nº Venda]]>1,1,0) -> 1
B7: Despesas | C7: =SUM(M6:M11) -> 0 | E7: 10689 | F7: Marcos Fernando da Silva | G7: CTC | H7: 50 | I7: 50 | R7: =IF(vend19[[#This Row],[Nº Venda]]>1,1,0) -> 1
B8: Total entrada | C8: =SUM(C6:C7) -> 3739.6 | E8: 10690 | F8: Jefferson | G8: SS | H8: 30 | I8: 0 | R8: =IF(vend19[[#This Row],[Nº Venda]]>1,1,0) -> 1
E9: 10691 | F9: Irani de Souza Silva | G9: CTC | H9: 99.9 | I9: 99.9 | R9: =IF(vend19[[#This Row],[Nº Venda]]>1,1,0) -> 1
B10: Tipos de Pagtos | E10: 10692 | F10: Marcelo Vieira Barbosa | G10: CTC | H10: 1700 | I10: 1700 | R10: =IF(vend19[[#This Row],[Nº Venda]]>1,1,0) -> 1
B11: DN | C11: =(SUMIF($G$2:$G$31,B11,$I$2:$I$31))+(SUMIF($G$35:$G$41,B11,$H$35:$H$41)) -> 0 | E11: 10693 | F11: Marcelo Vieira Barbosa | G11: CTC | H11: 999.9 | I11: 999.9 | O11: =IF(C16=0,0,1) -> 1 | R11: =IF(vend19[[#This Row],[Nº Venda]]>1,1,0) -> 1
B12: CTD | C12: =(SUMIF($G$2:$G$31,B12,$I$2:$I$31))+(SUMIF($G$35:$G$41,B12,$H$35:$H$41)) -> 809.9 | E12: 10696 | F12: Bruno Correira | G12: CTC | H12: 79.8 | I12: 39.9 | R12: =IF(vend19[[#This Row],[Nº Venda]]>1,1,0) -> 1
B13: CTC | C13: =(SUMIF($G$2:$G$31,B13,$I$2:$I$31))+(SUMIF($G$35:$G$41,B13,$H$35:$H$41)) -> 2889.7 | E13: 10696 | F13: Bruno Correira | G13: CTD | H13: 0 | I13: 39.9 | K13: OS Entregue no Dia | R13: =IF(vend19[[#This Row],[Nº Venda]]>1,1,0) -> 1
B14: PCTC | C14: =(SUMIF($G$2:$G$31,B14,$I$2:$I$31))+(SUMIF($G$35:$G$41,B14,$H$35:$H$41)) -> 0 | K14: OS | L14: Vendedor | M14: CARNE | R14: =IF(vend19[[#This Row],[Nº Venda]]>1,1,0) -> 0
B15: PIX | C15: =(SUMIF($G$2:$G$31,B15,$I$2:$I$31))+(SUMIF($G$35:$G$41,B15,$H$35:$H$41)) -> 40 | K15: 10501 | L15: ROGÉRIO | M15: Não | R15: =IF(vend19[[#This Row],[Nº Venda]]>1,1,0) -> 0
B16: Total | C16: =SUM(C11:C15) -> 3739.6 | K16: 10681 | L16: TATY | M16: Não | R16: =IF(vend19[[#This Row],[Nº Venda]]>1,1,0) -> 0
K17: 10686 | L17: TATY | M17: Não | R17: =IF(vend19[[#This Row],[Nº Venda]]>1,1,0) -> 0
B18: Entrega de Carne | K18: 10696 | L18: TATY | M18: Não | R18: =IF(vend19[[#This Row],[Nº Venda]]>1,1,0) -> 0
B19: =COUNT(entr_carn19[OS]) -> 0 | C19: =SUM(entr_carn19[Valor Total]) -> 0 | R19: =IF(vend19[[#This Row],[Nº Venda]]>1,1,0) -> 0
B20: Total | C20: =SUM(C19:C19) -> 0 | R20: =IF(vend19[[#This Row],[Nº Venda]]>1,1,0) -> 0
B22: Venda | C22: =C5 -> 3419.6
E24: Restante Entrada
E25: Nº Venda | F25: Cliente | G25: Forma de Pgto | H25: Valor Venda | I25: Entrada
E26: 8932 | F26: Maria Imaculada do Carmo Shinkado | G26: CTD | H26: 0 | I26: 290
E27: 10501 | F27: Eleni de Lima Bico | G27: PIX | H27: 40 | I27: 40
E28: 10681 | F28: Ana Paula Verginia da Silva | G28: CTD | H28: 0 | I28: 30
E33: Recebimento de Carnê | K33: Entrega de Carne
E34: OS | F34: Cliente | G34: Forma de Pgto | H34: Valor Parcela | I34: Nº Parcela | K34: OS | L34: Parcelas | M34: Valor Total
Q40: Total de OS | R40: =SUM(R6:R21) -> 8

Sheet 20
B1: ='19'!B1+1 -> 45736
B2: Fechamento Diário do Caixa
B4: Saldo Inicial | C4: 0 | E4: Vendas | K4: Despesas
B5: Vendas | C5: =SUMIF(I6:I31,">0",H6:H31) -> 7487.99 | E5: Nº Venda | F5: Cliente | G5: Forma de Pgto | H5: Valor Venda | I5: Entrada | K5: Descrição | L5: Tipo de Pagto | M5: Valor
B6: Entrada | C6: =C16 -> 7963 | E6: 10694 | F6: MARCIO VINICIUS MELLO PELONHA | G6: CTC | H6: 990 | I6: 990 | R6: =IF(vend20[[#This Row],[Nº Venda]]>1,1,0) -> 1
B7: Despesas | C7: =SUM(M6:M11) -> 0 | E7: 10695 | F7: MARCIO VINICIUS MELLO PELONHA | G7: CTC | H7: 234 | I7: 234 | R7: =IF(vend20[[#This Row],[Nº Venda]]>1,1,0) -> 1
B8: Total entrada | C8: =SUM(C6:C7) -> 7963 | E8: 10697 | F8: MARIA FERREIRA ALVES DE SOUZA | G8: GARANTIA | H8: 0 | I8: 0 | R8: =IF(vend20[[#This Row],[Nº Venda]]>1,1,0) -> 1
E9: 10698 | F9: LEONILDA SIQUEIRA DA SILVA | G9: GARANTIA | H9: 0 | I9: 0 | R9: =IF(vend20[[#This Row],[Nº Venda]]>1,1,0) -> 1
B10: Tipos de Pagtos | E10: 10699 | F10: SELMA BORGES | G10: SS | H10: 40 | I10: 0 | R10: =IF(vend20[[#This Row],[Nº Venda]]>1,1,0) -> 1
B11: DN | C11: =(SUMIF($G$2:$G$31,B11,$I$2:$I$31))+(SUMIF($G$35:$G$41,B11,$H$35:$H$41)) -> 0 | E11: 10700 | F11: MARIA ANGELA DE ARAUJO NUNES | G11: CTC | H11: 3614 | I11: 3614 | O11: =IF(C16=0,0,1) -> 1 | R11: =IF(vend20[[#This Row],[Nº Venda]]>1,1,0) -> 1
B12: CTD | C12: =(SUMIF($G$2:$G$31,B12,$I$2:$I$31))+(SUMIF($G$35:$G$41,B12,$H$35:$H$41)) -> 225 | E12: 10701 | F12: MARIA ANGELA DE ARAUJO NUNES | G12: SS | H12: 0 | I12: 0 | R12: =IF(vend20[[#This Row],[Nº Venda]]>1,1,0) -> 1
B13: CTC | C13: =(SUMIF($G$2:$G$31,B13,$I$2:$I$31))+(SUMIF($G$35:$G$41,B13,$H$35:$H$41)) -> 6988 | E13: 10702 | F13: REGINA CUSTODIA DA SILVA | G13: SS | H13: 630 | I13: 0 | K13: OS Entregue no Dia | R13: =IF(vend20[[#This Row],[Nº Venda]]>1,1,0) -> 1
B14: PCTC | C14: =(SUMIF($G$2:$G$31,B14,$I$2:$I$31))+(SUMIF($G$35:$G$41,B14,$H$35:$H$41)) -> 0 | E14: 10703 | F14: APARECIDA MARAES LIMA | G14: PIX | H14: 1499.99 | I14: 750 | K14: OS | L14: Vendedor | M14: CARNE | R14: =IF(vend20[[#This Row],[Nº Venda]]>1,1,0) -> 1
B15: PIX | C15: =(SUMIF($G$2:$G$31,B15,$I$2:$I$31))+(SUMIF($G$35:$G$41,B15,$H$35:$H$41)) -> 750 | E15: 10704 | F15: LEANDRO GONÇALVES RIBEIRO | G15: CTC | H15: 300 | I15: 300 | K15: 10648 | L15: JOCY | M15: Não | R15: =IF(vend20[[#This Row],[Nº Venda]]>1,1,0) -> 1
B16: Total | C16: =SUM(C11:C15) -> 7963 | E16: 10705 | F16: LEANDRO GONÇALVES RIBEIRO | G16: CTC | H16: 850 | I16: 850 | K16: 10669 | L16: TATY | M16: Não | R16: =IF(vend20[[#This Row],[Nº Venda]]>1,1,0) -> 1
K17: 10671 | L17: ROGÉRIO | M17: Não | R17: =IF(vend20[[#This Row],[Nº Venda]]>1,1,0) -> 0
B18: Entrega de Carne | R18: =IF(vend20[[#This Row],[Nº Venda]]>1,1,0) -> 0
B19: =COUNT(entr_carn20[OS]) -> 0 | C19: =SUM(entr_carn20[Valor Total]) -> 0 | R19: =IF(vend20[[#This Row],[Nº Venda]]>1,1,0) -> 0
B20: Total | C20: =SUM(C19:C19) -> 0 | R20: =IF(vend20[[#This Row],[Nº Venda]]>1,1,0) -> 0
B22: Venda | C22: =C5 -> 7487.99
E24: Restante Entrada
E25: Nº Venda | F25: Cliente | G25: Forma de Pgto | H25: Valor Venda | I25: Entrada
E26: 10648 | F26: JOSE APARECIDO ALVES DE LIMA | G26: CTC | H26: 0 | I26: 1000
E33: Recebimento de Carnê | K33: Entrega de Carne
E34: OS | F34: Cliente | G34: Forma de Pgto | H34: Valor Parcela | I34: Nº Parcela | K34: OS | L34: Parcelas | M34: Valor Total
E35: 9686 | F35: JAQUELINE SANTOS | G35: CTD | H35: 225 | I35: PARC. 7/8
Q40: Total de OS | R40: =SUM(R6:R21) -> 11

Sheet 21
B1: ='20'!B1+1 -> 45737
B2: Fechamento Diário do Caixa
B4: Saldo Inicial | C4: 0 | E4: Vendas | K4: Despesas
B5: Vendas | C5: =SUMIF(I6:I31,">0",H6:H31) -> 2779.98 | E5: Nº Venda | F5: Cliente | G5: Forma de Pgto | H5: Valor Venda | I5: Entrada | K5: Descrição | L5: Tipo de Pagto | M5: Valor
B6: Entrada | C6: =C16 -> 3288.99 | E6: 10706 | F6: NELY MARIA DE OLIVEIRA | G6: PIX | H6: 1170 | I6: 600 | R6: =IF(vend21[[#This Row],[Nº Venda]]>1,1,0) -> 1
B7: Despesas | C7: =SUM(M6:M11) -> 0 | E7: 10707 | F7: NELY MARIA DE OLIVEIRA | G7: CTC | H7: 450 | I7: 450 | R7: =IF(vend21[[#This Row],[Nº Venda]]>1,1,0) -> 1
B8: Total entrada | C8: =SUM(C6:C7) -> 3288.99 | E8: 10708 | F8: LENI DE SOUZA VERAS | G8: CTC | H8: 230 | I8: 230 | R8: =IF(vend21[[#This Row],[Nº Venda]]>1,1,0) -> 1
E9: 10709 | F9: CARMELINDA DE SOUSA FERRAMOSCA | G9: DN | H9: 429.99 | I9: 70 | R9: =IF(vend21[[#This Row],[Nº Venda]]>1,1,0) -> 1
B10: Tipos de Pagtos | E10: 10710 | F10: NAYARA ALVES FERNANDES | G10: PIX | H10: 499.99 | I10: 499.99 | R10: =IF(vend21[[#This Row],[Nº Venda]]>1,1,0) -> 1
B11: DN | C11: =(SUMIF($G$2:$G$31,B11,$I$2:$I$31))+(SUMIF($G$35:$G$41,B11,$H$35:$H$41)) -> 70 | O11: =IF(C16=0,0,1) -> 1 | R11: =IF(vend21[[#This Row],[Nº Venda]]>1,1,0) -> 0
B12: CTD | C12: =(SUMIF($G$2:$G$31,B12,$I$2:$I$31))+(SUMIF($G$35:$G$41,B12,$H$35:$H$41)) -> 1389 | R12: =IF(vend21[[#This Row],[Nº Venda]]>1,1,0) -> 0
B13: CTC | C13: =(SUMIF($G$2:$G$31,B13,$I$2:$I$31))+(SUMIF($G$35:$G$41,B13,$H$35:$H$41)) -> 680 | K13: OS Entregue no Dia | R13: =IF(vend21[[#This Row],[Nº Venda]]>1,1,0) -> 0
B14: PCTC | C14: =(SUMIF($G$2:$G$31,B14,$I$2:$I$31))+(SUMIF($G$35:$G$41,B14,$H$35:$H$41)) -> 0 | K14: OS | L14: Vendedor | M14: CARNE | R14: =IF(vend21[[#This Row],[Nº Venda]]>1,1,0) -> 0
B15: PIX | C15: =(SUMIF($G$2:$G$31,B15,$I$2:$I$31))+(SUMIF($G$35:$G$41,B15,$H$35:$H$41)) -> 1149.99 | K15: 10578 | L15: JOCY | M15: Não | R15: =IF(vend21[[#This Row],[Nº Venda]]>1,1,0) -> 0
B16: Total | C16: =SUM(C11:C15) -> 3288.99 | K16: 10593 | L16: ROGÉRIO | M16: Não | R16: =IF(vend21[[#This Row],[Nº Venda]]>1,1,0) -> 0
K17: 10601 | L17: JOCY | M17: Não | R17: =IF(vend21[[#This Row],[Nº Venda]]>1,1,0) -> 0
B18: Entrega de Carne | K18: 10616 | L18: TATY | M18: Não | R18: =IF(vend21[[#This Row],[Nº Venda]]>1,1,0) -> 0
B19: =COUNT(entr_carn21[OS]) -> 0 | C19: =SUM(entr_carn21[Valor Total]) -> 0 | K19: 10645 | L19: ROGÉRIO | M19: Não | R19: =IF(vend21[[#This Row],[Nº Venda]]>1,1,0) -> 0
B20: Total | C20: =SUM(C19:C19) -> 0 | K20: 10670 | L20: ROGÉRIO | M20: Não | R20: =IF(vend21[[#This Row],[Nº Venda]]>1,1,0) -> 0
K21: 10679 | L21: ROGÉRIO | M21: Não
B22: Venda | C22: =C5 -> 2779.98 | K22: 10691 | L22: TATY | M22: Não
K23: 10697 | L23: TATY | M23: Não
E24: Restante Entrada | K24: 10708 | L24: TATY | M24: Não
E25: Nº Venda | F25: Cliente | G25: Forma de Pgto | H25: Valor Venda | I25: Entrada
E26: 10601 | F26: JOSE PEREIRA DA SILVA | G26: CTD | H26: 0 | I26: 900
E27: 10664 | F27: TALITA DE FREITAS GOMES | G27: CTD | H27: 0 | I27: 133
E28: 10665 | F28: TALITA DE FREITAS GOMES | G28: CTD | H28: 0 | I28: 133
E29: 10666 | F29: TALITA DE FREITAS GOMES | G29: CTD | H29: 0 | I29: 133
E33: Recebimento de Carnê | K33: Entrega de Carne
E34: OS | F34: Cliente | G34: Forma de Pgto | H34: Valor Parcela | I34: Nº Parcela | K34: OS | L34: Parcelas | M34: Valor Total
E35: 9956 | F35: ALINE B. DE MELO | G35: CTD | H35: 45 | I35: PARC. 5/6
E36: 9956 | F36: ALINE B. DE MELO | G36: CTD | H36: 45 | I36: PARC. 6/6
E37: 10513 | F37: RODRIGO SILVA DE ARAÚJO | G37: PIX | H37: 50 | I37: PARC. 1/6
Q40: Total de OS | R40: =SUM(R6:R21) -> 5

Sheet 22
B1: ='21'!B1+1 -> 45738
B2: Fechamento Diário do Caixa
B4: Saldo Inicial | C4: 0 | E4: Vendas | K4: Despesas
B5: Vendas | C5: =SUMIF(I6:I31,">0",H6:H31) -> 4088 | E5: Nº Venda | F5: Cliente | G5: Forma de Pgto | H5: Valor Venda | I5: Entrada | K5: Descrição | L5: Tipo de Pagto | M5: Valor
B6: Entrada | C6: =C16 -> 4577 | E6: 10711 | F6: INES DA SILVA MESQUITA | G6: CTD | H6: 100 | I6: 50 | R6: =IF(vend22[[#This Row],[Nº Venda]]>1,1,0) -> 1
B7: Despesas | C7: =SUM(M6:M11) -> 0 | E7: 10711 | F7: INES DA SILVA MESQUITA | G7: DN | H7: 0 | I7: 50 | R7: =IF(vend22[[#This Row],[Nº Venda]]>1,1,0) -> 1
B8: Total entrada | C8: =SUM(C6:C7) -> 4577 | E8: 10712 | F8: CHRISTIAN LIMA GOMES | G8: CTC | H8: 600 | I8: 600 | R8: =IF(vend22[[#This Row],[Nº Venda]]>1,1,0) -> 1
E9: 10713 | F9: CHRISTIAN LIMA GOMES | G9: SS | H9: 0 | I9: 0 | R9: =IF(vend22[[#This Row],[Nº Venda]]>1,1,0) -> 1
B10: Tipos de Pagtos | E10: 10714 | F10: ELISANGELA DA SILVA ARAUJO | G10: CTD | H10: 399 | I10: 399 | R10: =IF(vend22[[#This Row],[Nº Venda]]>1,1,0) -> 1
B11: DN | C11: =(SUMIF($G$2:$G$31,B11,$I$2:$I$31))+(SUMIF($G$35:$G$41,B11,$H$35:$H$41)) -> 190 | E11: 10715 | F11: SAMUEL SILVA FELIX | G11: PIX | H11: 900 | I11: 900 | O11: =IF(C16=0,0,1) -> 1 | R11: =IF(vend22[[#This Row],[Nº Venda]]>1,1,0) -> 1
B12: CTD | C12: =(SUMIF($G$2:$G$31,B12,$I$2:$I$31))+(SUMIF($G$35:$G$41,B12,$H$35:$H$41)) -> 449 | E12: 10716 | F12: SIRLENE ALVES DE GODOY | G12: CTC | H12: 850 | I12: 850 | R12: =IF(vend22[[#This Row],[Nº Venda]]>1,1,0) -> 1
B13: CTC | C13: =(SUMIF($G$2:$G$31,B13,$I$2:$I$31))+(SUMIF($G$35:$G$41,B13,$H$35:$H$41)) -> 3038 | E13: 10717 | F13: MARCELO RENATO DE GODOY | G13: CTC | H13: 1199 | I13: 1199 | K13: OS Entregue no Dia | R13: =IF(vend22[[#This Row],[Nº Venda]]>1,1,0) -> 1
B14: PCTC | C14: =(SUMIF($G$2:$G$31,B14,$I$2:$I$31))+(SUMIF($G$35:$G$41,B14,$H$35:$H$41)) -> 0 | E14: 10718 | F14: MISLENE CRUZ COSTA | G14: DN | H14: 40 | I14: 40 | K14: OS | L14: Vendedor | M14: CARNE | R14: =IF(vend22[[#This Row],[Nº Venda]]>1,1,0) -> 1
B15: PIX | C15: =(SUMIF($G$2:$G$31,B15,$I$2:$I$31))+(SUMIF($G$35:$G$41,B15,$H$35:$H$41)) -> 900 | K15: 10657 | L15: ROGÉRIO | M15: Não | R15: =IF(vend22[[#This Row],[Nº Venda]]>1,1,0) -> 0
B16: Total | C16: =SUM(C11:C15) -> 4577 | K16: 10660 | L16: ROGÉRIO | M16: Não | R16: =IF(vend22[[#This Row],[Nº Venda]]>1,1,0) -> 0
K17: 10664 | L17: TATY | M17: Sim | R17: =IF(vend22[[#This Row],[Nº Venda]]>1,1,0) -> 0
B18: Entrega de Carne | K18: 10665 | L18: TATY | M18: Sim | R18: =IF(vend22[[#This Row],[Nº Venda]]>1,1,0) -> 0
B19: =COUNT(entr_carn22[OS]) -> 1 | C19: =SUM(entr_carn22[Valor Total]) -> 1100 | K19: 10670 | L19: ROGÉRIO | M19: Não | R19: =IF(vend22[[#This Row],[Nº Venda]]>1,1,0) -> 0
B20: Total | C20: =SUM(C19:C19) -> 1100 | K20: 10718 | L20: ARIANI | M20: Não | R20: =IF(vend22[[#This Row],[Nº Venda]]>1,1,0) -> 0
B22: Venda | C22: =C5 -> 4088
E24: Restante Entrada
E25: Nº Venda | F25: Cliente | G25: Forma de Pgto | H25: Valor Venda | I25: Entrada
E26: 10657 | F26: MARCIA DE ALCANTARA BODO PIRES | G26: CTC | H26: 0 | I26: 389
E27: 10657 | F27: MARCIA DE ALCANTARA BODO PIRES | G27: DN | H27: 0 | I27: 100
E33: Recebimento de Carnê | K33: Entrega de Carne
E34: OS | F34: Cliente | G34: Forma de Pgto | H34: Valor Parcela | I34: Nº Parcela | K34: OS | L34: Parcelas | M34: Valor Total
K35: 10664 | L35: 6 | M35: 1100
Q40: Total de OS | R40: =SUM(R6:R21) -> 9

Sheet 23
B1: ='22'!B1+1 -> 45739
B2: Fechamento Diário do Caixa
B4: Saldo Inicial | C4: 0 | E4: Vendas | K4: Despesas
B5: Vendas | C5: =SUMIF(I6:I31,">0",H6:H31) -> 0 | E5: Nº Venda | F5: Cliente | G5: Forma de Pgto | H5: Valor Venda | I5: Entrada | K5: Descrição | L5: Tipo de Pagto | M5: Valor
B6: Entrada | C6: =C16 -> 0 | R6: =IF(vend23[[#This Row],[Nº Venda]]>1,1,0) -> 0
B7: Despesas | C7: =SUM(M6:M11) -> 0 | R7: =IF(vend23[[#This Row],[Nº Venda]]>1,1,0) -> 0
B8: Total entrada | C8: =SUM(C6:C7) -> 0 | R8: =IF(vend23[[#This Row],[Nº Venda]]>1,1,0) -> 0
R9: =IF(vend23[[#This Row],[Nº Venda]]>1,1,0) -> 0
B10: Tipos de Pagtos | R10: =IF(vend23[[#This Row],[Nº Venda]]>1,1,0) -> 0
B11: DN | C11: =(SUMIF($G$2:$G$31,B11,$I$2:$I$31))+(SUMIF($G$35:$G$44,B11,$H$35:$H$44)) -> 0 | O11: =IF(C16=0,0,1) -> 0 | R11: =IF(vend23[[#This Row],[Nº Venda]]>1,1,0) -> 0
B12: CTD | C12: =(SUMIF($G$2:$G$31,B12,$I$2:$I$31))+(SUMIF($G$35:$G$44,B12,$H$35:$H$44)) -> 0 | R12: =IF(vend23[[#This Row],[Nº Venda]]>1,1,0) -> 0
B13: CTC | C13: =(SUMIF($G$2:$G$31,B13,$I$2:$I$31))+(SUMIF($G$35:$G$44,B13,$H$35:$H$44)) -> 0 | K13: OS Entregue no Dia | R13: =IF(vend23[[#This Row],[Nº Venda]]>1,1,0) -> 0
B14: PCTC | C14: =(SUMIF($G$2:$G$31,B14,$I$2:$I$31))+(SUMIF($G$35:$G$44,B14,$H$35:$H$44)) -> 0 | K14: OS | L14: Vendedor | M14: CARNE | R14: =IF(vend23[[#This Row],[Nº Venda]]>1,1,0) -> 0
B15: PIX | C15: =(SUMIF($G$2:$G$31,B15,$I$2:$I$31))+(SUMIF($G$35:$G$44,B15,$H$35:$H$44)) -> 0 | R15: =IF(vend23[[#This Row],[Nº Venda]]>1,1,0) -> 0
B16: Total | C16: =SUM(C11:C15) -> 0 | R16: =IF(vend23[[#This Row],[Nº Venda]]>1,1,0) -> 0
R17: =IF(vend23[[#This Row],[Nº Venda]]>1,1,0) -> 0
B18: Entrega de Carne | R18: =IF(vend23[[#This Row],[Nº Venda]]>1,1,0) -> 0
B19: =COUNT(entr_carn23[OS]) -> 0 | C19: =SUM(entr_carn23[Valor Total]) -> 0 | R19: =IF(vend23[[#This Row],[Nº Venda]]>1,1,0) -> 0
B20: Total | C20: =SUM(C19:C19) -> 0 | R20: =IF(vend23[[#This Row],[Nº Venda]]>1,1,0) -> 0
B22: Venda | C22: =C5 -> 0
E24: Restante Entrada
E25: Nº Venda | F25: Cliente | G25: Forma de Pgto | H25: Valor Venda | I25: Entrada
E33: Recebimento de Carnê | K33: Entrega de Carne
E34: OS | F34: Cliente | G34: Forma de Pgto | H34: Valor Parcela | I34: Nº Parcela | K34: OS | L34: Parcelas | M34: Valor Total
Q40: Total de OS | R40: =SUM(R6:R21) -> 0

Sheet 24
B1: ='23'!B1+1 -> 45740
B2: Fechamento Diário do Caixa
B4: Saldo Inicial | C4: 0 | E4: Vendas | K4: Despesas
B5: Vendas | C5: =SUMIF(I6:I31,">0",H6:H31) -> 3435 | E5: Nº Venda | F5: Cliente | G5: Forma de Pgto | H5: Valor Venda | I5: Entrada | K5: Descrição | L5: Tipo de Pagto | M5: Valor
B6: Entrada | C6: =C16 -> 1407 | E6: 10719 | F6: SIMONE GOMES BISPO | G6: DN | H6: 1800 | I6: 180 | R6: =IF(vend24[[#This Row],[Nº Venda]]>1,1,0) -> 1
B7: Despesas | C7: =SUM(M6:M11) -> 0 | E7: 10720 | F7: SIMONE GOMES BISPO | G7: SS | H7: 0 | I7: 0 | R7: =IF(vend24[[#This Row],[Nº Venda]]>1,1,0) -> 1
B8: Total entrada | C8: =SUM(C6:C7) -> 1407 | E8: 10721 | F8: PAULO ROBERTO DA SILVA OLIVEIRA | G8: SS | H8: 50 | I8: 0 | R8: =IF(vend24[[#This Row],[Nº Venda]]>1,1,0) -> 1
E9: 10722 | F9: GABRIELLA AMARO DOS SANTOS | G9: DN | H9: 550 | I9: 50 | R9: =IF(vend24[[#This Row],[Nº Venda]]>1,1,0) -> 1
B10: Tipos de Pagtos | E10: 10723 | F10: PAULO MACHADO VIEIRA ARAUJO | G10: GARANTIA | H10: 0 | I10: 0 | R10: =IF(vend24[[#This Row],[Nº Venda]]>1,1,0) -> 1
B11: DN | C11: =(SUMIF($G$2:$G$31,B11,$I$2:$I$31))+(SUMIF($G$35:$G$41,B11,$H$35:$H$41)) -> 565 | E11: 10724 | F11: SUELI CRISTINA DOS SANTOS | G11: DN | H11: 35 | I11: 35 | O11: =IF(C16=0,0,1) -> 1 | R11: =IF(vend24[[#This Row],[Nº Venda]]>1,1,0) -> 1
B12: CTD | C12: =(SUMIF($G$2:$G$31,B12,$I$2:$I$31))+(SUMIF($G$35:$G$41,B12,$H$35:$H$41)) -> 750 | E12: 10725 | F12: ANA CAROLINE ALVES DE SOUZA | G12: DN | H12: 550 | I12: 150 | R12: =IF(vend24[[#This Row],[Nº Venda]]>1,1,0) -> 1
B13: CTC | C13: =(SUMIF($G$2:$G$31,B13,$I$2:$I$31))+(SUMIF($G$35:$G$41,B13,$H$35:$H$41)) -> 0 | E13: 10725 | F13: ANA CAROLINE ALVES DE SOUZA | G13: CTD | H13: 0 | I13: 400 | K13: OS Entregue no Dia | R13: =IF(vend24[[#This Row],[Nº Venda]]>1,1,0) -> 1
B14: PCTC | C14: =(SUMIF($G$2:$G$31,B14,$I$2:$I$31))+(SUMIF($G$35:$G$41,B14,$H$35:$H$41)) -> 0 | E14: 10726 | F14: ANA CAROLINE ALVES DE SOUZA | G14: DN | H14: 500 | I14: 150 | K14: OS | L14: Vendedor | M14: CARNE | R14: =IF(vend24[[#This Row],[Nº Venda]]>1,1,0) -> 1
B15: PIX | C15: =(SUMIF($G$2:$G$31,B15,$I$2:$I$31))+(SUMIF($G$35:$G$41,B15,$H$35:$H$41)) -> 92 | E15: 10726 | F15: ANA CAROLINE ALVES DE SOUZA | G15: CTD | H15: 0 | I15: 350 | K15: 10577 | L15: ROGÉRIO | M15: Não | R15: =IF(vend24[[#This Row],[Nº Venda]]>1,1,0) -> 1
B16: Total | C16: =SUM(C11:C15) -> 1407 | K16: 10678 | L16: ARIANI | M16: Não | R16: =IF(vend24[[#This Row],[Nº Venda]]>1,1,0) -> 0
K17: 10690 | L17: TATY | M17: Não | R17: =IF(vend24[[#This Row],[Nº Venda]]>1,1,0) -> 0
B18: Entrega de Carne | K18: 10724 | L18: TATY | M18: Não | R18: =IF(vend24[[#This Row],[Nº Venda]]>1,1,0) -> 0
B19: =COUNT(entr_carn24[OS]) -> 0 | C19: =SUM(entr_carn24[Valor Total]) -> 0 | R19: =IF(vend24[[#This Row],[Nº Venda]]>1,1,0) -> 0
B20: Total | C20: =SUM(C19:C19) -> 0 | R20: =IF(vend24[[#This Row],[Nº Venda]]>1,1,0) -> 0
B22: Venda | C22: =C5 -> 3435
E24: Restante Entrada
E25: Nº Venda | F25: Cliente | G25: Forma de Pgto | H25: Valor Venda | I25: Entrada
E33: Recebimento de Carnê | K33: Entrega de Carne
E34: OS | F34: Cliente | G34: Forma de Pgto | H34: Valor Parcela | I34: Nº Parcela | K34: OS | L34: Parcelas | M34: Valor Total
E35: 9948 | F35: JOELSON VICENTE | G35: PIX | H35: 92 | I35: PARC. 5/6
Q40: Total de OS | R40: =SUM(R6:R21) -> 10

Sheet 25
B1: ='24'!B1+1 -> 45741
B2: Fechamento Diário do Caixa
B4: Saldo Inicial | C4: 0 | E4: Vendas | K4: Despesas
B5: Vendas | C5: =SUMIF(I6:I31,">0",H6:H31) -> 600 | E5: Nº Venda | F5: Cliente | G5: Forma de Pgto | H5: Valor Venda | I5: Entrada | K5: Descrição | L5: Tipo de Pagto | M5: Valor
B6: Entrada | C6: =C16 -> 900 | E6: 10729 | F6: CAROLINA APARECIDA ALVES | G6: CTC | H6: 600 | I6: 600 | R6: =IF(vend25[[#This Row],[Nº Venda]]>1,1,0) -> 1
B7: Despesas | C7: =SUM(M6:M11) -> 0 | E7: 10730 | F7: IRANI DE SOUZA SILA | G7: GARANTIA | R7: =IF(vend25[[#This Row],[Nº Venda]]>1,1,0) -> 1
B8: Total entrada | C8: =SUM(C6:C7) -> 900 | R8: =IF(vend25[[#This Row],[Nº Venda]]>1,1,0) -> 0
R9: =IF(vend25[[#This Row],[Nº Venda]]>1,1,0) -> 0
B10: Tipos de Pagtos | R10: =IF(vend25[[#This Row],[Nº Venda]]>1,1,0) -> 0
B11: DN | C11: =(SUMIF($G$2:$G$31,B11,$I$2:$I$31))+(SUMIF($G$35:$G$41,B11,$H$36:$H$41)) -> 0 | O11: =IF(C16=0,0,1) -> 1 | R11: =IF(vend25[[#This Row],[Nº Venda]]>1,1,0) -> 0
B12: CTD | C12: =(SUMIF($G$2:$G$31,B12,$I$2:$I$31))+(SUMIF($G$35:$G$41,B12,$H$36:$H$41)) -> 300 | R12: =IF(vend25[[#This Row],[Nº Venda]]>1,1,0) -> 0
B13: CTC | C13: =(SUMIF($G$2:$G$31,B13,$I$2:$I$31))+(SUMIF($G$35:$G$41,B13,$H$36:$H$41)) -> 600 | K13: OS Entregue no Dia | R13: =IF(vend25[[#This Row],[Nº Venda]]>1,1,0) -> 0
B14: PCTC | C14: =(SUMIF($G$2:$G$31,B14,$I$2:$I$31))+(SUMIF($G$35:$G$41,B14,$H$36:$H$41)) -> 0 | K14: OS | L14: Vendedor | M14: CARNE | R14: =IF(vend25[[#This Row],[Nº Venda]]>1,1,0) -> 0
B15: PIX | C15: =(SUMIF($G$2:$G$31,B15,$I$2:$I$31))+(SUMIF($G$35:$G$41,B15,$H$36:$H$41)) -> 0 | K15: 10672 | L15: ROGÉRIO | M15: Não | R15: =IF(vend25[[#This Row],[Nº Venda]]>1,1,0) -> 0
B16: Total | C16: =SUM(C11:C15) -> 900 | K16: 10658 | L16: ROGÉRIO | M16: Não | R16: =IF(vend25[[#This Row],[Nº Venda]]>1,1,0) -> 0
R17: =IF(vend25[[#This Row],[Nº Venda]]>1,1,0) -> 0
B18: Entrega de Carne | R18: =IF(vend25[[#This Row],[Nº Venda]]>1,1,0) -> 0
B19: =COUNT(entr_carn25[OS]) -> 0 | C19: =SUM(entr_carn25[Valor Total]) -> 0 | R19: =IF(vend25[[#This Row],[Nº Venda]]>1,1,0) -> 0
B20: Total | C20: =SUM(C19:C19) -> 0 | R20: =IF(vend25[[#This Row],[Nº Venda]]>1,1,0) -> 0
B22: Venda | C22: =C5 -> 600
E24: Restante Entrada
E25: Nº Venda | F25: Cliente | G25: Forma de Pgto | H25: Valor Venda | I25: Entrada
E26: 10672 | F26: SILVANA REJANE FERREIRA VIEIRA | G26: CTD | I26: 300
E33: Recebimento de Carnê | K33: Entrega de Carne
E34: OS | F34: Cliente | G34: Forma de Pgto | H34: Valor Parcela | I34: Nº Parcela | K34: OS | L34: Parcelas | M34: Valor Total
Q40: Total de OS | R40: =SUM(R6:R21) -> 2

Sheet 26
B1: ='25'!B1+1 -> 45742
B2: Fechamento Diário do Caixa
B4: Saldo Inicial | C4: 0 | E4: Vendas | K4: Despesas
B5: Vendas | C5: =SUMIF(I6:I31,">0",H6:H31) -> 2650 | E5: Nº Venda | F5: Cliente | G5: Forma de Pgto | H5: Valor Venda | I5: Entrada | K5: Descrição | L5: Tipo de Pagto | M5: Valor
B6: Entrada | C6: =C16 -> 1995.12 | E6: 10731 | F6: ELISANGELA NICACIO CAMILO | G6: DN | H6: 220 | I6: 220 | R6: =IF(vend26[[#This Row],[Nº Venda]]>1,1,0) -> 1
B7: Despesas | C7: =SUM(M6:M11) -> 0 | E7: 10732 | F7: JACOB FIRMINO DO NASCIMENTO | G7: CTD | H7: 800 | I7: 25 | R7: =IF(vend26[[#This Row],[Nº Venda]]>1,1,0) -> 1
B8: Total entrada | C8: =SUM(C6:C7) -> 1995.12 | E8: 10733 | F8: JACOB FIRMINO DO NASCIMENTO | G8: CTD | H8: 130 | I8: 25 | R8: =IF(vend26[[#This Row],[Nº Venda]]>1,1,0) -> 1
E9: 10734 | F9: NEIMAR PEREIRA DOS SANTOS | G9: CTC | H9: 400 | I9: 400 | R9: =IF(vend26[[#This Row],[Nº Venda]]>1,1,0) -> 1
B10: Tipos de Pagtos | E10: 10735 | F10: TASMIN MACHADO RODRIGUES | G10: CTD | H10: 50 | I10: 50 | R10: =IF(vend26[[#This Row],[Nº Venda]]>1,1,0) -> 1
B11: DN | C11: =(SUMIF($G$2:$G$31,B11,$I$2:$I$31))+(SUMIF($G$35:$G$41,B11,$H$35:$H$41)) -> 270 | E11: 10736 | F11: CARMERINDA DE SOUSA FERRAMOSCA | G11: PIX | H11: 250 | I11: 250 | O11: =IF(C16=0,0,1) -> 1 | R11: =IF(vend26[[#This Row],[Nº Venda]]>1,1,0) -> 1
B12: CTD | C12: =(SUMIF($G$2:$G$31,B12,$I$2:$I$31))+(SUMIF($G$35:$G$41,B12,$H$35:$H$41)) -> 150 | E12: 10737 | F12: MANOEL FRANCELINO DE OLIVEIRA | G12: CTC | H12: 200 | I12: 200 | R12: =IF(vend26[[#This Row],[Nº Venda]]>1,1,0) -> 1
B13: CTC | C13: =(SUMIF($G$2:$G$31,B13,$I$2:$I$31))+(SUMIF($G$35:$G$41,B13,$H$35:$H$41)) -> 1100 | E13: 10738 | F13: MANOEL FRANCELINO DE OLIVEIRA | G13: CTC | H13: 500 | I13: 500 | K13: OS Entregue no Dia | R13: =IF(vend26[[#This Row],[Nº Venda]]>1,1,0) -> 1
B14: PCTC | C14: =(SUMIF($G$2:$G$31,B14,$I$2:$I$31))+(SUMIF($G$35:$G$41,B14,$H$35:$H$41)) -> 0 | E14: 10739 | F14: NATAL APARECIDO MARTINS | G14: DN | H14: 50 | I14: 50 | K14: OS | L14: Vendedor | M14: CARNE | R14: =IF(vend26[[#This Row],[Nº Venda]]>1,1,0) -> 1
B15: PIX | C15: =(SUMIF($G$2:$G$31,B15,$I$2:$I$31))+(SUMIF($G$35:$G$41,B15,$H$35:$H$41)) -> 475.12 | K15: 10606 | L15: TATY | M15: Não | R15: =IF(vend26[[#This Row],[Nº Venda]]>1,1,0) -> 0
B16: Total | C16: =SUM(C11:C15) -> 1995.12 | K16: 10607 | L16: TATY | M16: Não | R16: =IF(vend26[[#This Row],[Nº Venda]]>1,1,0) -> 0
K17: 10683 | L17: TATY | M17: Não | R17: =IF(vend26[[#This Row],[Nº Venda]]>1,1,0) -> 0
B18: Entrega de Carne | K18: 10721 | L18: ARIANI | M18: Não | R18: =IF(vend26[[#This Row],[Nº Venda]]>1,1,0) -> 0
B19: =COUNT(entr_carn26[OS]) -> 0 | C19: =SUM(entr_carn26[Valor Total]) -> 0 | K19: 10731 | L19: TATY | M19: Não | R19: =IF(vend26[[#This Row],[Nº Venda]]>1,1,0) -> 0
B20: Total | C20: =SUM(C19:C19) -> 0 | R20: =IF(vend26[[#This Row],[Nº Venda]]>1,1,0) -> 0
B22: Venda | C22: =C5 -> 2650
E24: Restante Entrada
E25: Nº Venda | F25: Cliente | G25: Forma de Pgto | H25: Valor Venda | I25: Entrada
E26: 10721 | F26: PAULO ROBERTO DA SILVA OLIVEIRA | G26: CTD | H26: 50 | I26: 50
E33: Recebimento de Carnê | K33: Entrega de Carne
E34: OS | F34: Cliente | G34: Forma de Pgto | H34: Valor Parcela | I34: Nº Parcela | K34: OS | L34: Parcelas | M34: Valor Total
E35: 9681 | F35: quereen santos | G35: PIX | H35: 89 | I35: PARC. 5/8
E36: 10337 | F36: marta vaz | G36: PIX | H36: 136.12 | I36: PARC. 2/8
Q40: Total de OS | R40: =SUM(R6:R21) -> 9

Sheet 27
B1: ='26'!B1+1 -> 45743
B2: Fechamento Diário do Caixa
B4: Saldo Inicial | C4: 0 | E4: Vendas | K4: Despesas
B5: Vendas | C5: =SUMIF(I6:I31,">0",H6:H31) -> 0 | E5: Nº Venda | F5: Cliente | G5: Forma de Pgto | H5: Valor Venda | I5: Entrada | K5: Descrição | L5: Tipo de Pagto | M5: Valor
B6: Entrada | C6: =C16 -> 0 | E6: 10740 | F6: IVALCIR MACENA | G6: GARANTIA | H6: 0 | I6: 0 | R6: =IF(vend27[[#This Row],[Nº Venda]]>1,1,0) -> 1
B7: Despesas | C7: =SUM(M6:M11) -> 0 | E7: 10741 | F7: SOLANGE APARECIDA DOS SANRTOS | G7: GARANTIA | H7: 0 | I7: 0 | R7: =IF(vend27[[#This Row],[Nº Venda]]>1,1,0) -> 1
B8: Total entrada | C8: =SUM(C6:C7) -> 0 | R8: =IF(vend27[[#This Row],[Nº Venda]]>1,1,0) -> 0
R9: =IF(vend27[[#This Row],[Nº Venda]]>1,1,0) -> 0
B10: Tipos de Pagtos | R10: =IF(vend27[[#This Row],[Nº Venda]]>1,1,0) -> 0
B11: DN | C11: =(SUMIF($G$2:$G$31,B11,$I$2:$I$31))+(SUMIF($G$35:$G$41,B11,$H$35:$H$41)) -> 0 | O11: =IF(C16=0,0,1) -> 0 | R11: =IF(vend27[[#This Row],[Nº Venda]]>1,1,0) -> 0
B12: CTD | C12: =(SUMIF($G$2:$G$31,B12,$I$2:$I$31))+(SUMIF($G$35:$G$41,B12,$H$35:$H$41)) -> 0 | R12: =IF(vend27[[#This Row],[Nº Venda]]>1,1,0) -> 0
B13: CTC | C13: =(SUMIF($G$2:$G$31,B13,$I$2:$I$31))+(SUMIF($G$35:$G$41,B13,$H$35:$H$41)) -> 0 | K13: OS Entregue no Dia | R13: =IF(vend27[[#This Row],[Nº Venda]]>1,1,0) -> 0
B14: PCTC | C14: =(SUMIF($G$2:$G$31,B14,$I$2:$I$31))+(SUMIF($G$35:$G$41,B14,$H$35:$H$41)) -> 0 | K14: OS | L14: Vendedor | M14: CARNE | R14: =IF(vend27[[#This Row],[Nº Venda]]>1,1,0) -> 0
B15: PIX | C15: =(SUMIF($G$2:$G$31,B15,$I$2:$I$31))+(SUMIF($G$35:$G$41,B15,$H$35:$H$41)) -> 0 | K15: 10729 | L15: ARIANI | M15: Não | R15: =IF(vend27[[#This Row],[Nº Venda]]>1,1,0) -> 0
B16: Total | C16: =SUM(C11:C15) -> 0 | K16: 10674 | L16: ROGÉRIO | M16: Não | R16: =IF(vend27[[#This Row],[Nº Venda]]>1,1,0) -> 0
K17: 10739 | L17: ARIANI | M17: Não | R17: =IF(vend27[[#This Row],[Nº Venda]]>1,1,0) -> 0
B18: Entrega de Carne | R18: =IF(vend27[[#This Row],[Nº Venda]]>1,1,0) -> 0
B19: =COUNT(entr_carn27[OS]) -> 0 | C19: =SUM(entr_carn27[Valor Total]) -> 0 | R19: =IF(vend27[[#This Row],[Nº Venda]]>1,1,0) -> 0
B20: Total | C20: =SUM(C19:C19) -> 0 | R20: =IF(vend27[[#This Row],[Nº Venda]]>1,1,0) -> 0
B22: Venda | C22: =C5 -> 0
E24: Restante Entrada
E25: Nº Venda | F25: Cliente | G25: Forma de Pgto | H25: Valor Venda | I25: Entrada
E33: Recebimento de Carnê | K33: Entrega de Carne
E34: OS | F34: Cliente | G34: Forma de Pgto | H34: Valor Parcela | I34: Nº Parcela | K34: OS | L34: Parcelas | M34: Valor Total
Q40: Total de OS | R40: =SUM(R6:R21) -> 2

Sheet 28
B1: ='27'!B1+1 -> 45744
B2: Fechamento Diário do Caixa
B4: Saldo Inicial | C4: 0 | E4: Vendas | K4: Despesas
B5: Vendas | C5: =SUMIF(I6:I31,">0",H6:H31) -> 1319.8 | E5: Nº Venda | F5: Cliente | G5: Forma de Pgto | H5: Valor Venda | I5: Entrada | K5: Descrição | L5: Tipo de Pagto | M5: Valor
B6: Entrada | C6: =C16 -> 929.8 | E6: 10742 | F6: NOEMIA AVELINO DE SOUZA | G6: DN | H6: 350 | I6: 350 | R6: =IF(vend28[[#This Row],[Nº Venda]]>1,1,0) -> 1
B7: Despesas | C7: =SUM(M6:M11) -> 0 | E7: 10743 | F7: MARCIA FERREIRA DA SILVA | G7: CTC | H7: 150 | I7: 150 | R7: =IF(vend28[[#This Row],[Nº Venda]]>1,1,0) -> 1
B8: Total entrada | C8: =SUM(C6:C7) -> 929.8 | E8: 10744 | F8: LIDIA MARIA LISBOA | G8: CTD | H8: 79.8 | I8: 79.8 | R8: =IF(vend28[[#This Row],[Nº Venda]]>1,1,0) -> 1
E9: 10745 | F9: ADRIANO DE ALMEIDA CHAGAS | G9: CTD | H9: 740 | I9: 150 | R9: =IF(vend28[[#This Row],[Nº Venda]]>1,1,0) -> 1
B10: Tipos de Pagtos | E10: 10746 | F10: SIMONE MARISTELA DA SILVA | G10: GARANTIA | H10: 0 | I10: 0 | R10: =IF(vend28[[#This Row],[Nº Venda]]>1,1,0) -> 1
B11: DN | C11: =(SUMIF($G$2:$G$31,B11,$I$2:$I$31))+(SUMIF($G$35:$G$41,B11,$H$35:$H$41)) -> 550 | O11: =IF(C16=0,0,1) -> 1 | R11: =IF(vend28[[#This Row],[Nº Venda]]>1,1,0) -> 0
B12: CTD | C12: =(SUMIF($G$2:$G$31,B12,$I$2:$I$31))+(SUMIF($G$35:$G$41,B12,$H$35:$H$41)) -> 229.8 | R12: =IF(vend28[[#This Row],[Nº Venda]]>1,1,0) -> 0
B13: CTC | C13: =(SUMIF($G$2:$G$31,B13,$I$2:$I$31))+(SUMIF($G$35:$G$41,B13,$H$35:$H$41)) -> 150 | K13: OS Entregue no Dia | R13: =IF(vend28[[#This Row],[Nº Venda]]>1,1,0) -> 0
B14: PCTC | C14: =(SUMIF($G$2:$G$31,B14,$I$2:$I$31))+(SUMIF($G$35:$G$41,B14,$H$35:$H$41)) -> 0 | K14: OS | L14: Vendedor | M14: CARNE | R14: =IF(vend28[[#This Row],[Nº Venda]]>1,1,0) -> 0
B15: PIX | C15: =(SUMIF($G$2:$G$31,B15,$I$2:$I$31))+(SUMIF($G$35:$G$41,B15,$H$35:$H$41)) -> 0 | K15: 10644 | L15: ROGÉRIO | M15: Não | R15: =IF(vend28[[#This Row],[Nº Venda]]>1,1,0) -> 0
B16: Total | C16: =SUM(C11:C15) -> 929.8 | K16: 10661 | L16: TATY | M16: Não | R16: =IF(vend28[[#This Row],[Nº Venda]]>1,1,0) -> 0
K17: 10704 | L17: TATY | M17: Não | R17: =IF(vend28[[#This Row],[Nº Venda]]>1,1,0) -> 0
B18: Entrega de Carne | K18: 10725 | L18: TATY | M18: Não | R18: =IF(vend28[[#This Row],[Nº Venda]]>1,1,0) -> 0
B19: =COUNT(entr_carn28[OS]) -> 0 | C19: =SUM(entr_carn28[Valor Total]) -> 0 | K19: 10726 | L19: TATY | M19: Não | R19: =IF(vend28[[#This Row],[Nº Venda]]>1,1,0) -> 0
B20: Total | C20: =SUM(C19:C19) -> 0 | K20: 10743 | L20: TATY | M20: Não | R20: =IF(vend28[[#This Row],[Nº Venda]]>1,1,0) -> 0
K21: 10744 | L21: TATY | M21: Não
B22: Venda | C22: =C5 -> 1319.8
E24: Restante Entrada
E25: Nº Venda | F25: Cliente | G25: Forma de Pgto | H25: Valor Venda | I25: Entrada
E33: Recebimento de Carnê | K33: Entrega de Carne
E34: OS | F34: Cliente | G34: Forma de Pgto | H34: Valor Parcela | I34: Nº Parcela | K34: OS | L34: Parcelas | M34: Valor Total
E35: 9942 | F35: FATIMA APARECIDA MENEZES | G35: DN | H35: 100 | I35: PARC. 3/7
E36: 9942 | F36: FATIMA APARECIDA MENEZES | G36: DN | H36: 100 | I36: PARC. 4/7
Q40: Total de OS | R40: =SUM(R6:R21) -> 5

Sheet 29
B1: ='28'!B1+1 -> 45745
B2: Fechamento Diário do Caixa
B4: Saldo Inicial | C4: 0 | E4: Vendas | K4: Despesas
B5: Vendas | C5: =SUMIF(I6:I31,">0",H6:H31) -> 1479.8 | E5: Nº Venda | F5: Cliente | G5: Forma de Pgto | H5: Valor Venda | I5: Entrada | K5: Descrição | L5: Tipo de Pagto | M5: Valor
B6: Entrada | C6: =C16 -> 1644.3 | E6: 10747 | F6: LIDIA MARIA LISBOA | G6: CTD | H6: 79.8 | I6: 79.8 | R6: =IF(vend29[[#This Row],[Nº Venda]]>1,1,0) -> 1
B7: Despesas | C7: =SUM(M6:M11) -> 0 | E7: 10748 | F7: ROBSON RODRIGUES PEGO | G7: PIX | H7: 470 | I7: 470 | R7: =IF(vend29[[#This Row],[Nº Venda]]>1,1,0) -> 1
B8: Total entrada | C8: =SUM(C6:C7) -> 1644.3 | E8: 10749 | F8: ROBSON RODRIGUES PEGO | G8: PIX | H8: 130 | I8: 130 | R8: =IF(vend29[[#This Row],[Nº Venda]]>1,1,0) -> 1
E9: 10750 | F9: FABIO AUGUSTO LUIS ALVES COSTA | G9: PIX | H9: 800 | I9: 800 | R9: =IF(vend29[[#This Row],[Nº Venda]]>1,1,0) -> 1
B10: Tipos de Pagtos | R10: =IF(vend29[[#This Row],[Nº Venda]]>1,1,0) -> 0
B11: DN | C11: =(SUMIF($G$2:$G$31,B11,$I$2:$I$31))+(SUMIF($G$35:$G$41,B11,$H$35:$H$41)) -> 0 | O11: =IF(C16=0,0,1) -> 1 | R11: =IF(vend29[[#This Row],[Nº Venda]]>1,1,0) -> 0
B12: CTD | C12: =(SUMIF($G$2:$G$31,B12,$I$2:$I$31))+(SUMIF($G$35:$G$41,B12,$H$35:$H$41)) -> 79.8 | R12: =IF(vend29[[#This Row],[Nº Venda]]>1,1,0) -> 0
B13: CTC | C13: =(SUMIF($G$2:$G$31,B13,$I$2:$I$31))+(SUMIF($G$35:$G$41,B13,$H$35:$H$41)) -> 0 | K13: OS Entregue no Dia | R13: =IF(vend29[[#This Row],[Nº Venda]]>1,1,0) -> 0
B14: PCTC | C14: =(SUMIF($G$2:$G$31,B14,$I$2:$I$31))+(SUMIF($G$35:$G$41,B14,$H$35:$H$41)) -> 0 | K14: OS | L14: Vendedor | M14: CARNE | R14: =IF(vend29[[#This Row],[Nº Venda]]>1,1,0) -> 0
B15: PIX | C15: =(SUMIF($G$2:$G$31,B15,$I$2:$I$31))+(SUMIF($G$35:$G$41,B15,$H$35:$H$41)) -> 1564.5 | K15: 10688 | L15: TATY | M15: Não | R15: =IF(vend29[[#This Row],[Nº Venda]]>1,1,0) -> 0
B16: Total | C16: =SUM(C11:C15) -> 1644.3 | K16: 10642 | L16: ROGÉRIO | M16: Não | R16: =IF(vend29[[#This Row],[Nº Venda]]>1,1,0) -> 0
K17: 10747 | L17: TATY | M17: Não | R17: =IF(vend29[[#This Row],[Nº Venda]]>1,1,0) -> 0
B18: Entrega de Carne | R18: =IF(vend29[[#This Row],[Nº Venda]]>1,1,0) -> 0
B19: =COUNT(entr_carn29[OS]) -> 0 | C19: =SUM(entr_carn29[Valor Total]) -> 0 | R19: =IF(vend29[[#This Row],[Nº Venda]]>1,1,0) -> 0
B20: Total | C20: =SUM(C19:C19) -> 0 | R20: =IF(vend29[[#This Row],[Nº Venda]]>1,1,0) -> 0
B22: Venda | C22: =C5 -> 1479.8
E24: Restante Entrada
E25: Nº Venda | F25: Cliente | G25: Forma de Pgto | H25: Valor Venda | I25: Entrada
E33: Recebimento de Carnê | K33: Entrega de Carne
E34: OS | F34: Cliente | G34: Forma de Pgto | H34: Valor Parcela | I34: Nº Parcela | K34: OS | L34: Parcelas | M34: Valor Total
E35: 9845 | F35: DEISYANE DE CASTRO | G35: PIX | H35: 72.5 | I35: PARC. 6/8
E36: 9800 | F36: SUELI RIBEIRO | G36: PIX | H36: 92 | I36: PARC. 6/6
Q40: Total de OS | R40: =SUM(R6:R21) -> 4

Sheet 30
B1: ='29'!B1+1 -> 45746
B2: Fechamento Diário do Caixa
B4: Saldo Inicial | C4: 0 | E4: Vendas | K4: Despesas
B5: Vendas | C5: =SUMIF(I6:I31,">0",H6:H31) -> 0 | E5: Nº Venda | F5: Cliente | G5: Forma de Pgto | H5: Valor Venda | I5: Entrada | K5: Descrição | L5: Tipo de Pagto | M5: Valor
B6: Entrada | C6: =C16 -> 0 | R6: =IF(vend30[[#This Row],[Nº Venda]]>1,1,0) -> 0
B7: Despesas | C7: =SUM(M6:M11) -> 0 | R7: =IF(vend30[[#This Row],[Nº Venda]]>1,1,0) -> 0
B8: Total entrada | C8: =SUM(C6:C7) -> 0 | R8: =IF(vend30[[#This Row],[Nº Venda]]>1,1,0) -> 0
R9: =IF(vend30[[#This Row],[Nº Venda]]>1,1,0) -> 0
B10: Tipos de Pagtos | R10: =IF(vend30[[#This Row],[Nº Venda]]>1,1,0) -> 0
B11: DN | C11: =(SUMIF($G$2:$G$31,B11,$I$2:$I$31))+(SUMIF($G$35:$G$41,B11,$H$35:$H$41)) -> 0 | O11: =IF(C16=0,0,1) -> 0 | R11: =IF(vend30[[#This Row],[Nº Venda]]>1,1,0) -> 0
B12: CTD | C12: =(SUMIF($G$2:$G$31,B12,$I$2:$I$31))+(SUMIF($G$35:$G$41,B12,$H$35:$H$41)) -> 0 | R12: =IF(vend30[[#This Row],[Nº Venda]]>1,1,0) -> 0
B13: CTC | C13: =(SUMIF($G$2:$G$31,B13,$I$2:$I$31))+(SUMIF($G$35:$G$41,B13,$H$35:$H$41)) -> 0 | K13: OS Entregue no Dia | R13: =IF(vend30[[#This Row],[Nº Venda]]>1,1,0) -> 0
B14: PCTC | C14: =(SUMIF($G$2:$G$31,B14,$I$2:$I$31))+(SUMIF($G$35:$G$41,B14,$H$35:$H$41)) -> 0 | K14: OS | L14: Vendedor | M14: CARNE | R14: =IF(vend30[[#This Row],[Nº Venda]]>1,1,0) -> 0
B15: PIX | C15: =(SUMIF($G$2:$G$31,B15,$I$2:$I$31))+(SUMIF($G$35:$G$41,B15,$H$35:$H$41)) -> 0 | R15: =IF(vend30[[#This Row],[Nº Venda]]>1,1,0) -> 0
B16: Total | C16: =SUM(C11:C15) -> 0 | R16: =IF(vend30[[#This Row],[Nº Venda]]>1,1,0) -> 0
R17: =IF(vend30[[#This Row],[Nº Venda]]>1,1,0) -> 0
B18: Entrega de Carne | R18: =IF(vend30[[#This Row],[Nº Venda]]>1,1,0) -> 0
B19: =COUNT(entr_carn30[OS]) -> 0 | C19: =SUM(entr_carn30[Valor Total]) -> 0 | R19: =IF(vend30[[#This Row],[Nº Venda]]>1,1,0) -> 0
B20: Total | C20: =SUM(C19:C19) -> 0 | R20: =IF(vend30[[#This Row],[Nº Venda]]>1,1,0) -> 0
B22: Venda | C22: =C5 -> 0
E24: Restante Entrada
E25: Nº Venda | F25: Cliente | G25: Forma de Pgto | H25: Valor Venda | I25: Entrada
E33: Recebimento de Carnê | K33: Entrega de Carne
E34: OS | F34: Cliente | G34: Forma de Pgto | H34: Valor Parcela | I34: Nº Parcela | K34: OS | L34: Parcelas | M34: Valor Total
Q40: Total de OS | R40: =SUM(R6:R21) -> 0

Sheet 31
B1: ='30'!B1+1 -> 45747
B2: Fechamento Diário do Caixa
B4: Saldo Inicial | C4: 0 | E4: Vendas | K4: Despesas
B5: Vendas | C5: =SUMIF(I6:I31,">0",H6:H31) -> 0 | E5: Nº Venda | F5: Cliente | G5: Forma de Pgto | H5: Valor Venda | I5: Entrada | K5: Descrição | L5: Tipo de Pagto | M5: Valor
B6: Entrada | C6: =C16 -> 1080.5 | E6: 10752 | F6: GILVANILSON JACINTO DO NASCIMENTO | G6: GARANTIA | H6: 0 | I6: 0 | R6: =IF(vend31[[#This Row],[Nº Venda]]>1,1,0) -> 1
B7: Despesas | C7: =SUM(M6:M11) -> 0 | E7: 10753 | F7: LEONARDO BELMONTE DE PAULA | G7: GARANTIA | H7: 0 | I7: 0 | R7: =IF(vend31[[#This Row],[Nº Venda]]>1,1,0) -> 1
B8: Total entrada | C8: =SUM(C6:C7) -> 1080.5 | E8: 10754 | F8: ADRIANO RODRIGUES COSTA | G8: SS | H8: 3899 | I8: 0 | R8: =IF(vend31[[#This Row],[Nº Venda]]>1,1,0) -> 1
E9: 10755 | F9: ADRIANO RODRIGUES COSTA | G9: SS | H9: 0 | I9: 0 | R9: =IF(vend31[[#This Row],[Nº Venda]]>1,1,0) -> 1
B10: Tipos de Pagtos | R10: =IF(vend31[[#This Row],[Nº Venda]]>1,1,0) -> 0
B11: DN | C11: =(SUMIF($G$2:$G$31,B11,$I$2:$I$31))+(SUMIF($G$35:$G$41,B11,$H$35:$H$41)) -> 165.5 | O11: =IF(C16=0,0,1) -> 1 | R11: =IF(vend31[[#This Row],[Nº Venda]]>1,1,0) -> 0
B12: CTD | C12: =(SUMIF($G$2:$G$31,B12,$I$2:$I$31))+(SUMIF($G$35:$G$41,B12,$H$35:$H$41)) -> 0 | R12: =IF(vend31[[#This Row],[Nº Venda]]>1,1,0) -> 0
B13: CTC | C13: =(SUMIF($G$2:$G$31,B13,$I$2:$I$31))+(SUMIF($G$35:$G$41,B13,$H$35:$H$41)) -> 915 | K13: OS Entregue no Dia | R13: =IF(vend31[[#This Row],[Nº Venda]]>1,1,0) -> 0
B14: PCTC | C14: =(SUMIF($G$2:$G$31,B14,$I$2:$I$31))+(SUMIF($G$35:$G$41,B14,$H$35:$H$41)) -> 0 | K14: OS | L14: Vendedor | M14: CARNE | R14: =IF(vend31[[#This Row],[Nº Venda]]>1,1,0) -> 0
B15: PIX | C15: =(SUMIF($G$2:$G$31,B15,$I$2:$I$31))+(SUMIF($G$35:$G$41,B15,$H$35:$H$41)) -> 0 | K15: 10649 | L15: TATY | M15: Não | R15: =IF(vend31[[#This Row],[Nº Venda]]>1,1,0) -> 0
B16: Total | C16: =SUM(C11:C15) -> 1080.5 | K16: 10679 | L16: ARIANI | M16: Não | R16: =IF(vend31[[#This Row],[Nº Venda]]>1,1,0) -> 0
K17: 10685 | L17: ROGÉRIO | M17: Não | R17: =IF(vend31[[#This Row],[Nº Venda]]>1,1,0) -> 0
B18: Entrega de Carne | K18: 10689 | L18: TATY | M18: Não | R18: =IF(vend31[[#This Row],[Nº Venda]]>1,1,0) -> 0
B19: =COUNT(entr_carn31[OS]) -> 0 | C19: =SUM(entr_carn31[Valor Total]) -> 0 | K19: 10707 | L19: TATY | M19: Não | R19: =IF(vend31[[#This Row],[Nº Venda]]>1,1,0) -> 0
B20: Total | C20: =SUM(C19:C19) -> 0 | K20: 10710 | L20: TATY | M20: Não | R20: =IF(vend31[[#This Row],[Nº Venda]]>1,1,0) -> 0
K21: 10740 | L21: ARIANI | M21: Não
B22: Venda | C22: =C5 -> 0
E24: Restante Entrada
E25: Nº Venda | F25: Cliente | G25: Forma de Pgto | H25: Valor Venda | I25: Entrada
E26: 10649 | F26: PRISCILA PAULINO BRESSIANI VICENTI | G26: CTC | H26: 0 | I26: 370
E27: 10679 | F27: NICOLE PAULINO DOS SANTOS | G27: CTC | H27: 0 | I27: 545
E33: Recebimento de Carnê | K33: Entrega de Carne
E34: OS | F34: Cliente | G34: Forma de Pgto | H34: Valor Parcela | I34: Nº Parcela | K34: OS | L34: Parcelas | M34: Valor Total
E35: 10336 | F35: SIMONE IGNACIO | G35: DN | H35: 114 | I35: PARC. 2/7
E36: 10620 | F36: VALQUIRIA BATISTA FERNANDES | G36: DN | H36: 51.5 | I36: PARC. 1/6
Q40: Total de OS | R40: =SUM(R6:R21) -> 4

Sheet base_OS
A1: OSs Mauá
A2: 190
A3: 191
A4: 192
A5: 193
A6: 194
A7: 195
A8: 196
A9: 197
A10: 198
A11: 199
A12: 200
A13: 201
... A13000: 13188

Sheet base
A1: Tipo Pagto | B1: descricao | E1: Parcelas
A2: DN | B2: Dinheiro | E2: PARC. 1/1
A3: CTD | B3: Cartão Débito | E3: PARC. 1/2
A4: CTC | B4: Cartão Crédito | E4: PARC. 2/2
A5: PCTC | B5: Parcelado Cartão Crédito | E5: PARC. 1/3
A6: PIX | B6: PIX | E6: PARC. 2/3
A7: SS | B7: Sem Sinal | E7: PARC. 3/3
A8: CARNE | B8: Carne | E8: PARC. 1/4
A9: GARANTIA | B9: Todas as Garantias | E9: PARC. 2/4
E10: PARC. 3/4
E11: PARC. 4/4
E12: PARC. 1/5
E13: PARC. 2/5
E14: PARC. 3/5
E15: PARC. 4/5
E16: PARC. 5/5
E17: PARC. 1/6
E18: PARC. 2/6
E19: PARC. 3/6
E20: PARC. 4/6
E21: PARC. 5/6
... E79: PARC. 12/12
